kotlin version: 2.1.10
error message: org.jetbrains.kotlin.codegen.CompilationException: Back-end (JVM) Internal error: Couldn't transform method node:
ChannelScreenUI (Ljava/util/List;Ljava/lang/String;Lkotlin/jvm/functions/Function1;Ljava/lang/String;Lkotlin/jvm/functions/Function0;Landroidx/compose/runtime/Composer;I)V:
  @Landroidx/compose/runtime/Composable;() // invisible
  @Landroidx/compose/runtime/ComposableTarget;(applier="androidx.compose.ui.UiComposable") // invisible
    // annotable parameter count: 7 (visible)
    // annotable parameter count: 7 (invisible)
   L0
    LINENUMBER 70 L0
    ALOAD 5
    LDC -1620639389
    INVOKEINTERFACE androidx/compose/runtime/Composer.startRestartGroup (I)Landroidx/compose/runtime/Composer; (itf)
    ASTORE 5
    ALOAD 5
    LDC "C(ChannelScreenUI)P(4,3,2)71@2468L46,72@2531L31,74@2568L7969:ChannelScreen.kt#dnwu2"
    INVOKESTATIC androidx/compose/runtime/ComposerKt.sourceInformation (Landroidx/compose/runtime/Composer;Ljava/lang/String;)V
    ILOAD 6
    ISTORE 7
   L1
    ILOAD 6
    BIPUSH 6
    IAND
    IFNE L2
    ILOAD 7
    ALOAD 5
    ALOAD 0
    INVOKEINTERFACE androidx/compose/runtime/Composer.changedInstance (Ljava/lang/Object;)Z (itf)
    IFEQ L3
    ICONST_4
    GOTO L4
   L3
    ICONST_2
   L4
    IOR
    ISTORE 7
   L2
    ILOAD 6
    BIPUSH 48
    IAND
    IFNE L5
    ILOAD 7
    ALOAD 5
    ALOAD 1
    INVOKEINTERFACE androidx/compose/runtime/Composer.changed (Ljava/lang/Object;)Z (itf)
    IFEQ L6
    BIPUSH 32
    GOTO L7
   L6
    BIPUSH 16
   L7
    IOR
    ISTORE 7
   L5
    ILOAD 6
    SIPUSH 384
    IAND
    IFNE L8
    ILOAD 7
    ALOAD 5
    ALOAD 2
    INVOKEINTERFACE androidx/compose/runtime/Composer.changedInstance (Ljava/lang/Object;)Z (itf)
    IFEQ L9
    SIPUSH 256
    GOTO L10
   L9
    SIPUSH 128
   L10
    IOR
    ISTORE 7
   L8
    ILOAD 6
    SIPUSH 3072
    IAND
    IFNE L11
    ILOAD 7
    ALOAD 5
    ALOAD 3
    INVOKEINTERFACE androidx/compose/runtime/Composer.changed (Ljava/lang/Object;)Z (itf)
    IFEQ L12
    SIPUSH 2048
    GOTO L13
   L12
    SIPUSH 1024
   L13
    IOR
    ISTORE 7
   L11
    ILOAD 6
    SIPUSH 24576
    IAND
    IFNE L14
    ILOAD 7
    ALOAD 5
    ALOAD 4
    INVOKEINTERFACE androidx/compose/runtime/Composer.changedInstance (Ljava/lang/Object;)Z (itf)
    IFEQ L15
    SIPUSH 16384
    GOTO L16
   L15
    SIPUSH 8192
   L16
    IOR
    ISTORE 7
   L14
    ILOAD 7
    SIPUSH 9363
    IAND
    SIPUSH 9362
    IF_ICMPNE L17
    ALOAD 5
    INVOKEINTERFACE androidx/compose/runtime/Composer.getSkipping ()Z (itf)
    IFNE L18
   L17
    INVOKESTATIC androidx/compose/runtime/ComposerKt.isTraceInProgress ()Z
    IFEQ L19
    LDC -1620639389
    ILOAD 7
    ICONST_M1
    LDC "capstone.safeline.ui.ChannelScreenUI (ChannelScreen.kt:69)"
    INVOKESTATIC androidx/compose/runtime/ComposerKt.traceEventStart (IIILjava/lang/String;)V
   L19
    ALOAD 5
    LDC 433422089
    INVOKEINTERFACE androidx/compose/runtime/Composer.startReplaceGroup (I)V (itf)
    ALOAD 5
    LDC "CC(remember):ChannelScreen.kt#9igjgp"
    INVOKESTATIC androidx/compose/runtime/ComposerKt.sourceInformation (Landroidx/compose/runtime/Composer;Ljava/lang/String;)V
    ALOAD 5
    ASTORE 10
    NOP
    ICONST_0
    ISTORE 11
   L20
    LINENUMBER 72 L20
    NOP
   L21
    ICONST_0
    ISTORE 12
   L22
    LINENUMBER 271 L22
    ALOAD 10
    INVOKEINTERFACE androidx/compose/runtime/Composer.rememberedValue ()Ljava/lang/Object; (itf)
    ASTORE 13
   L23
    ICONST_0
    ISTORE 14
   L24
    LINENUMBER 272 L24
    ILOAD 11
    IFNE L25
    ALOAD 13
    GETSTATIC androidx/compose/runtime/Composer.Companion : Landroidx/compose/runtime/Composer$Companion;
    INVOKEVIRTUAL androidx/compose/runtime/Composer$Companion.getEmpty ()Ljava/lang/Object;
    IF_ACMPNE L26
   L25
    LINENUMBER 273 L25
    NOP
    INVOKESTATIC kotlin/jvm/internal/InlineMarker.beforeInlineCall ()V
   L27
    ICONST_0
    ISTORE 15
   L28
    LINENUMBER 72 L28
    NOP
    INVOKESTATIC kotlin/collections/CollectionsKt.emptyList ()Ljava/util/List;
    GOTO L29
   L29
    LINENUMBER 72 L29
    ACONST_NULL
    ICONST_2
    ACONST_NULL
    INVOKESTATIC androidx/compose/runtime/SnapshotStateKt.mutableStateOf$default (Ljava/lang/Object;Landroidx/compose/runtime/SnapshotMutationPolicy;ILjava/lang/Object;)Landroidx/compose/runtime/MutableState;
    NOP
    GOTO L30
   L30
    INVOKESTATIC kotlin/jvm/internal/InlineMarker.afterInlineCall ()V
   L31
    LINENUMBER 273 L31
    ASTORE 15
   L32
    LINENUMBER 274 L32
    ALOAD 10
    ALOAD 15
    INVOKEINTERFACE androidx/compose/runtime/Composer.updateRememberedValue (Ljava/lang/Object;)V (itf)
   L33
    LINENUMBER 275 L33
    ALOAD 15
   L34
    GOTO L35
   L26
    LINENUMBER 276 L26
    ALOAD 13
   L35
    LINENUMBER 271 L35
    NOP
   L36
    LINENUMBER 271 L36
    NOP
    GOTO L37
   L37
    LINENUMBER 72 L37
    CHECKCAST androidx/compose/runtime/MutableState
    ASTORE 9
   L38
    ALOAD 5
    INVOKEINTERFACE androidx/compose/runtime/Composer.endReplaceGroup ()V (itf)
    ALOAD 9
   L39
    ASTORE 8
   L40
    ALOAD 5
    LDC 433424090
    INVOKEINTERFACE androidx/compose/runtime/Composer.startReplaceGroup (I)V (itf)
    ALOAD 5
    LDC "CC(remember):ChannelScreen.kt#9igjgp"
    INVOKESTATIC androidx/compose/runtime/ComposerKt.sourceInformation (Landroidx/compose/runtime/Composer;Ljava/lang/String;)V
    ALOAD 5
    ASTORE 11
    NOP
    ICONST_0
    ISTORE 12
   L41
    LINENUMBER 73 L41
    NOP
   L42
    ICONST_0
    ISTORE 13
   L43
    LINENUMBER 277 L43
    ALOAD 11
    INVOKEINTERFACE androidx/compose/runtime/Composer.rememberedValue ()Ljava/lang/Object; (itf)
    ASTORE 14
   L44
    ICONST_0
    ISTORE 15
   L45
    LINENUMBER 278 L45
    ILOAD 12
    IFNE L46
    ALOAD 14
    GETSTATIC androidx/compose/runtime/Composer.Companion : Landroidx/compose/runtime/Composer$Companion;
    INVOKEVIRTUAL androidx/compose/runtime/Composer$Companion.getEmpty ()Ljava/lang/Object;
    IF_ACMPNE L47
   L46
    LINENUMBER 279 L46
    NOP
    INVOKESTATIC kotlin/jvm/internal/InlineMarker.beforeInlineCall ()V
   L48
    ICONST_0
    ISTORE 16
   L49
    LINENUMBER 73 L49
    LDC ""
    ACONST_NULL
    ICONST_2
    ACONST_NULL
    INVOKESTATIC androidx/compose/runtime/SnapshotStateKt.mutableStateOf$default (Ljava/lang/Object;Landroidx/compose/runtime/SnapshotMutationPolicy;ILjava/lang/Object;)Landroidx/compose/runtime/MutableState;
    NOP
    GOTO L50
   L50
    INVOKESTATIC kotlin/jvm/internal/InlineMarker.afterInlineCall ()V
   L51
    LINENUMBER 279 L51
    ASTORE 16
   L52
    LINENUMBER 280 L52
    ALOAD 11
    ALOAD 16
    INVOKEINTERFACE androidx/compose/runtime/Composer.updateRememberedValue (Ljava/lang/Object;)V (itf)
   L53
    LINENUMBER 281 L53
    ALOAD 16
   L54
    GOTO L55
   L47
    LINENUMBER 282 L47
    ALOAD 14
   L55
    LINENUMBER 277 L55
    NOP
   L56
    LINENUMBER 277 L56
    NOP
    GOTO L57
   L57
    LINENUMBER 73 L57
    CHECKCAST androidx/compose/runtime/MutableState
    ASTORE 10
   L58
    ALOAD 5
    INVOKEINTERFACE androidx/compose/runtime/Composer.endReplaceGroup ()V (itf)
    ALOAD 10
   L59
    ASTORE 9
   L60
    LINENUMBER 75 L60
    GETSTATIC androidx/compose/ui/Modifier.Companion : Landroidx/compose/ui/Modifier$Companion;
    CHECKCAST androidx/compose/ui/Modifier
    FCONST_0
    ICONST_1
    ACONST_NULL
    INVOKESTATIC androidx/compose/foundation/layout/SizeKt.fillMaxSize$default (Landroidx/compose/ui/Modifier;FILjava/lang/Object;)Landroidx/compose/ui/Modifier;
    ASTORE 10
    BIPUSH 6
    ISTORE 13
    NOP
   L61
    ICONST_0
    ISTORE 14
   L62
    ALOAD 5
    LDC 1042775818
    LDC "CC(Box)N(modifier,contentAlignment,propagateMinConstraints,content)71@3424L131:Box.kt#2w3rfo"
   L63
    LINENUMBER 283 L63
    INVOKESTATIC androidx/compose/runtime/ComposerKt.sourceInformationMarkerStart (Landroidx/compose/runtime/Composer;ILjava/lang/String;)V
   L64
    LINENUMBER 284 L64
    GETSTATIC androidx/compose/ui/Alignment.Companion : Landroidx/compose/ui/Alignment$Companion;
    INVOKEVIRTUAL androidx/compose/ui/Alignment$Companion.getTopStart ()Landroidx/compose/ui/Alignment;
    ASTORE 11
   L65
    LINENUMBER 285 L65
    ICONST_0
    ISTORE 12
   L66
    LINENUMBER 288 L66
    ALOAD 11
    ILOAD 12
    INVOKESTATIC androidx/compose/foundation/layout/BoxKt.maybeCachedBoxMeasurePolicy (Landroidx/compose/ui/Alignment;Z)Landroidx/compose/ui/layout/MeasurePolicy;
    ASTORE 15
   L67
    LINENUMBER 292 L67
    ALOAD 10
    ASTORE 16
   L68
    LINENUMBER 291 L68
    ALOAD 15
    ASTORE 17
    ALOAD 5
    ASTORE 18
    BIPUSH 112
    ILOAD 13
    ICONST_3
    ISHL
    IAND
    ISTORE 19
   L69
    LINENUMBER 289 L69
    NOP
   L70
    ICONST_0
    ISTORE 20
   L71
    ALOAD 18
    LDC -1159599143
    LDC "CC(Layout)P(!1,2)81@3355L27,84@3521L416:Layout.kt#80mrfh"
   L72
    LINENUMBER 293 L72
    INVOKESTATIC androidx/compose/runtime/ComposerKt.sourceInformationMarkerStart (Landroidx/compose/runtime/Composer;ILjava/lang/String;)V
   L73
    LINENUMBER 294 L73
    ALOAD 18
    ICONST_0
    INVOKESTATIC androidx/compose/runtime/ComposablesKt.getCurrentCompositeKeyHashCode (Landroidx/compose/runtime/Composer;I)J
    INVOKESTATIC java/lang/Long.hashCode (J)I
    ISTORE 21
   L74
    ALOAD 18
   L75
    LINENUMBER 295 L75
    INVOKEINTERFACE androidx/compose/runtime/Composer.getCurrentCompositionLocalMap ()Landroidx/compose/runtime/CompositionLocalMap; (itf)
    ASTORE 22
   L76
    ALOAD 18
   L77
    LINENUMBER 296 L77
    ALOAD 16
    INVOKESTATIC androidx/compose/ui/ComposedModifierKt.materializeModifier (Landroidx/compose/runtime/Composer;Landroidx/compose/ui/Modifier;)Landroidx/compose/ui/Modifier;
    ASTORE 23
   L78
    LINENUMBER 298 L78
    GETSTATIC androidx/compose/ui/node/ComposeUiNode.Companion : Landroidx/compose/ui/node/ComposeUiNode$Companion;
    INVOKEVIRTUAL androidx/compose/ui/node/ComposeUiNode$Companion.getConstructor ()Lkotlin/jvm/functions/Function0;
    ASTORE 24
    ALOAD 18
    ASTORE 25
    BIPUSH 6
    SIPUSH 896
    ILOAD 19
    BIPUSH 6
    ISHL
    IAND
    IOR
    ISTORE 26
   L79
    LINENUMBER 297 L79
    NOP
   L80
    ICONST_0
    ISTORE 27
   L81
    ALOAD 25
    LDC -553112988
    LDC "CC(ReusableComposeNode)N(factory,update,content)399@15590L9:Composables.kt#9igjgp"
   L82
    LINENUMBER 299 L82
    INVOKESTATIC androidx/compose/runtime/ComposerKt.sourceInformationMarkerStart (Landroidx/compose/runtime/Composer;ILjava/lang/String;)V
   L83
    LINENUMBER 300 L83
    ALOAD 25
    INVOKEINTERFACE androidx/compose/runtime/Composer.getApplier ()Landroidx/compose/runtime/Applier; (itf)
    INSTANCEOF androidx/compose/runtime/Applier
    IFNE L84
    INVOKESTATIC androidx/compose/runtime/ComposablesKt.invalidApplier ()V
   L84
    ALOAD 25
   L85
    LINENUMBER 301 L85
    INVOKEINTERFACE androidx/compose/runtime/Composer.startReusableNode ()V (itf)
   L86
    LINENUMBER 302 L86
    ALOAD 25
    INVOKEINTERFACE androidx/compose/runtime/Composer.getInserting ()Z (itf)
    IFEQ L87
    ALOAD 25
   L88
    LINENUMBER 303 L88
    ALOAD 24
    INVOKEINTERFACE androidx/compose/runtime/Composer.createNode (Lkotlin/jvm/functions/Function0;)V (itf)
    GOTO L89
   L87
    ALOAD 25
   L90
    LINENUMBER 305 L90
    INVOKEINTERFACE androidx/compose/runtime/Composer.useNode ()V (itf)
   L89
    LINENUMBER 307 L89
    ALOAD 25
    INVOKESTATIC androidx/compose/runtime/Updater.constructor-impl (Landroidx/compose/runtime/Composer;)Landroidx/compose/runtime/Composer;
    ASTORE 28
   L91
    ICONST_0
    ISTORE 29
   L92
    LINENUMBER 308 L92
    ALOAD 28
    ALOAD 17
    GETSTATIC androidx/compose/ui/node/ComposeUiNode.Companion : Landroidx/compose/ui/node/ComposeUiNode$Companion;
    INVOKEVIRTUAL androidx/compose/ui/node/ComposeUiNode$Companion.getSetMeasurePolicy ()Lkotlin/jvm/functions/Function2;
    INVOKESTATIC androidx/compose/runtime/Updater.set-impl (Landroidx/compose/runtime/Composer;Ljava/lang/Object;Lkotlin/jvm/functions/Function2;)V
   L93
    LINENUMBER 309 L93
    ALOAD 28
    ALOAD 22
    GETSTATIC androidx/compose/ui/node/ComposeUiNode.Companion : Landroidx/compose/ui/node/ComposeUiNode$Companion;
    INVOKEVIRTUAL androidx/compose/ui/node/ComposeUiNode$Companion.getSetResolvedCompositionLocals ()Lkotlin/jvm/functions/Function2;
    INVOKESTATIC androidx/compose/runtime/Updater.set-impl (Landroidx/compose/runtime/Composer;Ljava/lang/Object;Lkotlin/jvm/functions/Function2;)V
   L94
    LINENUMBER 310 L94
    ALOAD 28
    ILOAD 21
    INVOKESTATIC java/lang/Integer.valueOf (I)Ljava/lang/Integer;
    GETSTATIC androidx/compose/ui/node/ComposeUiNode.Companion : Landroidx/compose/ui/node/ComposeUiNode$Companion;
    INVOKEVIRTUAL androidx/compose/ui/node/ComposeUiNode$Companion.getSetCompositeKeyHash ()Lkotlin/jvm/functions/Function2;
    INVOKESTATIC androidx/compose/runtime/Updater.init-impl (Landroidx/compose/runtime/Composer;Ljava/lang/Object;Lkotlin/jvm/functions/Function2;)V
   L95
    LINENUMBER 311 L95
    ALOAD 28
    GETSTATIC androidx/compose/ui/node/ComposeUiNode.Companion : Landroidx/compose/ui/node/ComposeUiNode$Companion;
    INVOKEVIRTUAL androidx/compose/ui/node/ComposeUiNode$Companion.getApplyOnDeactivatedNodeAssertion ()Lkotlin/jvm/functions/Function1;
    INVOKESTATIC androidx/compose/runtime/Updater.reconcile-impl (Landroidx/compose/runtime/Composer;Lkotlin/jvm/functions/Function1;)V
   L96
    LINENUMBER 312 L96
    ALOAD 28
    ALOAD 23
    GETSTATIC androidx/compose/ui/node/ComposeUiNode.Companion : Landroidx/compose/ui/node/ComposeUiNode$Companion;
    INVOKEVIRTUAL androidx/compose/ui/node/ComposeUiNode$Companion.getSetModifier ()Lkotlin/jvm/functions/Function2;
    INVOKESTATIC androidx/compose/runtime/Updater.set-impl (Landroidx/compose/runtime/Composer;Ljava/lang/Object;Lkotlin/jvm/functions/Function2;)V
   L97
    LINENUMBER 313 L97
    NOP
   L98
    LINENUMBER 307 L98
    NOP
   L99
    LINENUMBER 314 L99
    ALOAD 25
    BIPUSH 14
    ILOAD 26
    BIPUSH 6
    ISHR
    IAND
    ISTORE 30
    ASTORE 31
   L100
    ICONST_0
    ISTORE 32
   L101
    ALOAD 31
    LDC 1833054614
    LDC "C72@3469L9:Box.kt#2w3rfo"
   L102
    LINENUMBER 290 L102
    INVOKESTATIC androidx/compose/runtime/ComposerKt.sourceInformationMarkerStart (Landroidx/compose/runtime/Composer;ILjava/lang/String;)V
    GETSTATIC androidx/compose/foundation/layout/BoxScopeInstance.INSTANCE : Landroidx/compose/foundation/layout/BoxScopeInstance;
    ALOAD 31
    BIPUSH 6
    BIPUSH 112
    ILOAD 13
    BIPUSH 6
    ISHR
    IAND
    IOR
    INVOKESTATIC java/lang/Integer.valueOf (I)Ljava/lang/Integer;
    CHECKCAST java/lang/Number
    INVOKEVIRTUAL java/lang/Number.intValue ()I
    ISTORE 33
    CHECKCAST androidx/compose/runtime/Composer
    ASTORE 34
    CHECKCAST androidx/compose/foundation/layout/BoxScope
    ASTORE 35
    INVOKESTATIC kotlin/jvm/internal/InlineMarker.beforeInlineCall ()V
   L103
    ICONST_0
    ISTORE 36
   L104
    ALOAD 34
    LDC 1010105952
    LDC "C95@3260L7152,264@10422L109:ChannelScreen.kt#dnwu2"
   L105
    LINENUMBER 77 L105
    INVOKESTATIC androidx/compose/runtime/ComposerKt.sourceInformationMarkerStart (Landroidx/compose/runtime/Composer;ILjava/lang/String;)V
    GETSTATIC capstone/safeline/ui/theme/ThemeManager.INSTANCE : Lcapstone/safeline/ui/theme/ThemeManager;
    INVOKEVIRTUAL capstone/safeline/ui/theme/ThemeManager.getCurrentTheme ()Lcapstone/safeline/ui/theme/ThemeManager$Theme;
    GETSTATIC capstone/safeline/ui/theme/ThemeManager$Theme.CLASSIC : Lcapstone/safeline/ui/theme/ThemeManager$Theme;
    IF_ACMPNE L106
    ALOAD 34
    LDC 1009929313
    INVOKEINTERFACE androidx/compose/runtime/Composer.startReplaceGroup (I)V (itf)
    ALOAD 34
    LDC "78@2726L48,77@2693L239"
    INVOKESTATIC androidx/compose/runtime/ComposerKt.sourceInformation (Landroidx/compose/runtime/Composer;Ljava/lang/String;)V
   L107
    LINENUMBER 79 L107
    GETSTATIC capstone/safeline/R$drawable.community_servers_bg : I
    ALOAD 34
    ICONST_0
    INVOKESTATIC androidx/compose/ui/res/PainterResources_androidKt.painterResource (ILandroidx/compose/runtime/Composer;I)Landroidx/compose/ui/graphics/painter/Painter;
   L108
    LINENUMBER 80 L108
    ACONST_NULL
   L109
    LINENUMBER 81 L109
    GETSTATIC androidx/compose/ui/Modifier.Companion : Landroidx/compose/ui/Modifier$Companion;
    CHECKCAST androidx/compose/ui/Modifier
    FCONST_0
    ICONST_1
    ACONST_NULL
    INVOKESTATIC androidx/compose/foundation/layout/SizeKt.fillMaxSize$default (Landroidx/compose/ui/Modifier;FILjava/lang/Object;)Landroidx/compose/ui/Modifier;
    ACONST_NULL
   L110
    LINENUMBER 82 L110
    GETSTATIC androidx/compose/ui/layout/ContentScale.Companion : Landroidx/compose/ui/layout/ContentScale$Companion;
    INVOKEVIRTUAL androidx/compose/ui/layout/ContentScale$Companion.getCrop ()Landroidx/compose/ui/layout/ContentScale;
    FCONST_0
    ACONST_NULL
    ALOAD 34
    SIPUSH 25008
    GETSTATIC androidx/compose/ui/graphics/painter/Painter.$stable : I
    IOR
    BIPUSH 104
   L111
    LINENUMBER 78 L111
    INVOKESTATIC androidx/compose/foundation/ImageKt.Image (Landroidx/compose/ui/graphics/painter/Painter;Ljava/lang/String;Landroidx/compose/ui/Modifier;Landroidx/compose/ui/Alignment;Landroidx/compose/ui/layout/ContentScale;FLandroidx/compose/ui/graphics/ColorFilter;Landroidx/compose/runtime/Composer;II)V
   L112
    LINENUMBER 77 L112
    ALOAD 34
    INVOKEINTERFACE androidx/compose/runtime/Composer.endReplaceGroup ()V (itf)
    GOTO L113
   L106
    LINENUMBER 84 L106
    ALOAD 34
    LDC 1010197370
    INVOKEINTERFACE androidx/compose/runtime/Composer.startReplaceGroup (I)V (itf)
    ALOAD 34
    LDC "84@2962L278"
    INVOKESTATIC androidx/compose/runtime/ComposerKt.sourceInformation (Landroidx/compose/runtime/Composer;Ljava/lang/String;)V
   L114
    LINENUMBER 86 L114
    GETSTATIC androidx/compose/ui/Modifier.Companion : Landroidx/compose/ui/Modifier$Companion;
    CHECKCAST androidx/compose/ui/Modifier
   L115
    LINENUMBER 87 L115
    FCONST_0
    ICONST_1
    ACONST_NULL
    INVOKESTATIC androidx/compose/foundation/layout/SizeKt.fillMaxSize$default (Landroidx/compose/ui/Modifier;FILjava/lang/Object;)Landroidx/compose/ui/Modifier;
   L116
    LINENUMBER 89 L116
    GETSTATIC androidx/compose/ui/graphics/Brush.Companion : Landroidx/compose/ui/graphics/Brush$Companion;
   L117
    LINENUMBER 90 L117
    GETSTATIC capstone/safeline/ui/theme/ThemeManager.INSTANCE : Lcapstone/safeline/ui/theme/ThemeManager;
    INVOKEVIRTUAL capstone/safeline/ui/theme/ThemeManager.getBackgroundGradient ()Ljava/util/List;
   L118
    LINENUMBER 89 L118
    FCONST_0
    FCONST_0
    ICONST_0
    BIPUSH 14
    ACONST_NULL
    INVOKESTATIC androidx/compose/ui/graphics/Brush$Companion.verticalGradient-8A-3gB4$default (Landroidx/compose/ui/graphics/Brush$Companion;Ljava/util/List;FFIILjava/lang/Object;)Landroidx/compose/ui/graphics/Brush;
   L119
    LINENUMBER 88 L119
    ACONST_NULL
    FCONST_0
    BIPUSH 6
    ACONST_NULL
    INVOKESTATIC androidx/compose/foundation/BackgroundKt.background$default (Landroidx/compose/ui/Modifier;Landroidx/compose/ui/graphics/Brush;Landroidx/compose/ui/graphics/Shape;FILjava/lang/Object;)Landroidx/compose/ui/Modifier;
    ALOAD 34
    ICONST_0
   L120
    LINENUMBER 85 L120
    INVOKESTATIC androidx/compose/foundation/layout/BoxKt.Box (Landroidx/compose/ui/Modifier;Landroidx/compose/runtime/Composer;I)V
   L121
    LINENUMBER 84 L121
    ALOAD 34
    INVOKEINTERFACE androidx/compose/runtime/Composer.endReplaceGroup ()V (itf)
   L113
    LINENUMBER 96 L113
    GETSTATIC androidx/compose/ui/Modifier.Companion : Landroidx/compose/ui/Modifier$Companion;
    CHECKCAST androidx/compose/ui/Modifier
    FCONST_0
    ICONST_1
    ACONST_NULL
    INVOKESTATIC androidx/compose/foundation/layout/SizeKt.fillMaxSize$default (Landroidx/compose/ui/Modifier;FILjava/lang/Object;)Landroidx/compose/ui/Modifier;
    ASTORE 37
    BIPUSH 6
    ISTORE 38
   L122
    ICONST_0
    ISTORE 39
   L123
    ALOAD 34
    LDC 844473419
    LDC "CC(Row)N(modifier,horizontalArrangement,verticalAlignment,content)99@5125L58,100@5188L131:Row.kt#2w3rfo"
   L124
    LINENUMBER 315 L124
    INVOKESTATIC androidx/compose/runtime/ComposerKt.sourceInformationMarkerStart (Landroidx/compose/runtime/Composer;ILjava/lang/String;)V
   L125
    LINENUMBER 316 L125
    GETSTATIC androidx/compose/foundation/layout/Arrangement.INSTANCE : Landroidx/compose/foundation/layout/Arrangement;
    INVOKEVIRTUAL androidx/compose/foundation/layout/Arrangement.getStart ()Landroidx/compose/foundation/layout/Arrangement$Horizontal;
    ASTORE 40
   L126
    LINENUMBER 317 L126
    GETSTATIC androidx/compose/ui/Alignment.Companion : Landroidx/compose/ui/Alignment$Companion;
    INVOKEVIRTUAL androidx/compose/ui/Alignment$Companion.getTop ()Landroidx/compose/ui/Alignment$Vertical;
    ASTORE 41
   L127
    LINENUMBER 320 L127
    ALOAD 40
    ALOAD 41
    ALOAD 34
    BIPUSH 14
    ILOAD 38
    ICONST_3
    ISHR
    IAND
    BIPUSH 112
    ILOAD 38
    ICONST_3
    ISHR
    IAND
    IOR
    INVOKESTATIC androidx/compose/foundation/layout/RowKt.rowMeasurePolicy (Landroidx/compose/foundation/layout/Arrangement$Horizontal;Landroidx/compose/ui/Alignment$Vertical;Landroidx/compose/runtime/Composer;I)Landroidx/compose/ui/layout/MeasurePolicy;
    ASTORE 42
   L128
    LINENUMBER 324 L128
    ALOAD 37
    ASTORE 43
   L129
    LINENUMBER 323 L129
    ALOAD 42
    ASTORE 44
    ALOAD 34
    ASTORE 45
    BIPUSH 112
    ILOAD 38
    ICONST_3
    ISHL
    IAND
    ISTORE 46
   L130
    LINENUMBER 321 L130
    NOP
   L131
    ICONST_0
    ISTORE 47
   L132
    ALOAD 45
    LDC -1159599143
    LDC "CC(Layout)P(!1,2)81@3355L27,84@3521L416:Layout.kt#80mrfh"
   L133
    LINENUMBER 325 L133
    INVOKESTATIC androidx/compose/runtime/ComposerKt.sourceInformationMarkerStart (Landroidx/compose/runtime/Composer;ILjava/lang/String;)V
   L134
    LINENUMBER 326 L134
    ALOAD 45
    ICONST_0
    INVOKESTATIC androidx/compose/runtime/ComposablesKt.getCurrentCompositeKeyHashCode (Landroidx/compose/runtime/Composer;I)J
    INVOKESTATIC java/lang/Long.hashCode (J)I
    ISTORE 48
   L135
    ALOAD 45
   L136
    LINENUMBER 327 L136
    INVOKEINTERFACE androidx/compose/runtime/Composer.getCurrentCompositionLocalMap ()Landroidx/compose/runtime/CompositionLocalMap; (itf)
    ASTORE 49
   L137
    ALOAD 45
   L138
    LINENUMBER 328 L138
    ALOAD 43
    INVOKESTATIC androidx/compose/ui/ComposedModifierKt.materializeModifier (Landroidx/compose/runtime/Composer;Landroidx/compose/ui/Modifier;)Landroidx/compose/ui/Modifier;
    ASTORE 50
   L139
    LINENUMBER 330 L139
    GETSTATIC androidx/compose/ui/node/ComposeUiNode.Companion : Landroidx/compose/ui/node/ComposeUiNode$Companion;
    INVOKEVIRTUAL androidx/compose/ui/node/ComposeUiNode$Companion.getConstructor ()Lkotlin/jvm/functions/Function0;
    ASTORE 51
    ALOAD 45
    ASTORE 52
    BIPUSH 6
    SIPUSH 896
    ILOAD 46
    BIPUSH 6
    ISHL
    IAND
    IOR
    ISTORE 53
   L140
    LINENUMBER 329 L140
    NOP
   L141
    ICONST_0
    ISTORE 54
   L142
    ALOAD 52
    LDC -553112988
    LDC "CC(ReusableComposeNode)N(factory,update,content)399@15590L9:Composables.kt#9igjgp"
   L143
    LINENUMBER 331 L143
    INVOKESTATIC androidx/compose/runtime/ComposerKt.sourceInformationMarkerStart (Landroidx/compose/runtime/Composer;ILjava/lang/String;)V
   L144
    LINENUMBER 332 L144
    ALOAD 52
    INVOKEINTERFACE androidx/compose/runtime/Composer.getApplier ()Landroidx/compose/runtime/Applier; (itf)
    INSTANCEOF androidx/compose/runtime/Applier
    IFNE L145
    INVOKESTATIC androidx/compose/runtime/ComposablesKt.invalidApplier ()V
   L145
    ALOAD 52
   L146
    LINENUMBER 333 L146
    INVOKEINTERFACE androidx/compose/runtime/Composer.startReusableNode ()V (itf)
   L147
    LINENUMBER 334 L147
    ALOAD 52
    INVOKEINTERFACE androidx/compose/runtime/Composer.getInserting ()Z (itf)
    IFEQ L148
    ALOAD 52
   L149
    LINENUMBER 335 L149
    ALOAD 51
    INVOKEINTERFACE androidx/compose/runtime/Composer.createNode (Lkotlin/jvm/functions/Function0;)V (itf)
    GOTO L150
   L148
    ALOAD 52
   L151
    LINENUMBER 337 L151
    INVOKEINTERFACE androidx/compose/runtime/Composer.useNode ()V (itf)
   L150
    LINENUMBER 339 L150
    ALOAD 52
    INVOKESTATIC androidx/compose/runtime/Updater.constructor-impl (Landroidx/compose/runtime/Composer;)Landroidx/compose/runtime/Composer;
    ASTORE 55
   L152
    ICONST_0
    ISTORE 56
   L153
    LINENUMBER 340 L153
    ALOAD 55
    ALOAD 44
    GETSTATIC androidx/compose/ui/node/ComposeUiNode.Companion : Landroidx/compose/ui/node/ComposeUiNode$Companion;
    INVOKEVIRTUAL androidx/compose/ui/node/ComposeUiNode$Companion.getSetMeasurePolicy ()Lkotlin/jvm/functions/Function2;
    INVOKESTATIC androidx/compose/runtime/Updater.set-impl (Landroidx/compose/runtime/Composer;Ljava/lang/Object;Lkotlin/jvm/functions/Function2;)V
   L154
    LINENUMBER 341 L154
    ALOAD 55
    ALOAD 49
    GETSTATIC androidx/compose/ui/node/ComposeUiNode.Companion : Landroidx/compose/ui/node/ComposeUiNode$Companion;
    INVOKEVIRTUAL androidx/compose/ui/node/ComposeUiNode$Companion.getSetResolvedCompositionLocals ()Lkotlin/jvm/functions/Function2;
    INVOKESTATIC androidx/compose/runtime/Updater.set-impl (Landroidx/compose/runtime/Composer;Ljava/lang/Object;Lkotlin/jvm/functions/Function2;)V
   L155
    LINENUMBER 342 L155
    ALOAD 55
    ILOAD 48
    INVOKESTATIC java/lang/Integer.valueOf (I)Ljava/lang/Integer;
    GETSTATIC androidx/compose/ui/node/ComposeUiNode.Companion : Landroidx/compose/ui/node/ComposeUiNode$Companion;
    INVOKEVIRTUAL androidx/compose/ui/node/ComposeUiNode$Companion.getSetCompositeKeyHash ()Lkotlin/jvm/functions/Function2;
    INVOKESTATIC androidx/compose/runtime/Updater.init-impl (Landroidx/compose/runtime/Composer;Ljava/lang/Object;Lkotlin/jvm/functions/Function2;)V
   L156
    LINENUMBER 343 L156
    ALOAD 55
    GETSTATIC androidx/compose/ui/node/ComposeUiNode.Companion : Landroidx/compose/ui/node/ComposeUiNode$Companion;
    INVOKEVIRTUAL androidx/compose/ui/node/ComposeUiNode$Companion.getApplyOnDeactivatedNodeAssertion ()Lkotlin/jvm/functions/Function1;
    INVOKESTATIC androidx/compose/runtime/Updater.reconcile-impl (Landroidx/compose/runtime/Composer;Lkotlin/jvm/functions/Function1;)V
   L157
    LINENUMBER 344 L157
    ALOAD 55
    ALOAD 50
    GETSTATIC androidx/compose/ui/node/ComposeUiNode.Companion : Landroidx/compose/ui/node/ComposeUiNode$Companion;
    INVOKEVIRTUAL androidx/compose/ui/node/ComposeUiNode$Companion.getSetModifier ()Lkotlin/jvm/functions/Function2;
    INVOKESTATIC androidx/compose/runtime/Updater.set-impl (Landroidx/compose/runtime/Composer;Ljava/lang/Object;Lkotlin/jvm/functions/Function2;)V
   L158
    LINENUMBER 345 L158
    NOP
   L159
    LINENUMBER 339 L159
    NOP
   L160
    LINENUMBER 346 L160
    ALOAD 52
    BIPUSH 14
    ILOAD 53
    BIPUSH 6
    ISHR
    IAND
    ISTORE 57
    ASTORE 58
   L161
    ICONST_0
    ISTORE 59
   L162
    ALOAD 58
    LDC 1456264949
    LDC "C101@5233L9:Row.kt#2w3rfo"
   L163
    LINENUMBER 322 L163
    INVOKESTATIC androidx/compose/runtime/ComposerKt.sourceInformationMarkerStart (Landroidx/compose/runtime/Composer;ILjava/lang/String;)V
    GETSTATIC androidx/compose/foundation/layout/RowScopeInstance.INSTANCE : Landroidx/compose/foundation/layout/RowScopeInstance;
    ALOAD 58
    BIPUSH 6
    BIPUSH 112
    ILOAD 38
    BIPUSH 6
    ISHR
    IAND
    IOR
    INVOKESTATIC java/lang/Integer.valueOf (I)Ljava/lang/Integer;
    CHECKCAST java/lang/Number
    INVOKEVIRTUAL java/lang/Number.intValue ()I
    ISTORE 60
    CHECKCAST androidx/compose/runtime/Composer
    ASTORE 61
    CHECKCAST androidx/compose/foundation/layout/RowScope
    ASTORE 62
   L164
    ICONST_0
    ISTORE 63
   L165
    ALOAD 61
    LDC 926693466
    LDC "C101@3500L2,97@3314L286,106@3614L6788:ChannelScreen.kt#dnwu2"
   L166
    LINENUMBER 98 L166
    INVOKESTATIC androidx/compose/runtime/ComposerKt.sourceInformationMarkerStart (Landroidx/compose/runtime/Composer;ILjava/lang/String;)V
   L167
    LINENUMBER 99 L167
    ALOAD 0
   L168
    LINENUMBER 100 L168
    ALOAD 1
   L169
    LINENUMBER 101 L169
    ALOAD 2
    ALOAD 61
    LDC -524297125
    INVOKEINTERFACE androidx/compose/runtime/Composer.startReplaceGroup (I)V (itf)
    ALOAD 61
    LDC "CC(remember):ChannelScreen.kt#9igjgp"
    INVOKESTATIC androidx/compose/runtime/ComposerKt.sourceInformation (Landroidx/compose/runtime/Composer;Ljava/lang/String;)V
    ALOAD 61
    ASTORE 64
    ICONST_0
    ISTORE 65
   L170
    LINENUMBER 102 L170
    NOP
   L171
    ICONST_0
    ISTORE 66
   L172
    LINENUMBER 347 L172
    ALOAD 64
    INVOKEINTERFACE androidx/compose/runtime/Composer.rememberedValue ()Ljava/lang/Object; (itf)
    ASTORE 67
   L173
    ICONST_0
    ISTORE 68
   L174
    LINENUMBER 348 L174
    ILOAD 65
    IFNE L175
    ALOAD 67
    GETSTATIC androidx/compose/runtime/Composer.Companion : Landroidx/compose/runtime/Composer$Companion;
    INVOKEVIRTUAL androidx/compose/runtime/Composer$Companion.getEmpty ()Ljava/lang/Object;
    IF_ACMPNE L176
   L175
    LINENUMBER 349 L175
    ASTORE 69
    ASTORE 70
    ASTORE 71
    ICONST_0
    ISTORE 72
   L177
    INVOKEDYNAMIC invoke()Lkotlin/jvm/functions/Function0; [
      // handle kind 0x6 : INVOKESTATIC
      java/lang/invoke/LambdaMetafactory.metafactory(Ljava/lang/invoke/MethodHandles$Lookup;Ljava/lang/String;Ljava/lang/invoke/MethodType;Ljava/lang/invoke/MethodType;Ljava/lang/invoke/MethodHandle;Ljava/lang/invoke/MethodType;)Ljava/lang/invoke/CallSite;
      // arguments:
      ()Ljava/lang/Object;, 
      // handle kind 0x6 : INVOKESTATIC
      capstone/safeline/ui/ChannelScreenKt.ChannelScreenUI$lambda$27$lambda$26$lambda$7$lambda$6()Lkotlin/Unit;, 
      ()Lkotlin/Unit;
    ]
    GOTO L178
   L178
    ASTORE 73
    ALOAD 71
    ALOAD 70
    ALOAD 69
    ALOAD 73
   L179
    LINENUMBER 349 L179
    ASTORE 72
   L180
    LINENUMBER 350 L180
    ALOAD 64
    ALOAD 72
    INVOKEINTERFACE androidx/compose/runtime/Composer.updateRememberedValue (Ljava/lang/Object;)V (itf)
   L181
    LINENUMBER 351 L181
    ALOAD 72
   L182
    GOTO L183
   L176
    LINENUMBER 352 L176
    ALOAD 67
   L183
    LINENUMBER 347 L183
    NOP
   L184
    LINENUMBER 347 L184
    GOTO L185
   L185
    LINENUMBER 102 L185
    CHECKCAST kotlin/jvm/functions/Function0
    ASTORE 74
    ALOAD 61
    INVOKEINTERFACE androidx/compose/runtime/Composer.endReplaceGroup ()V (itf)
    ALOAD 74
   L186
    LINENUMBER 103 L186
    ACONST_NULL
   L187
    LINENUMBER 104 L187
    GETSTATIC capstone/safeline/R$drawable.back_btn : I
    ALOAD 61
    SIPUSH 27648
    BIPUSH 14
    ILOAD 7
    IAND
    IOR
    BIPUSH 112
    ILOAD 7
    IAND
    IOR
    SIPUSH 896
    ILOAD 7
    IAND
    IOR
   L188
    LINENUMBER 98 L188
    INVOKESTATIC capstone/safeline/ui/CommunityServersKt.LeftServersPanel (Ljava/util/List;Ljava/lang/String;Lkotlin/jvm/functions/Function1;Lkotlin/jvm/functions/Function0;Lkotlin/jvm/functions/Function0;ILandroidx/compose/runtime/Composer;I)V
   L189
    LINENUMBER 108 L189
    GETSTATIC androidx/compose/ui/Modifier.Companion : Landroidx/compose/ui/Modifier$Companion;
    CHECKCAST androidx/compose/ui/Modifier
   L190
    LINENUMBER 109 L190
    FCONST_0
    ICONST_1
    ACONST_NULL
    INVOKESTATIC androidx/compose/foundation/layout/SizeKt.fillMaxSize$default (Landroidx/compose/ui/Modifier;FILjava/lang/Object;)Landroidx/compose/ui/Modifier;
   L191
    LINENUMBER 110 L191
    INVOKESTATIC androidx/compose/foundation/layout/WindowInsetsPadding_androidKt.statusBarsPadding (Landroidx/compose/ui/Modifier;)Landroidx/compose/ui/Modifier;
    ASTORE 74
   L192
    LINENUMBER 111 L192
    BIPUSH 22
    ISTORE 65
   L193
    ICONST_0
    ISTORE 66
   L194
    LINENUMBER 353 L194
    ILOAD 65
    I2F
    INVOKESTATIC androidx/compose/ui/unit/Dp.constructor-impl (F)F
    GOTO L195
   L195
    LINENUMBER 111 L195
    FSTORE 64
    ICONST_4
    ISTORE 66
   L196
    ICONST_0
    ISTORE 67
   L197
    LINENUMBER 353 L197
    ILOAD 66
    I2F
    INVOKESTATIC androidx/compose/ui/unit/Dp.constructor-impl (F)F
    GOTO L198
   L198
    LINENUMBER 111 L198
    FSTORE 65
    ICONST_4
    ISTORE 67
   L199
    ICONST_0
    ISTORE 68
   L200
    LINENUMBER 353 L200
    ILOAD 67
    I2F
    INVOKESTATIC androidx/compose/ui/unit/Dp.constructor-impl (F)F
    GOTO L201
   L201
    LINENUMBER 111 L201
    FSTORE 66
   L202
    LINENUMBER 110 L202
    ALOAD 74
   L203
    LINENUMBER 111 L203
    FLOAD 65
    FLOAD 64
    FLOAD 66
    FCONST_0
    BIPUSH 8
    ACONST_NULL
    INVOKESTATIC androidx/compose/foundation/layout/PaddingKt.padding-qDBjuR0$default (Landroidx/compose/ui/Modifier;FFFFILjava/lang/Object;)Landroidx/compose/ui/Modifier;
    ASTORE 74
    ICONST_0
    ISTORE 66
   L204
    LINENUMBER 107 L204
    NOP
   L205
    ICONST_0
    ISTORE 67
   L206
    ALOAD 61
    LDC 1341605231
    LDC "CC(Column)N(modifier,verticalArrangement,horizontalAlignment,content)87@4443L61,88@4509L134:Column.kt#2w3rfo"
   L207
    LINENUMBER 354 L207
    INVOKESTATIC androidx/compose/runtime/ComposerKt.sourceInformationMarkerStart (Landroidx/compose/runtime/Composer;ILjava/lang/String;)V
   L208
    LINENUMBER 355 L208
    GETSTATIC androidx/compose/foundation/layout/Arrangement.INSTANCE : Landroidx/compose/foundation/layout/Arrangement;
    INVOKEVIRTUAL androidx/compose/foundation/layout/Arrangement.getTop ()Landroidx/compose/foundation/layout/Arrangement$Vertical;
    ASTORE 64
   L209
    LINENUMBER 356 L209
    GETSTATIC androidx/compose/ui/Alignment.Companion : Landroidx/compose/ui/Alignment$Companion;
    INVOKEVIRTUAL androidx/compose/ui/Alignment$Companion.getStart ()Landroidx/compose/ui/Alignment$Horizontal;
    ASTORE 65
   L210
    LINENUMBER 359 L210
    ALOAD 64
    ALOAD 65
    ALOAD 61
    BIPUSH 14
    ILOAD 66
    ICONST_3
    ISHR
    IAND
    BIPUSH 112
    ILOAD 66
    ICONST_3
    ISHR
    IAND
    IOR
    INVOKESTATIC androidx/compose/foundation/layout/ColumnKt.columnMeasurePolicy (Landroidx/compose/foundation/layout/Arrangement$Vertical;Landroidx/compose/ui/Alignment$Horizontal;Landroidx/compose/runtime/Composer;I)Landroidx/compose/ui/layout/MeasurePolicy;
    ASTORE 68
   L211
    LINENUMBER 363 L211
    ALOAD 74
    ASTORE 72
   L212
    LINENUMBER 362 L212
    ALOAD 68
    ASTORE 75
    ALOAD 61
    ASTORE 76
    BIPUSH 112
    ILOAD 66
    ICONST_3
    ISHL
    IAND
    ISTORE 77
   L213
    LINENUMBER 360 L213
    NOP
   L214
    ICONST_0
    ISTORE 78
   L215
    ALOAD 76
    LDC -1159599143
    LDC "CC(Layout)P(!1,2)81@3355L27,84@3521L416:Layout.kt#80mrfh"
   L216
    LINENUMBER 364 L216
    INVOKESTATIC androidx/compose/runtime/ComposerKt.sourceInformationMarkerStart (Landroidx/compose/runtime/Composer;ILjava/lang/String;)V
   L217
    LINENUMBER 365 L217
    ALOAD 76
    ICONST_0
    INVOKESTATIC androidx/compose/runtime/ComposablesKt.getCurrentCompositeKeyHashCode (Landroidx/compose/runtime/Composer;I)J
    INVOKESTATIC java/lang/Long.hashCode (J)I
    ISTORE 79
   L218
    ALOAD 76
   L219
    LINENUMBER 366 L219
    INVOKEINTERFACE androidx/compose/runtime/Composer.getCurrentCompositionLocalMap ()Landroidx/compose/runtime/CompositionLocalMap; (itf)
    ASTORE 80
   L220
    ALOAD 76
   L221
    LINENUMBER 367 L221
    ALOAD 72
    INVOKESTATIC androidx/compose/ui/ComposedModifierKt.materializeModifier (Landroidx/compose/runtime/Composer;Landroidx/compose/ui/Modifier;)Landroidx/compose/ui/Modifier;
    ASTORE 81
   L222
    LINENUMBER 369 L222
    GETSTATIC androidx/compose/ui/node/ComposeUiNode.Companion : Landroidx/compose/ui/node/ComposeUiNode$Companion;
    INVOKEVIRTUAL androidx/compose/ui/node/ComposeUiNode$Companion.getConstructor ()Lkotlin/jvm/functions/Function0;
    ASTORE 82
    ALOAD 76
    ASTORE 83
    BIPUSH 6
    SIPUSH 896
    ILOAD 77
    BIPUSH 6
    ISHL
    IAND
    IOR
    ISTORE 84
   L223
    LINENUMBER 368 L223
    NOP
   L224
    ICONST_0
    ISTORE 85
   L225
    ALOAD 83
    LDC -553112988
    LDC "CC(ReusableComposeNode)N(factory,update,content)399@15590L9:Composables.kt#9igjgp"
   L226
    LINENUMBER 370 L226
    INVOKESTATIC androidx/compose/runtime/ComposerKt.sourceInformationMarkerStart (Landroidx/compose/runtime/Composer;ILjava/lang/String;)V
   L227
    LINENUMBER 371 L227
    ALOAD 83
    INVOKEINTERFACE androidx/compose/runtime/Composer.getApplier ()Landroidx/compose/runtime/Applier; (itf)
    INSTANCEOF androidx/compose/runtime/Applier
    IFNE L228
    INVOKESTATIC androidx/compose/runtime/ComposablesKt.invalidApplier ()V
   L228
    ALOAD 83
   L229
    LINENUMBER 372 L229
    INVOKEINTERFACE androidx/compose/runtime/Composer.startReusableNode ()V (itf)
   L230
    LINENUMBER 373 L230
    ALOAD 83
    INVOKEINTERFACE androidx/compose/runtime/Composer.getInserting ()Z (itf)
    IFEQ L231
    ALOAD 83
   L232
    LINENUMBER 374 L232
    ALOAD 82
    INVOKEINTERFACE androidx/compose/runtime/Composer.createNode (Lkotlin/jvm/functions/Function0;)V (itf)
    GOTO L233
   L231
    ALOAD 83
   L234
    LINENUMBER 376 L234
    INVOKEINTERFACE androidx/compose/runtime/Composer.useNode ()V (itf)
   L233
    LINENUMBER 378 L233
    ALOAD 83
    INVOKESTATIC androidx/compose/runtime/Updater.constructor-impl (Landroidx/compose/runtime/Composer;)Landroidx/compose/runtime/Composer;
    ASTORE 86
   L235
    ICONST_0
    ISTORE 87
   L236
    LINENUMBER 379 L236
    ALOAD 86
    ALOAD 75
    GETSTATIC androidx/compose/ui/node/ComposeUiNode.Companion : Landroidx/compose/ui/node/ComposeUiNode$Companion;
    INVOKEVIRTUAL androidx/compose/ui/node/ComposeUiNode$Companion.getSetMeasurePolicy ()Lkotlin/jvm/functions/Function2;
    INVOKESTATIC androidx/compose/runtime/Updater.set-impl (Landroidx/compose/runtime/Composer;Ljava/lang/Object;Lkotlin/jvm/functions/Function2;)V
   L237
    LINENUMBER 380 L237
    ALOAD 86
    ALOAD 80
    GETSTATIC androidx/compose/ui/node/ComposeUiNode.Companion : Landroidx/compose/ui/node/ComposeUiNode$Companion;
    INVOKEVIRTUAL androidx/compose/ui/node/ComposeUiNode$Companion.getSetResolvedCompositionLocals ()Lkotlin/jvm/functions/Function2;
    INVOKESTATIC androidx/compose/runtime/Updater.set-impl (Landroidx/compose/runtime/Composer;Ljava/lang/Object;Lkotlin/jvm/functions/Function2;)V
   L238
    LINENUMBER 381 L238
    ALOAD 86
    ILOAD 79
    INVOKESTATIC java/lang/Integer.valueOf (I)Ljava/lang/Integer;
    GETSTATIC androidx/compose/ui/node/ComposeUiNode.Companion : Landroidx/compose/ui/node/ComposeUiNode$Companion;
    INVOKEVIRTUAL androidx/compose/ui/node/ComposeUiNode$Companion.getSetCompositeKeyHash ()Lkotlin/jvm/functions/Function2;
    INVOKESTATIC androidx/compose/runtime/Updater.init-impl (Landroidx/compose/runtime/Composer;Ljava/lang/Object;Lkotlin/jvm/functions/Function2;)V
   L239
    LINENUMBER 382 L239
    ALOAD 86
    GETSTATIC androidx/compose/ui/node/ComposeUiNode.Companion : Landroidx/compose/ui/node/ComposeUiNode$Companion;
    INVOKEVIRTUAL androidx/compose/ui/node/ComposeUiNode$Companion.getApplyOnDeactivatedNodeAssertion ()Lkotlin/jvm/functions/Function1;
    INVOKESTATIC androidx/compose/runtime/Updater.reconcile-impl (Landroidx/compose/runtime/Composer;Lkotlin/jvm/functions/Function1;)V
   L240
    LINENUMBER 383 L240
    ALOAD 86
    ALOAD 81
    GETSTATIC androidx/compose/ui/node/ComposeUiNode.Companion : Landroidx/compose/ui/node/ComposeUiNode$Companion;
    INVOKEVIRTUAL androidx/compose/ui/node/ComposeUiNode$Companion.getSetModifier ()Lkotlin/jvm/functions/Function2;
    INVOKESTATIC androidx/compose/runtime/Updater.set-impl (Landroidx/compose/runtime/Composer;Ljava/lang/Object;Lkotlin/jvm/functions/Function2;)V
   L241
    LINENUMBER 384 L241
    NOP
   L242
    LINENUMBER 378 L242
    NOP
   L243
    LINENUMBER 385 L243
    ALOAD 83
    BIPUSH 14
    ILOAD 84
    BIPUSH 6
    ISHR
    IAND
    ISTORE 88
    ASTORE 89
   L244
    ICONST_0
    ISTORE 90
   L245
    ALOAD 89
    LDC 2093002350
    LDC "C89@4557L9:Column.kt#2w3rfo"
   L246
    LINENUMBER 361 L246
    INVOKESTATIC androidx/compose/runtime/ComposerKt.sourceInformationMarkerStart (Landroidx/compose/runtime/Composer;ILjava/lang/String;)V
    GETSTATIC androidx/compose/foundation/layout/ColumnScopeInstance.INSTANCE : Landroidx/compose/foundation/layout/ColumnScopeInstance;
    ALOAD 89
    BIPUSH 6
    BIPUSH 112
    ILOAD 66
    BIPUSH 6
    ISHR
    IAND
    IOR
    INVOKESTATIC java/lang/Integer.valueOf (I)Ljava/lang/Integer;
    CHECKCAST java/lang/Number
    INVOKEVIRTUAL java/lang/Number.intValue ()I
    ISTORE 91
    CHECKCAST androidx/compose/runtime/Composer
    ASTORE 92
    CHECKCAST androidx/compose/foundation/layout/ColumnScope
    ASTORE 93
   L247
    ICONST_0
    ISTORE 94
   L248
    ALOAD 92
    LDC 2087429586
    LDC "C113@3835L1222,151@5425L1551,144@5075L1901,185@6994L3394:ChannelScreen.kt#dnwu2"
   L249
    LINENUMBER 114 L249
    INVOKESTATIC androidx/compose/runtime/ComposerKt.sourceInformationMarkerStart (Landroidx/compose/runtime/Composer;ILjava/lang/String;)V
    GETSTATIC androidx/compose/ui/Alignment.Companion : Landroidx/compose/ui/Alignment$Companion;
    INVOKEVIRTUAL androidx/compose/ui/Alignment$Companion.getCenterVertically ()Landroidx/compose/ui/Alignment$Vertical;
    ASTORE 95
    SIPUSH 384
    ISTORE 96
   L250
    ICONST_0
    ISTORE 97
   L251
    ALOAD 92
    LDC 844473419
    LDC "CC(Row)N(modifier,horizontalArrangement,verticalAlignment,content)99@5125L58,100@5188L131:Row.kt#2w3rfo"
   L252
    LINENUMBER 386 L252
    INVOKESTATIC androidx/compose/runtime/ComposerKt.sourceInformationMarkerStart (Landroidx/compose/runtime/Composer;ILjava/lang/String;)V
   L253
    LINENUMBER 387 L253
    GETSTATIC androidx/compose/ui/Modifier.Companion : Landroidx/compose/ui/Modifier$Companion;
    CHECKCAST androidx/compose/ui/Modifier
    ASTORE 98
   L254
    LINENUMBER 388 L254
    GETSTATIC androidx/compose/foundation/layout/Arrangement.INSTANCE : Landroidx/compose/foundation/layout/Arrangement;
    INVOKEVIRTUAL androidx/compose/foundation/layout/Arrangement.getStart ()Landroidx/compose/foundation/layout/Arrangement$Horizontal;
    ASTORE 99
   L255
    LINENUMBER 392 L255
    ALOAD 99
    ALOAD 95
    ALOAD 92
    BIPUSH 14
    ILOAD 96
    ICONST_3
    ISHR
    IAND
    BIPUSH 112
    ILOAD 96
    ICONST_3
    ISHR
    IAND
    IOR
    INVOKESTATIC androidx/compose/foundation/layout/RowKt.rowMeasurePolicy (Landroidx/compose/foundation/layout/Arrangement$Horizontal;Landroidx/compose/ui/Alignment$Vertical;Landroidx/compose/runtime/Composer;I)Landroidx/compose/ui/layout/MeasurePolicy;
    ASTORE 100
   L256
    LINENUMBER 396 L256
    ALOAD 98
    ASTORE 101
   L257
    LINENUMBER 395 L257
    ALOAD 100
    ASTORE 102
    ALOAD 92
    ASTORE 103
    BIPUSH 112
    ILOAD 96
    ICONST_3
    ISHL
    IAND
    ISTORE 104
   L258
    LINENUMBER 393 L258
    NOP
   L259
    ICONST_0
    ISTORE 105
   L260
    ALOAD 103
    LDC -1159599143
    LDC "CC(Layout)P(!1,2)81@3355L27,84@3521L416:Layout.kt#80mrfh"
   L261
    LINENUMBER 397 L261
    INVOKESTATIC androidx/compose/runtime/ComposerKt.sourceInformationMarkerStart (Landroidx/compose/runtime/Composer;ILjava/lang/String;)V
   L262
    LINENUMBER 398 L262
    ALOAD 103
    ICONST_0
    INVOKESTATIC androidx/compose/runtime/ComposablesKt.getCurrentCompositeKeyHashCode (Landroidx/compose/runtime/Composer;I)J
    INVOKESTATIC java/lang/Long.hashCode (J)I
    ISTORE 106
   L263
    ALOAD 103
   L264
    LINENUMBER 399 L264
    INVOKEINTERFACE androidx/compose/runtime/Composer.getCurrentCompositionLocalMap ()Landroidx/compose/runtime/CompositionLocalMap; (itf)
    ASTORE 107
   L265
    ALOAD 103
   L266
    LINENUMBER 400 L266
    ALOAD 101
    INVOKESTATIC androidx/compose/ui/ComposedModifierKt.materializeModifier (Landroidx/compose/runtime/Composer;Landroidx/compose/ui/Modifier;)Landroidx/compose/ui/Modifier;
    ASTORE 108
   L267
    LINENUMBER 402 L267
    GETSTATIC androidx/compose/ui/node/ComposeUiNode.Companion : Landroidx/compose/ui/node/ComposeUiNode$Companion;
    INVOKEVIRTUAL androidx/compose/ui/node/ComposeUiNode$Companion.getConstructor ()Lkotlin/jvm/functions/Function0;
    ASTORE 109
    ALOAD 103
    ASTORE 110
    BIPUSH 6
    SIPUSH 896
    ILOAD 104
    BIPUSH 6
    ISHL
    IAND
    IOR
    ISTORE 111
   L268
    LINENUMBER 401 L268
    NOP
   L269
    ICONST_0
    ISTORE 112
   L270
    ALOAD 110
    LDC -553112988
    LDC "CC(ReusableComposeNode)N(factory,update,content)399@15590L9:Composables.kt#9igjgp"
   L271
    LINENUMBER 403 L271
    INVOKESTATIC androidx/compose/runtime/ComposerKt.sourceInformationMarkerStart (Landroidx/compose/runtime/Composer;ILjava/lang/String;)V
   L272
    LINENUMBER 404 L272
    ALOAD 110
    INVOKEINTERFACE androidx/compose/runtime/Composer.getApplier ()Landroidx/compose/runtime/Applier; (itf)
    INSTANCEOF androidx/compose/runtime/Applier
    IFNE L273
    INVOKESTATIC androidx/compose/runtime/ComposablesKt.invalidApplier ()V
   L273
    ALOAD 110
   L274
    LINENUMBER 405 L274
    INVOKEINTERFACE androidx/compose/runtime/Composer.startReusableNode ()V (itf)
   L275
    LINENUMBER 406 L275
    ALOAD 110
    INVOKEINTERFACE androidx/compose/runtime/Composer.getInserting ()Z (itf)
    IFEQ L276
    ALOAD 110
   L277
    LINENUMBER 407 L277
    ALOAD 109
    INVOKEINTERFACE androidx/compose/runtime/Composer.createNode (Lkotlin/jvm/functions/Function0;)V (itf)
    GOTO L278
   L276
    ALOAD 110
   L279
    LINENUMBER 409 L279
    INVOKEINTERFACE androidx/compose/runtime/Composer.useNode ()V (itf)
   L278
    LINENUMBER 411 L278
    ALOAD 110
    INVOKESTATIC androidx/compose/runtime/Updater.constructor-impl (Landroidx/compose/runtime/Composer;)Landroidx/compose/runtime/Composer;
    ASTORE 113
   L280
    ICONST_0
    ISTORE 114
   L281
    LINENUMBER 412 L281
    ALOAD 113
    ALOAD 102
    GETSTATIC androidx/compose/ui/node/ComposeUiNode.Companion : Landroidx/compose/ui/node/ComposeUiNode$Companion;
    INVOKEVIRTUAL androidx/compose/ui/node/ComposeUiNode$Companion.getSetMeasurePolicy ()Lkotlin/jvm/functions/Function2;
    INVOKESTATIC androidx/compose/runtime/Updater.set-impl (Landroidx/compose/runtime/Composer;Ljava/lang/Object;Lkotlin/jvm/functions/Function2;)V
   L282
    LINENUMBER 413 L282
    ALOAD 113
    ALOAD 107
    GETSTATIC androidx/compose/ui/node/ComposeUiNode.Companion : Landroidx/compose/ui/node/ComposeUiNode$Companion;
    INVOKEVIRTUAL androidx/compose/ui/node/ComposeUiNode$Companion.getSetResolvedCompositionLocals ()Lkotlin/jvm/functions/Function2;
    INVOKESTATIC androidx/compose/runtime/Updater.set-impl (Landroidx/compose/runtime/Composer;Ljava/lang/Object;Lkotlin/jvm/functions/Function2;)V
   L283
    LINENUMBER 414 L283
    ALOAD 113
    ILOAD 106
    INVOKESTATIC java/lang/Integer.valueOf (I)Ljava/lang/Integer;
    GETSTATIC androidx/compose/ui/node/ComposeUiNode.Companion : Landroidx/compose/ui/node/ComposeUiNode$Companion;
    INVOKEVIRTUAL androidx/compose/ui/node/ComposeUiNode$Companion.getSetCompositeKeyHash ()Lkotlin/jvm/functions/Function2;
    INVOKESTATIC androidx/compose/runtime/Updater.init-impl (Landroidx/compose/runtime/Composer;Ljava/lang/Object;Lkotlin/jvm/functions/Function2;)V
   L284
    LINENUMBER 415 L284
    ALOAD 113
    GETSTATIC androidx/compose/ui/node/ComposeUiNode.Companion : Landroidx/compose/ui/node/ComposeUiNode$Companion;
    INVOKEVIRTUAL androidx/compose/ui/node/ComposeUiNode$Companion.getApplyOnDeactivatedNodeAssertion ()Lkotlin/jvm/functions/Function1;
    INVOKESTATIC androidx/compose/runtime/Updater.reconcile-impl (Landroidx/compose/runtime/Composer;Lkotlin/jvm/functions/Function1;)V
   L285
    LINENUMBER 416 L285
    ALOAD 113
    ALOAD 108
    GETSTATIC androidx/compose/ui/node/ComposeUiNode.Companion : Landroidx/compose/ui/node/ComposeUiNode$Companion;
    INVOKEVIRTUAL androidx/compose/ui/node/ComposeUiNode$Companion.getSetModifier ()Lkotlin/jvm/functions/Function2;
    INVOKESTATIC androidx/compose/runtime/Updater.set-impl (Landroidx/compose/runtime/Composer;Ljava/lang/Object;Lkotlin/jvm/functions/Function2;)V
   L286
    LINENUMBER 417 L286
    NOP
   L287
    LINENUMBER 411 L287
    NOP
   L288
    LINENUMBER 418 L288
    ALOAD 110
    BIPUSH 14
    ILOAD 111
    BIPUSH 6
    ISHR
    IAND
    ISTORE 115
    ASTORE 116
   L289
    ICONST_0
    ISTORE 117
   L290
    ALOAD 116
    LDC 1456264949
    LDC "C101@5233L9:Row.kt#2w3rfo"
   L291
    LINENUMBER 394 L291
    INVOKESTATIC androidx/compose/runtime/ComposerKt.sourceInformationMarkerStart (Landroidx/compose/runtime/Composer;ILjava/lang/String;)V
    GETSTATIC androidx/compose/foundation/layout/RowScopeInstance.INSTANCE : Landroidx/compose/foundation/layout/RowScopeInstance;
    ALOAD 116
    BIPUSH 6
    BIPUSH 112
    ILOAD 96
    BIPUSH 6
    ISHR
    IAND
    IOR
    INVOKESTATIC java/lang/Integer.valueOf (I)Ljava/lang/Integer;
    CHECKCAST java/lang/Number
    INVOKEVIRTUAL java/lang/Number.intValue ()I
    ISTORE 118
    CHECKCAST androidx/compose/runtime/Composer
    ASTORE 119
    CHECKCAST androidx/compose/foundation/layout/RowScope
    ASTORE 120
   L292
    ICONST_0
    ISTORE 121
   L293
    ALOAD 119
    LDC -2065761917
    LDC "C115@3910L1129:ChannelScreen.kt#dnwu2"
   L294
    LINENUMBER 116 L294
    INVOKESTATIC androidx/compose/runtime/ComposerKt.sourceInformationMarkerStart (Landroidx/compose/runtime/Composer;ILjava/lang/String;)V
   L295
    LINENUMBER 117 L295
    ALOAD 120
    GETSTATIC androidx/compose/ui/Modifier.Companion : Landroidx/compose/ui/Modifier$Companion;
    CHECKCAST androidx/compose/ui/Modifier
    FCONST_1
    ICONST_0
    ICONST_2
    ACONST_NULL
    INVOKESTATIC androidx/compose/foundation/layout/RowScope.weight$default (Landroidx/compose/foundation/layout/RowScope;Landroidx/compose/ui/Modifier;FZILjava/lang/Object;)Landroidx/compose/ui/Modifier; (itf)
    ASTORE 122
   L296
    LINENUMBER 118 L296
    GETSTATIC androidx/compose/ui/Alignment.Companion : Landroidx/compose/ui/Alignment$Companion;
    INVOKEVIRTUAL androidx/compose/ui/Alignment$Companion.getCenter ()Landroidx/compose/ui/Alignment;
    ASTORE 123
    BIPUSH 48
    ISTORE 124
   L297
    LINENUMBER 116 L297
    NOP
   L298
    ICONST_0
    ISTORE 125
   L299
    ALOAD 119
    LDC 1042775818
    LDC "CC(Box)N(modifier,contentAlignment,propagateMinConstraints,content)71@3424L131:Box.kt#2w3rfo"
   L300
    LINENUMBER 419 L300
    INVOKESTATIC androidx/compose/runtime/ComposerKt.sourceInformationMarkerStart (Landroidx/compose/runtime/Composer;ILjava/lang/String;)V
   L301
    LINENUMBER 420 L301
    ICONST_0
    ISTORE 126
   L302
    LINENUMBER 423 L302
    ALOAD 123
    ILOAD 126
    INVOKESTATIC androidx/compose/foundation/layout/BoxKt.maybeCachedBoxMeasurePolicy (Landroidx/compose/ui/Alignment;Z)Landroidx/compose/ui/layout/MeasurePolicy;
    ASTORE 127
   L303
    LINENUMBER 427 L303
    ALOAD 122
    ASTORE 128
   L304
    LINENUMBER 426 L304
    ALOAD 127
    ASTORE 129
    ALOAD 119
    ASTORE 130
    BIPUSH 112
    ILOAD 124
    ICONST_3
    ISHL
    IAND
    ISTORE 131
   L305
    LINENUMBER 424 L305
    NOP
   L306
    ICONST_0
    ISTORE 132
   L307
    ALOAD 130
    LDC -1159599143
    LDC "CC(Layout)P(!1,2)81@3355L27,84@3521L416:Layout.kt#80mrfh"
   L308
    LINENUMBER 428 L308
    INVOKESTATIC androidx/compose/runtime/ComposerKt.sourceInformationMarkerStart (Landroidx/compose/runtime/Composer;ILjava/lang/String;)V
   L309
    LINENUMBER 429 L309
    ALOAD 130
    ICONST_0
    INVOKESTATIC androidx/compose/runtime/ComposablesKt.getCurrentCompositeKeyHashCode (Landroidx/compose/runtime/Composer;I)J
    INVOKESTATIC java/lang/Long.hashCode (J)I
    ISTORE 133
   L310
    ALOAD 130
   L311
    LINENUMBER 430 L311
    INVOKEINTERFACE androidx/compose/runtime/Composer.getCurrentCompositionLocalMap ()Landroidx/compose/runtime/CompositionLocalMap; (itf)
    ASTORE 134
   L312
    ALOAD 130
   L313
    LINENUMBER 431 L313
    ALOAD 128
    INVOKESTATIC androidx/compose/ui/ComposedModifierKt.materializeModifier (Landroidx/compose/runtime/Composer;Landroidx/compose/ui/Modifier;)Landroidx/compose/ui/Modifier;
    ASTORE 135
   L314
    LINENUMBER 433 L314
    GETSTATIC androidx/compose/ui/node/ComposeUiNode.Companion : Landroidx/compose/ui/node/ComposeUiNode$Companion;
    INVOKEVIRTUAL androidx/compose/ui/node/ComposeUiNode$Companion.getConstructor ()Lkotlin/jvm/functions/Function0;
    ASTORE 136
    ALOAD 130
    ASTORE 137
    BIPUSH 6
    SIPUSH 896
    ILOAD 131
    BIPUSH 6
    ISHL
    IAND
    IOR
    ISTORE 138
   L315
    LINENUMBER 432 L315
    NOP
   L316
    ICONST_0
    ISTORE 139
   L317
    ALOAD 137
    LDC -553112988
    LDC "CC(ReusableComposeNode)N(factory,update,content)399@15590L9:Composables.kt#9igjgp"
   L318
    LINENUMBER 434 L318
    INVOKESTATIC androidx/compose/runtime/ComposerKt.sourceInformationMarkerStart (Landroidx/compose/runtime/Composer;ILjava/lang/String;)V
   L319
    LINENUMBER 435 L319
    ALOAD 137
    INVOKEINTERFACE androidx/compose/runtime/Composer.getApplier ()Landroidx/compose/runtime/Applier; (itf)
    INSTANCEOF androidx/compose/runtime/Applier
    IFNE L320
    INVOKESTATIC androidx/compose/runtime/ComposablesKt.invalidApplier ()V
   L320
    ALOAD 137
   L321
    LINENUMBER 436 L321
    INVOKEINTERFACE androidx/compose/runtime/Composer.startReusableNode ()V (itf)
   L322
    LINENUMBER 437 L322
    ALOAD 137
    INVOKEINTERFACE androidx/compose/runtime/Composer.getInserting ()Z (itf)
    IFEQ L323
    ALOAD 137
   L324
    LINENUMBER 438 L324
    ALOAD 136
    INVOKEINTERFACE androidx/compose/runtime/Composer.createNode (Lkotlin/jvm/functions/Function0;)V (itf)
    GOTO L325
   L323
    ALOAD 137
   L326
    LINENUMBER 440 L326
    INVOKEINTERFACE androidx/compose/runtime/Composer.useNode ()V (itf)
   L325
    LINENUMBER 442 L325
    ALOAD 137
    INVOKESTATIC androidx/compose/runtime/Updater.constructor-impl (Landroidx/compose/runtime/Composer;)Landroidx/compose/runtime/Composer;
    ASTORE 140
   L327
    ICONST_0
    ISTORE 141
   L328
    LINENUMBER 443 L328
    ALOAD 140
    ALOAD 129
    GETSTATIC androidx/compose/ui/node/ComposeUiNode.Companion : Landroidx/compose/ui/node/ComposeUiNode$Companion;
    INVOKEVIRTUAL androidx/compose/ui/node/ComposeUiNode$Companion.getSetMeasurePolicy ()Lkotlin/jvm/functions/Function2;
    INVOKESTATIC androidx/compose/runtime/Updater.set-impl (Landroidx/compose/runtime/Composer;Ljava/lang/Object;Lkotlin/jvm/functions/Function2;)V
   L329
    LINENUMBER 444 L329
    ALOAD 140
    ALOAD 134
    GETSTATIC androidx/compose/ui/node/ComposeUiNode.Companion : Landroidx/compose/ui/node/ComposeUiNode$Companion;
    INVOKEVIRTUAL androidx/compose/ui/node/ComposeUiNode$Companion.getSetResolvedCompositionLocals ()Lkotlin/jvm/functions/Function2;
    INVOKESTATIC androidx/compose/runtime/Updater.set-impl (Landroidx/compose/runtime/Composer;Ljava/lang/Object;Lkotlin/jvm/functions/Function2;)V
   L330
    LINENUMBER 445 L330
    ALOAD 140
    ILOAD 133
    INVOKESTATIC java/lang/Integer.valueOf (I)Ljava/lang/Integer;
    GETSTATIC androidx/compose/ui/node/ComposeUiNode.Companion : Landroidx/compose/ui/node/ComposeUiNode$Companion;
    INVOKEVIRTUAL androidx/compose/ui/node/ComposeUiNode$Companion.getSetCompositeKeyHash ()Lkotlin/jvm/functions/Function2;
    INVOKESTATIC androidx/compose/runtime/Updater.init-impl (Landroidx/compose/runtime/Composer;Ljava/lang/Object;Lkotlin/jvm/functions/Function2;)V
   L331
    LINENUMBER 446 L331
    ALOAD 140
    GETSTATIC androidx/compose/ui/node/ComposeUiNode.Companion : Landroidx/compose/ui/node/ComposeUiNode$Companion;
    INVOKEVIRTUAL androidx/compose/ui/node/ComposeUiNode$Companion.getApplyOnDeactivatedNodeAssertion ()Lkotlin/jvm/functions/Function1;
    INVOKESTATIC androidx/compose/runtime/Updater.reconcile-impl (Landroidx/compose/runtime/Composer;Lkotlin/jvm/functions/Function1;)V
   L332
    LINENUMBER 447 L332
    ALOAD 140
    ALOAD 135
    GETSTATIC androidx/compose/ui/node/ComposeUiNode.Companion : Landroidx/compose/ui/node/ComposeUiNode$Companion;
    INVOKEVIRTUAL androidx/compose/ui/node/ComposeUiNode$Companion.getSetModifier ()Lkotlin/jvm/functions/Function2;
    INVOKESTATIC androidx/compose/runtime/Updater.set-impl (Landroidx/compose/runtime/Composer;Ljava/lang/Object;Lkotlin/jvm/functions/Function2;)V
   L333
    LINENUMBER 448 L333
    NOP
   L334
    LINENUMBER 442 L334
    NOP
   L335
    LINENUMBER 449 L335
    ALOAD 137
    BIPUSH 14
    ILOAD 138
    BIPUSH 6
    ISHR
    IAND
    ISTORE 142
    ASTORE 143
   L336
    ICONST_0
    ISTORE 144
   L337
    ALOAD 143
    LDC 1833054614
    LDC "C72@3469L9:Box.kt#2w3rfo"
   L338
    LINENUMBER 425 L338
    INVOKESTATIC androidx/compose/runtime/ComposerKt.sourceInformationMarkerStart (Landroidx/compose/runtime/Composer;ILjava/lang/String;)V
    GETSTATIC androidx/compose/foundation/layout/BoxScopeInstance.INSTANCE : Landroidx/compose/foundation/layout/BoxScopeInstance;
    ALOAD 143
    BIPUSH 6
    BIPUSH 112
    ILOAD 124
    BIPUSH 6
    ISHR
    IAND
    IOR
    INVOKESTATIC java/lang/Integer.valueOf (I)Ljava/lang/Integer;
    CHECKCAST java/lang/Number
    INVOKEVIRTUAL java/lang/Number.intValue ()I
    ISTORE 145
    CHECKCAST androidx/compose/runtime/Composer
    ASTORE 146
    CHECKCAST androidx/compose/foundation/layout/BoxScope
    ASTORE 147
   L339
    ICONST_0
    ISTORE 148
   L340
    ALOAD 146
    LDC -396006044
    LDC "C120@4080L297,128@4403L614:ChannelScreen.kt#dnwu2"
   L341
    LINENUMBER 121 L341
    INVOKESTATIC androidx/compose/runtime/ComposerKt.sourceInformationMarkerStart (Landroidx/compose/runtime/Composer;ILjava/lang/String;)V
   L342
    LINENUMBER 123 L342
    GETSTATIC capstone/safeline/ui/theme/ThemeManager.INSTANCE : Lcapstone/safeline/ui/theme/ThemeManager;
    INVOKEVIRTUAL capstone/safeline/ui/theme/ThemeManager.getFontFamily ()Landroidx/compose/ui/text/font/FontFamily;
    ASTORE 149
   L343
    LINENUMBER 124 L343
    GETSTATIC androidx/compose/ui/text/font/FontWeight.Companion : Landroidx/compose/ui/text/font/FontWeight$Companion;
    INVOKEVIRTUAL androidx/compose/ui/text/font/FontWeight$Companion.getBold ()Landroidx/compose/ui/text/font/FontWeight;
    ASTORE 150
   L344
    LINENUMBER 125 L344
    BIPUSH 32
    INVOKESTATIC androidx/compose/ui/unit/TextUnitKt.getSp (I)J
    LSTORE 151
   L345
    LINENUMBER 126 L345
    GETSTATIC androidx/compose/ui/graphics/Color.Companion : Landroidx/compose/ui/graphics/Color$Companion;
    INVOKEVIRTUAL androidx/compose/ui/graphics/Color$Companion.getWhite-0d7_KjU ()J
    LSTORE 153
   L346
    LINENUMBER 122 L346
    ALOAD 3
    ACONST_NULL
   L347
    LINENUMBER 126 L347
    LLOAD 153
   L348
    LINENUMBER 125 L348
    LLOAD 151
    ACONST_NULL
   L349
    LINENUMBER 124 L349
    ALOAD 150
   L350
    LINENUMBER 123 L350
    ALOAD 149
    LCONST_0
    ACONST_NULL
    ACONST_NULL
    LCONST_0
    ICONST_0
    ICONST_0
    ICONST_0
    ICONST_0
    ACONST_NULL
    ACONST_NULL
    ALOAD 146
    LDC 200064
    BIPUSH 14
    ILOAD 7
    BIPUSH 9
    ISHR
    IAND
    IOR
    ICONST_0
    LDC 130962
   L351
    LINENUMBER 121 L351
    INVOKESTATIC androidx/compose/material3/TextKt.Text--4IGK_g (Ljava/lang/String;Landroidx/compose/ui/Modifier;JJLandroidx/compose/ui/text/font/FontStyle;Landroidx/compose/ui/text/font/FontWeight;Landroidx/compose/ui/text/font/FontFamily;JLandroidx/compose/ui/text/style/TextDecoration;Landroidx/compose/ui/text/style/TextAlign;JIZIILkotlin/jvm/functions/Function1;Landroidx/compose/ui/text/TextStyle;Landroidx/compose/runtime/Composer;III)V
   L352
    LINENUMBER 131 L352
    GETSTATIC capstone/safeline/ui/theme/ThemeManager.INSTANCE : Lcapstone/safeline/ui/theme/ThemeManager;
    INVOKEVIRTUAL capstone/safeline/ui/theme/ThemeManager.getFontFamily ()Landroidx/compose/ui/text/font/FontFamily;
    ASTORE 149
   L353
    LINENUMBER 132 L353
    GETSTATIC androidx/compose/ui/text/font/FontWeight.Companion : Landroidx/compose/ui/text/font/FontWeight$Companion;
    INVOKEVIRTUAL androidx/compose/ui/text/font/FontWeight$Companion.getBold ()Landroidx/compose/ui/text/font/FontWeight;
    ASTORE 150
   L354
    LINENUMBER 133 L354
    BIPUSH 32
    INVOKESTATIC androidx/compose/ui/unit/TextUnitKt.getSp (I)J
    LSTORE 151
   L355
    LINENUMBER 134 L355
    GETSTATIC androidx/compose/ui/graphics/Color.Companion : Landroidx/compose/ui/graphics/Color$Companion;
    INVOKEVIRTUAL androidx/compose/ui/graphics/Color$Companion.getTransparent-0d7_KjU ()J
    LSTORE 153
   L356
    LINENUMBER 135 L356
    NEW androidx/compose/ui/text/TextStyle
    DUP
   L357
    LINENUMBER 136 L357
    GETSTATIC androidx/compose/ui/graphics/Brush.Companion : Landroidx/compose/ui/graphics/Brush$Companion;
   L358
    LINENUMBER 137 L358
    ICONST_2
    ANEWARRAY androidx/compose/ui/graphics/Color
    ASTORE 155
    ALOAD 155
    ICONST_0
    LDC 4279083775
    INVOKESTATIC androidx/compose/ui/graphics/ColorKt.Color (J)J
    INVOKESTATIC androidx/compose/ui/graphics/Color.box-impl (J)Landroidx/compose/ui/graphics/Color;
    AASTORE
    ALOAD 155
    ICONST_1
    LDC 4293525759
    INVOKESTATIC androidx/compose/ui/graphics/ColorKt.Color (J)J
    INVOKESTATIC androidx/compose/ui/graphics/Color.box-impl (J)Landroidx/compose/ui/graphics/Color;
    AASTORE
    ALOAD 155
    INVOKESTATIC kotlin/collections/CollectionsKt.listOf ([Ljava/lang/Object;)Ljava/util/List;
   L359
    LINENUMBER 136 L359
    LCONST_0
    LCONST_0
    ICONST_0
    BIPUSH 14
    ACONST_NULL
    INVOKESTATIC androidx/compose/ui/graphics/Brush$Companion.linearGradient-mHitzGk$default (Landroidx/compose/ui/graphics/Brush$Companion;Ljava/util/List;JJIILjava/lang/Object;)Landroidx/compose/ui/graphics/Brush;
   L360
    LINENUMBER 135 L360
    FCONST_0
    LCONST_0
    ACONST_NULL
    ACONST_NULL
    ACONST_NULL
    ACONST_NULL
    ACONST_NULL
    LCONST_0
    ACONST_NULL
    ACONST_NULL
    ACONST_NULL
    LCONST_0
    ACONST_NULL
    ACONST_NULL
   L361
    LINENUMBER 139 L361
    NEW androidx/compose/ui/graphics/drawscope/Stroke
    DUP
    LDC 3.0
    FCONST_0
    ICONST_0
    ICONST_0
    ACONST_NULL
    BIPUSH 30
    ACONST_NULL
    INVOKESPECIAL androidx/compose/ui/graphics/drawscope/Stroke.<init> (FFIILandroidx/compose/ui/graphics/PathEffect;ILkotlin/jvm/internal/DefaultConstructorMarker;)V
    CHECKCAST androidx/compose/ui/graphics/drawscope/DrawStyle
   L362
    LINENUMBER 135 L362
    ICONST_0
    ICONST_0
    LCONST_0
    ACONST_NULL
    ACONST_NULL
    ACONST_NULL
    ICONST_0
    ICONST_0
    ACONST_NULL
    LDC 33521662
    ACONST_NULL
    INVOKESPECIAL androidx/compose/ui/text/TextStyle.<init> (Landroidx/compose/ui/graphics/Brush;FJLandroidx/compose/ui/text/font/FontWeight;Landroidx/compose/ui/text/font/FontStyle;Landroidx/compose/ui/text/font/FontSynthesis;Landroidx/compose/ui/text/font/FontFamily;Ljava/lang/String;JLandroidx/compose/ui/text/style/BaselineShift;Landroidx/compose/ui/text/style/TextGeometricTransform;Landroidx/compose/ui/text/intl/LocaleList;JLandroidx/compose/ui/text/style/TextDecoration;Landroidx/compose/ui/graphics/Shadow;Landroidx/compose/ui/graphics/drawscope/DrawStyle;IIJLandroidx/compose/ui/text/style/TextIndent;Landroidx/compose/ui/text/PlatformTextStyle;Landroidx/compose/ui/text/style/LineHeightStyle;IILandroidx/compose/ui/text/style/TextMotion;ILkotlin/jvm/internal/DefaultConstructorMarker;)V
    ASTORE 156
   L363
    LINENUMBER 130 L363
    ALOAD 3
    ACONST_NULL
   L364
    LINENUMBER 134 L364
    LLOAD 153
   L365
    LINENUMBER 133 L365
    LLOAD 151
    ACONST_NULL
   L366
    LINENUMBER 132 L366
    ALOAD 150
   L367
    LINENUMBER 131 L367
    ALOAD 149
    LCONST_0
    ACONST_NULL
    ACONST_NULL
    LCONST_0
    ICONST_0
    ICONST_0
    ICONST_0
    ICONST_0
    ACONST_NULL
   L368
    LINENUMBER 135 L368
    ALOAD 156
    ALOAD 146
    LDC 200064
    BIPUSH 14
    ILOAD 7
    BIPUSH 9
    ISHR
    IAND
    IOR
    ICONST_0
    LDC 65426
   L369
    LINENUMBER 129 L369
    INVOKESTATIC androidx/compose/material3/TextKt.Text--4IGK_g (Ljava/lang/String;Landroidx/compose/ui/Modifier;JJLandroidx/compose/ui/text/font/FontStyle;Landroidx/compose/ui/text/font/FontWeight;Landroidx/compose/ui/text/font/FontFamily;JLandroidx/compose/ui/text/style/TextDecoration;Landroidx/compose/ui/text/style/TextAlign;JIZIILkotlin/jvm/functions/Function1;Landroidx/compose/ui/text/TextStyle;Landroidx/compose/runtime/Composer;III)V
    ALOAD 146
   L370
    LINENUMBER 121 L370
    INVOKESTATIC androidx/compose/runtime/ComposerKt.sourceInformationMarkerEnd (Landroidx/compose/runtime/Composer;)V
   L371
    LINENUMBER 142 L371
    GOTO L372
   L372
    GETSTATIC kotlin/Unit.INSTANCE : Lkotlin/Unit;
   L373
    LINENUMBER 425 L373
    POP
    ALOAD 143
    INVOKESTATIC androidx/compose/runtime/ComposerKt.sourceInformationMarkerEnd (Landroidx/compose/runtime/Composer;)V
   L374
    LINENUMBER 449 L374
    ALOAD 137
   L375
    LINENUMBER 450 L375
    INVOKEINTERFACE androidx/compose/runtime/Composer.endNode ()V (itf)
    ALOAD 137
   L376
    LINENUMBER 434 L376
    INVOKESTATIC androidx/compose/runtime/ComposerKt.sourceInformationMarkerEnd (Landroidx/compose/runtime/Composer;)V
   L377
    LINENUMBER 451 L377
    NOP
   L378
    ALOAD 130
   L379
    LINENUMBER 428 L379
    INVOKESTATIC androidx/compose/runtime/ComposerKt.sourceInformationMarkerEnd (Landroidx/compose/runtime/Composer;)V
   L380
    LINENUMBER 452 L380
    NOP
   L381
    ALOAD 119
   L382
    LINENUMBER 419 L382
    INVOKESTATIC androidx/compose/runtime/ComposerKt.sourceInformationMarkerEnd (Landroidx/compose/runtime/Composer;)V
   L383
    LINENUMBER 453 L383
    GOTO L384
   L384
    ALOAD 119
   L385
    LINENUMBER 116 L385
    INVOKESTATIC androidx/compose/runtime/ComposerKt.sourceInformationMarkerEnd (Landroidx/compose/runtime/Composer;)V
   L386
    LINENUMBER 143 L386
    GOTO L387
   L387
    GETSTATIC kotlin/Unit.INSTANCE : Lkotlin/Unit;
   L388
    LINENUMBER 394 L388
    POP
    ALOAD 116
    INVOKESTATIC androidx/compose/runtime/ComposerKt.sourceInformationMarkerEnd (Landroidx/compose/runtime/Composer;)V
   L389
    LINENUMBER 418 L389
    ALOAD 110
   L390
    LINENUMBER 454 L390
    INVOKEINTERFACE androidx/compose/runtime/Composer.endNode ()V (itf)
    ALOAD 110
   L391
    LINENUMBER 403 L391
    INVOKESTATIC androidx/compose/runtime/ComposerKt.sourceInformationMarkerEnd (Landroidx/compose/runtime/Composer;)V
   L392
    LINENUMBER 455 L392
    NOP
   L393
    ALOAD 103
   L394
    LINENUMBER 397 L394
    INVOKESTATIC androidx/compose/runtime/ComposerKt.sourceInformationMarkerEnd (Landroidx/compose/runtime/Composer;)V
   L395
    LINENUMBER 456 L395
    NOP
   L396
    ALOAD 92
   L397
    LINENUMBER 386 L397
    INVOKESTATIC androidx/compose/runtime/ComposerKt.sourceInformationMarkerEnd (Landroidx/compose/runtime/Composer;)V
   L398
    LINENUMBER 457 L398
    GOTO L399
   L399
    LINENUMBER 146 L399
    ALOAD 93
    GETSTATIC androidx/compose/ui/Modifier.Companion : Landroidx/compose/ui/Modifier$Companion;
    CHECKCAST androidx/compose/ui/Modifier
   L400
    LINENUMBER 147 L400
    FCONST_0
    ICONST_1
    ACONST_NULL
    INVOKESTATIC androidx/compose/foundation/layout/SizeKt.fillMaxWidth$default (Landroidx/compose/ui/Modifier;FILjava/lang/Object;)Landroidx/compose/ui/Modifier;
   L401
    LINENUMBER 148 L401
    FCONST_1
    ICONST_0
    ICONST_2
    ACONST_NULL
    INVOKESTATIC androidx/compose/foundation/layout/ColumnScope.weight$default (Landroidx/compose/foundation/layout/ColumnScope;Landroidx/compose/ui/Modifier;FZILjava/lang/Object;)Landroidx/compose/ui/Modifier; (itf)
   L402
    LINENUMBER 149 L402
    ICONST_0
    ISTORE 99
   L403
    ICONST_0
    ISTORE 95
   L404
    LINENUMBER 458 L404
    ILOAD 99
    I2F
    INVOKESTATIC androidx/compose/ui/unit/Dp.constructor-impl (F)F
    GOTO L405
   L405
    LINENUMBER 149 L405
    FCONST_0
    ICONST_2
    ACONST_NULL
    INVOKESTATIC androidx/compose/foundation/layout/PaddingKt.padding-VpY3zN4$default (Landroidx/compose/ui/Modifier;FFILjava/lang/Object;)Landroidx/compose/ui/Modifier;
    ASTORE 98
   L406
    LINENUMBER 150 L406
    GETSTATIC androidx/compose/foundation/layout/Arrangement.INSTANCE : Landroidx/compose/foundation/layout/Arrangement;
    BIPUSH 10
    ISTORE 95
   L407
    ICONST_0
    ISTORE 96
   L408
    LINENUMBER 459 L408
    ILOAD 95
    I2F
    INVOKESTATIC androidx/compose/ui/unit/Dp.constructor-impl (F)F
    GOTO L409
   L409
    LINENUMBER 150 L409
    INVOKEVIRTUAL androidx/compose/foundation/layout/Arrangement.spacedBy-0680j_4 (F)Landroidx/compose/foundation/layout/Arrangement$HorizontalOrVertical;
    ASTORE 99
   L410
    LINENUMBER 151 L410
    FCONST_0
    BIPUSH 12
    ISTORE 96
   L411
    ICONST_0
    ISTORE 97
   L412
    LINENUMBER 460 L412
    ILOAD 96
    I2F
    INVOKESTATIC androidx/compose/ui/unit/Dp.constructor-impl (F)F
    GOTO L413
   L413
    LINENUMBER 151 L413
    FCONST_0
    BIPUSH 12
    ISTORE 96
   L414
    ICONST_0
    ISTORE 97
   L415
    LINENUMBER 460 L415
    ILOAD 96
    I2F
    INVOKESTATIC androidx/compose/ui/unit/Dp.constructor-impl (F)F
    GOTO L416
   L416
    LINENUMBER 151 L416
    ICONST_5
    ACONST_NULL
    INVOKESTATIC androidx/compose/foundation/layout/PaddingKt.PaddingValues-a9UjIt4$default (FFFFILjava/lang/Object;)Landroidx/compose/foundation/layout/PaddingValues;
    ASTORE 95
   L417
    LINENUMBER 149 L417
    ALOAD 98
    ACONST_NULL
   L418
    LINENUMBER 151 L418
    ALOAD 95
    ICONST_0
   L419
    LINENUMBER 150 L419
    ALOAD 99
    CHECKCAST androidx/compose/foundation/layout/Arrangement$Vertical
    ACONST_NULL
    ACONST_NULL
    ICONST_0
    ACONST_NULL
    ALOAD 92
    LDC -1179543673
    INVOKEINTERFACE androidx/compose/runtime/Composer.startReplaceGroup (I)V (itf)
    ALOAD 92
    LDC "CC(remember):ChannelScreen.kt#9igjgp"
    INVOKESTATIC androidx/compose/runtime/ComposerKt.sourceInformation (Landroidx/compose/runtime/Composer;Ljava/lang/String;)V
    ALOAD 92
    ASTORE 97
    ICONST_0
    ISTORE 100
   L420
    LINENUMBER 152 L420
    NOP
   L421
    ICONST_0
    ISTORE 101
   L422
    LINENUMBER 461 L422
    ALOAD 97
    INVOKEINTERFACE androidx/compose/runtime/Composer.rememberedValue ()Ljava/lang/Object; (itf)
    ASTORE 102
   L423
    ICONST_0
    ISTORE 103
   L424
    LINENUMBER 462 L424
    ILOAD 100
    IFNE L425
    ALOAD 102
    GETSTATIC androidx/compose/runtime/Composer.Companion : Landroidx/compose/runtime/Composer$Companion;
    INVOKEVIRTUAL androidx/compose/runtime/Composer$Companion.getEmpty ()Ljava/lang/Object;
    IF_ACMPNE L426
   L425
    LINENUMBER 463 L425
    ASTORE 157
    ISTORE 158
    ASTORE 159
    ASTORE 160
    ASTORE 161
    ISTORE 162
    ASTORE 163
    ASTORE 164
    ASTORE 165
    ICONST_0
    ISTORE 104
   L427
    LINENUMBER 152 L427
    ALOAD 8
    INVOKEDYNAMIC invoke(Landroidx/compose/runtime/MutableState;)Lkotlin/jvm/functions/Function1; [
      // handle kind 0x6 : INVOKESTATIC
      java/lang/invoke/LambdaMetafactory.metafactory(Ljava/lang/invoke/MethodHandles$Lookup;Ljava/lang/String;Ljava/lang/invoke/MethodType;Ljava/lang/invoke/MethodType;Ljava/lang/invoke/MethodHandle;Ljava/lang/invoke/MethodType;)Ljava/lang/invoke/CallSite;
      // arguments:
      (Ljava/lang/Object;)Ljava/lang/Object;, 
      // handle kind 0x6 : INVOKESTATIC
      capstone/safeline/ui/ChannelScreenKt.ChannelScreenUI$lambda$27$lambda$26$lambda$25$lambda$15$lambda$14(Landroidx/compose/runtime/MutableState;Landroidx/compose/foundation/lazy/LazyListScope;)Lkotlin/Unit;, 
      (Landroidx/compose/foundation/lazy/LazyListScope;)Lkotlin/Unit;
    ]
    GOTO L428
   L428
    ASTORE 166
    ALOAD 165
    ALOAD 164
    ALOAD 163
    ILOAD 162
    ALOAD 161
    ALOAD 160
    ALOAD 159
    ILOAD 158
    ALOAD 157
    ALOAD 166
   L429
    LINENUMBER 463 L429
    ASTORE 105
   L430
    LINENUMBER 464 L430
    ALOAD 97
    ALOAD 105
    INVOKEINTERFACE androidx/compose/runtime/Composer.updateRememberedValue (Ljava/lang/Object;)V (itf)
   L431
    LINENUMBER 465 L431
    ALOAD 105
   L432
    GOTO L433
   L426
    LINENUMBER 466 L426
    ALOAD 102
   L433
    LINENUMBER 461 L433
    NOP
   L434
    LINENUMBER 461 L434
    GOTO L435
   L435
    LINENUMBER 152 L435
    CHECKCAST kotlin/jvm/functions/Function1
    ASTORE 96
    ALOAD 92
    INVOKEINTERFACE androidx/compose/runtime/Composer.endReplaceGroup ()V (itf)
    ALOAD 96
    ALOAD 92
    LDC 805331328
    SIPUSH 490
   L436
    LINENUMBER 145 L436
    INVOKESTATIC androidx/compose/foundation/lazy/LazyDslKt.LazyColumn (Landroidx/compose/ui/Modifier;Landroidx/compose/foundation/lazy/LazyListState;Landroidx/compose/foundation/layout/PaddingValues;ZLandroidx/compose/foundation/layout/Arrangement$Vertical;Landroidx/compose/ui/Alignment$Horizontal;Landroidx/compose/foundation/gestures/FlingBehavior;ZLandroidx/compose/foundation/OverscrollEffect;Lkotlin/jvm/functions/Function1;Landroidx/compose/runtime/Composer;II)V
   L437
    LINENUMBER 187 L437
    GETSTATIC androidx/compose/ui/Modifier.Companion : Landroidx/compose/ui/Modifier$Companion;
    CHECKCAST androidx/compose/ui/Modifier
   L438
    LINENUMBER 188 L438
    FCONST_0
    ICONST_1
    ACONST_NULL
    INVOKESTATIC androidx/compose/foundation/layout/SizeKt.fillMaxWidth$default (Landroidx/compose/ui/Modifier;FILjava/lang/Object;)Landroidx/compose/ui/Modifier;
   L439
    LINENUMBER 189 L439
    BIPUSH 74
    ISTORE 98
   L440
    ICONST_0
    ISTORE 99
   L441
    LINENUMBER 467 L441
    ILOAD 98
    I2F
    INVOKESTATIC androidx/compose/ui/unit/Dp.constructor-impl (F)F
    GOTO L442
   L442
    LINENUMBER 189 L442
    INVOKESTATIC androidx/compose/foundation/layout/SizeKt.height-3ABfNKs (Landroidx/compose/ui/Modifier;F)Landroidx/compose/ui/Modifier;
    ASTORE 98
    BIPUSH 6
    ISTORE 96
   L443
    LINENUMBER 186 L443
    NOP
   L444
    ICONST_0
    ISTORE 97
   L445
    ALOAD 92
    LDC 1042775818
    LDC "CC(Box)N(modifier,contentAlignment,propagateMinConstraints,content)71@3424L131:Box.kt#2w3rfo"
   L446
    LINENUMBER 468 L446
    INVOKESTATIC androidx/compose/runtime/ComposerKt.sourceInformationMarkerStart (Landroidx/compose/runtime/Composer;ILjava/lang/String;)V
   L447
    LINENUMBER 469 L447
    GETSTATIC androidx/compose/ui/Alignment.Companion : Landroidx/compose/ui/Alignment$Companion;
    INVOKEVIRTUAL androidx/compose/ui/Alignment$Companion.getTopStart ()Landroidx/compose/ui/Alignment;
    ASTORE 99
   L448
    LINENUMBER 470 L448
    ICONST_0
    ISTORE 95
   L449
    LINENUMBER 473 L449
    ALOAD 99
    ILOAD 95
    INVOKESTATIC androidx/compose/foundation/layout/BoxKt.maybeCachedBoxMeasurePolicy (Landroidx/compose/ui/Alignment;Z)Landroidx/compose/ui/layout/MeasurePolicy;
    ASTORE 100
   L450
    LINENUMBER 477 L450
    ALOAD 98
    ASTORE 101
   L451
    LINENUMBER 476 L451
    ALOAD 100
    ASTORE 102
    ALOAD 92
    ASTORE 103
    BIPUSH 112
    ILOAD 96
    ICONST_3
    ISHL
    IAND
    ISTORE 104
   L452
    LINENUMBER 474 L452
    NOP
   L453
    ICONST_0
    ISTORE 105
   L454
    ALOAD 103
    LDC -1159599143
    LDC "CC(Layout)P(!1,2)81@3355L27,84@3521L416:Layout.kt#80mrfh"
   L455
    LINENUMBER 478 L455
    INVOKESTATIC androidx/compose/runtime/ComposerKt.sourceInformationMarkerStart (Landroidx/compose/runtime/Composer;ILjava/lang/String;)V
   L456
    LINENUMBER 479 L456
    ALOAD 103
    ICONST_0
    INVOKESTATIC androidx/compose/runtime/ComposablesKt.getCurrentCompositeKeyHashCode (Landroidx/compose/runtime/Composer;I)J
    INVOKESTATIC java/lang/Long.hashCode (J)I
    ISTORE 106
   L457
    ALOAD 103
   L458
    LINENUMBER 480 L458
    INVOKEINTERFACE androidx/compose/runtime/Composer.getCurrentCompositionLocalMap ()Landroidx/compose/runtime/CompositionLocalMap; (itf)
    ASTORE 107
   L459
    ALOAD 103
   L460
    LINENUMBER 481 L460
    ALOAD 101
    INVOKESTATIC androidx/compose/ui/ComposedModifierKt.materializeModifier (Landroidx/compose/runtime/Composer;Landroidx/compose/ui/Modifier;)Landroidx/compose/ui/Modifier;
    ASTORE 108
   L461
    LINENUMBER 483 L461
    GETSTATIC androidx/compose/ui/node/ComposeUiNode.Companion : Landroidx/compose/ui/node/ComposeUiNode$Companion;
    INVOKEVIRTUAL androidx/compose/ui/node/ComposeUiNode$Companion.getConstructor ()Lkotlin/jvm/functions/Function0;
    ASTORE 109
    ALOAD 103
    ASTORE 110
    BIPUSH 6
    SIPUSH 896
    ILOAD 104
    BIPUSH 6
    ISHL
    IAND
    IOR
    ISTORE 111
   L462
    LINENUMBER 482 L462
    NOP
   L463
    ICONST_0
    ISTORE 112
   L464
    ALOAD 110
    LDC -553112988
    LDC "CC(ReusableComposeNode)N(factory,update,content)399@15590L9:Composables.kt#9igjgp"
   L465
    LINENUMBER 484 L465
    INVOKESTATIC androidx/compose/runtime/ComposerKt.sourceInformationMarkerStart (Landroidx/compose/runtime/Composer;ILjava/lang/String;)V
   L466
    LINENUMBER 485 L466
    ALOAD 110
    INVOKEINTERFACE androidx/compose/runtime/Composer.getApplier ()Landroidx/compose/runtime/Applier; (itf)
    INSTANCEOF androidx/compose/runtime/Applier
    IFNE L467
    INVOKESTATIC androidx/compose/runtime/ComposablesKt.invalidApplier ()V
   L467
    ALOAD 110
   L468
    LINENUMBER 486 L468
    INVOKEINTERFACE androidx/compose/runtime/Composer.startReusableNode ()V (itf)
   L469
    LINENUMBER 487 L469
    ALOAD 110
    INVOKEINTERFACE androidx/compose/runtime/Composer.getInserting ()Z (itf)
    IFEQ L470
    ALOAD 110
   L471
    LINENUMBER 488 L471
    ALOAD 109
    INVOKEINTERFACE androidx/compose/runtime/Composer.createNode (Lkotlin/jvm/functions/Function0;)V (itf)
    GOTO L472
   L470
    ALOAD 110
   L473
    LINENUMBER 490 L473
    INVOKEINTERFACE androidx/compose/runtime/Composer.useNode ()V (itf)
   L472
    LINENUMBER 492 L472
    ALOAD 110
    INVOKESTATIC androidx/compose/runtime/Updater.constructor-impl (Landroidx/compose/runtime/Composer;)Landroidx/compose/runtime/Composer;
    ASTORE 113
   L474
    ICONST_0
    ISTORE 114
   L475
    LINENUMBER 493 L475
    ALOAD 113
    ALOAD 102
    GETSTATIC androidx/compose/ui/node/ComposeUiNode.Companion : Landroidx/compose/ui/node/ComposeUiNode$Companion;
    INVOKEVIRTUAL androidx/compose/ui/node/ComposeUiNode$Companion.getSetMeasurePolicy ()Lkotlin/jvm/functions/Function2;
    INVOKESTATIC androidx/compose/runtime/Updater.set-impl (Landroidx/compose/runtime/Composer;Ljava/lang/Object;Lkotlin/jvm/functions/Function2;)V
   L476
    LINENUMBER 494 L476
    ALOAD 113
    ALOAD 107
    GETSTATIC androidx/compose/ui/node/ComposeUiNode.Companion : Landroidx/compose/ui/node/ComposeUiNode$Companion;
    INVOKEVIRTUAL androidx/compose/ui/node/ComposeUiNode$Companion.getSetResolvedCompositionLocals ()Lkotlin/jvm/functions/Function2;
    INVOKESTATIC androidx/compose/runtime/Updater.set-impl (Landroidx/compose/runtime/Composer;Ljava/lang/Object;Lkotlin/jvm/functions/Function2;)V
   L477
    LINENUMBER 495 L477
    ALOAD 113
    ILOAD 106
    INVOKESTATIC java/lang/Integer.valueOf (I)Ljava/lang/Integer;
    GETSTATIC androidx/compose/ui/node/ComposeUiNode.Companion : Landroidx/compose/ui/node/ComposeUiNode$Companion;
    INVOKEVIRTUAL androidx/compose/ui/node/ComposeUiNode$Companion.getSetCompositeKeyHash ()Lkotlin/jvm/functions/Function2;
    INVOKESTATIC androidx/compose/runtime/Updater.init-impl (Landroidx/compose/runtime/Composer;Ljava/lang/Object;Lkotlin/jvm/functions/Function2;)V
   L478
    LINENUMBER 496 L478
    ALOAD 113
    GETSTATIC androidx/compose/ui/node/ComposeUiNode.Companion : Landroidx/compose/ui/node/ComposeUiNode$Companion;
    INVOKEVIRTUAL androidx/compose/ui/node/ComposeUiNode$Companion.getApplyOnDeactivatedNodeAssertion ()Lkotlin/jvm/functions/Function1;
    INVOKESTATIC androidx/compose/runtime/Updater.reconcile-impl (Landroidx/compose/runtime/Composer;Lkotlin/jvm/functions/Function1;)V
   L479
    LINENUMBER 497 L479
    ALOAD 113
    ALOAD 108
    GETSTATIC androidx/compose/ui/node/ComposeUiNode.Companion : Landroidx/compose/ui/node/ComposeUiNode$Companion;
    INVOKEVIRTUAL androidx/compose/ui/node/ComposeUiNode$Companion.getSetModifier ()Lkotlin/jvm/functions/Function2;
    INVOKESTATIC androidx/compose/runtime/Updater.set-impl (Landroidx/compose/runtime/Composer;Ljava/lang/Object;Lkotlin/jvm/functions/Function2;)V
   L480
    LINENUMBER 498 L480
    NOP
   L481
    LINENUMBER 492 L481
    NOP
   L482
    LINENUMBER 499 L482
    ALOAD 110
    BIPUSH 14
    ILOAD 111
    BIPUSH 6
    ISHR
    IAND
    ISTORE 115
    ASTORE 116
   L483
    ICONST_0
    ISTORE 117
   L484
    ALOAD 116
    LDC 1833054614
    LDC "C72@3469L9:Box.kt#2w3rfo"
   L485
    LINENUMBER 475 L485
    INVOKESTATIC androidx/compose/runtime/ComposerKt.sourceInformationMarkerStart (Landroidx/compose/runtime/Composer;ILjava/lang/String;)V
    GETSTATIC androidx/compose/foundation/layout/BoxScopeInstance.INSTANCE : Landroidx/compose/foundation/layout/BoxScopeInstance;
    ALOAD 116
    BIPUSH 6
    BIPUSH 112
    ILOAD 96
    BIPUSH 6
    ISHR
    IAND
    IOR
    INVOKESTATIC java/lang/Integer.valueOf (I)Ljava/lang/Integer;
    CHECKCAST java/lang/Number
    INVOKEVIRTUAL java/lang/Number.intValue ()I
    ISTORE 118
    CHECKCAST androidx/compose/runtime/Composer
    ASTORE 119
    CHECKCAST androidx/compose/foundation/layout/BoxScope
    ASTORE 120
   L486
    ICONST_0
    ISTORE 121
   L487
    ALOAD 119
    LDC -2062475328
    LDC "C191@7199L44,190@7158L281,197@7461L2909:ChannelScreen.kt#dnwu2"
   L488
    LINENUMBER 191 L488
    INVOKESTATIC androidx/compose/runtime/ComposerKt.sourceInformationMarkerStart (Landroidx/compose/runtime/Composer;ILjava/lang/String;)V
   L489
    LINENUMBER 192 L489
    GETSTATIC capstone/safeline/R$drawable.input_background : I
    ALOAD 119
    ICONST_0
    INVOKESTATIC androidx/compose/ui/res/PainterResources_androidKt.painterResource (ILandroidx/compose/runtime/Composer;I)Landroidx/compose/ui/graphics/painter/Painter;
   L490
    LINENUMBER 193 L490
    ACONST_NULL
   L491
    LINENUMBER 194 L491
    GETSTATIC androidx/compose/ui/Modifier.Companion : Landroidx/compose/ui/Modifier$Companion;
    CHECKCAST androidx/compose/ui/Modifier
    FCONST_0
    ICONST_1
    ACONST_NULL
    INVOKESTATIC androidx/compose/foundation/layout/SizeKt.fillMaxSize$default (Landroidx/compose/ui/Modifier;FILjava/lang/Object;)Landroidx/compose/ui/Modifier;
    ACONST_NULL
   L492
    LINENUMBER 195 L492
    GETSTATIC androidx/compose/ui/layout/ContentScale.Companion : Landroidx/compose/ui/layout/ContentScale$Companion;
    INVOKEVIRTUAL androidx/compose/ui/layout/ContentScale$Companion.getFillBounds ()Landroidx/compose/ui/layout/ContentScale;
    FCONST_0
    ACONST_NULL
    ALOAD 119
    SIPUSH 25008
    GETSTATIC androidx/compose/ui/graphics/painter/Painter.$stable : I
    IOR
    BIPUSH 104
   L493
    LINENUMBER 191 L493
    INVOKESTATIC androidx/compose/foundation/ImageKt.Image (Landroidx/compose/ui/graphics/painter/Painter;Ljava/lang/String;Landroidx/compose/ui/Modifier;Landroidx/compose/ui/Alignment;Landroidx/compose/ui/layout/ContentScale;FLandroidx/compose/ui/graphics/ColorFilter;Landroidx/compose/runtime/Composer;II)V
   L494
    LINENUMBER 199 L494
    GETSTATIC androidx/compose/ui/Modifier.Companion : Landroidx/compose/ui/Modifier$Companion;
    CHECKCAST androidx/compose/ui/Modifier
   L495
    LINENUMBER 200 L495
    FCONST_0
    ICONST_1
    ACONST_NULL
    INVOKESTATIC androidx/compose/foundation/layout/SizeKt.fillMaxSize$default (Landroidx/compose/ui/Modifier;FILjava/lang/Object;)Landroidx/compose/ui/Modifier;
   L496
    LINENUMBER 201 L496
    ICONST_0
    ISTORE 122
   L497
    ICONST_0
    ISTORE 123
   L498
    LINENUMBER 500 L498
    ILOAD 122
    I2F
    INVOKESTATIC androidx/compose/ui/unit/Dp.constructor-impl (F)F
    GOTO L499
   L499
    LINENUMBER 201 L499
    FCONST_0
    ICONST_2
    ACONST_NULL
    INVOKESTATIC androidx/compose/foundation/layout/PaddingKt.padding-VpY3zN4$default (Landroidx/compose/ui/Modifier;FFILjava/lang/Object;)Landroidx/compose/ui/Modifier;
    ASTORE 122
   L500
    LINENUMBER 202 L500
    GETSTATIC androidx/compose/ui/Alignment.Companion : Landroidx/compose/ui/Alignment$Companion;
    INVOKEVIRTUAL androidx/compose/ui/Alignment$Companion.getCenterVertically ()Landroidx/compose/ui/Alignment$Vertical;
    ASTORE 124
    SIPUSH 390
    ISTORE 125
   L501
    LINENUMBER 198 L501
    NOP
   L502
    ICONST_0
    ISTORE 126
   L503
    ALOAD 119
    LDC 844473419
    LDC "CC(Row)N(modifier,horizontalArrangement,verticalAlignment,content)99@5125L58,100@5188L131:Row.kt#2w3rfo"
   L504
    LINENUMBER 501 L504
    INVOKESTATIC androidx/compose/runtime/ComposerKt.sourceInformationMarkerStart (Landroidx/compose/runtime/Composer;ILjava/lang/String;)V
   L505
    LINENUMBER 502 L505
    GETSTATIC androidx/compose/foundation/layout/Arrangement.INSTANCE : Landroidx/compose/foundation/layout/Arrangement;
    INVOKEVIRTUAL androidx/compose/foundation/layout/Arrangement.getStart ()Landroidx/compose/foundation/layout/Arrangement$Horizontal;
    ASTORE 123
   L506
    LINENUMBER 506 L506
    ALOAD 123
    ALOAD 124
    ALOAD 119
    BIPUSH 14
    ILOAD 125
    ICONST_3
    ISHR
    IAND
    BIPUSH 112
    ILOAD 125
    ICONST_3
    ISHR
    IAND
    IOR
    INVOKESTATIC androidx/compose/foundation/layout/RowKt.rowMeasurePolicy (Landroidx/compose/foundation/layout/Arrangement$Horizontal;Landroidx/compose/ui/Alignment$Vertical;Landroidx/compose/runtime/Composer;I)Landroidx/compose/ui/layout/MeasurePolicy;
    ASTORE 127
   L507
    LINENUMBER 510 L507
    ALOAD 122
    ASTORE 128
   L508
    LINENUMBER 509 L508
    ALOAD 127
    ASTORE 129
    ALOAD 119
    ASTORE 130
    BIPUSH 112
    ILOAD 125
    ICONST_3
    ISHL
    IAND
    ISTORE 131
   L509
    LINENUMBER 507 L509
    NOP
   L510
    ICONST_0
    ISTORE 132
   L511
    ALOAD 130
    LDC -1159599143
    LDC "CC(Layout)P(!1,2)81@3355L27,84@3521L416:Layout.kt#80mrfh"
   L512
    LINENUMBER 511 L512
    INVOKESTATIC androidx/compose/runtime/ComposerKt.sourceInformationMarkerStart (Landroidx/compose/runtime/Composer;ILjava/lang/String;)V
   L513
    LINENUMBER 512 L513
    ALOAD 130
    ICONST_0
    INVOKESTATIC androidx/compose/runtime/ComposablesKt.getCurrentCompositeKeyHashCode (Landroidx/compose/runtime/Composer;I)J
    INVOKESTATIC java/lang/Long.hashCode (J)I
    ISTORE 133
   L514
    ALOAD 130
   L515
    LINENUMBER 513 L515
    INVOKEINTERFACE androidx/compose/runtime/Composer.getCurrentCompositionLocalMap ()Landroidx/compose/runtime/CompositionLocalMap; (itf)
    ASTORE 134
   L516
    ALOAD 130
   L517
    LINENUMBER 514 L517
    ALOAD 128
    INVOKESTATIC androidx/compose/ui/ComposedModifierKt.materializeModifier (Landroidx/compose/runtime/Composer;Landroidx/compose/ui/Modifier;)Landroidx/compose/ui/Modifier;
    ASTORE 135
   L518
    LINENUMBER 516 L518
    GETSTATIC androidx/compose/ui/node/ComposeUiNode.Companion : Landroidx/compose/ui/node/ComposeUiNode$Companion;
    INVOKEVIRTUAL androidx/compose/ui/node/ComposeUiNode$Companion.getConstructor ()Lkotlin/jvm/functions/Function0;
    ASTORE 136
    ALOAD 130
    ASTORE 137
    BIPUSH 6
    SIPUSH 896
    ILOAD 131
    BIPUSH 6
    ISHL
    IAND
    IOR
    ISTORE 138
   L519
    LINENUMBER 515 L519
    NOP
   L520
    ICONST_0
    ISTORE 139
   L521
    ALOAD 137
    LDC -553112988
    LDC "CC(ReusableComposeNode)N(factory,update,content)399@15590L9:Composables.kt#9igjgp"
   L522
    LINENUMBER 517 L522
    INVOKESTATIC androidx/compose/runtime/ComposerKt.sourceInformationMarkerStart (Landroidx/compose/runtime/Composer;ILjava/lang/String;)V
   L523
    LINENUMBER 518 L523
    ALOAD 137
    INVOKEINTERFACE androidx/compose/runtime/Composer.getApplier ()Landroidx/compose/runtime/Applier; (itf)
    INSTANCEOF androidx/compose/runtime/Applier
    IFNE L524
    INVOKESTATIC androidx/compose/runtime/ComposablesKt.invalidApplier ()V
   L524
    ALOAD 137
   L525
    LINENUMBER 519 L525
    INVOKEINTERFACE androidx/compose/runtime/Composer.startReusableNode ()V (itf)
   L526
    LINENUMBER 520 L526
    ALOAD 137
    INVOKEINTERFACE androidx/compose/runtime/Composer.getInserting ()Z (itf)
    IFEQ L527
    ALOAD 137
   L528
    LINENUMBER 521 L528
    ALOAD 136
    INVOKEINTERFACE androidx/compose/runtime/Composer.createNode (Lkotlin/jvm/functions/Function0;)V (itf)
    GOTO L529
   L527
    ALOAD 137
   L530
    LINENUMBER 523 L530
    INVOKEINTERFACE androidx/compose/runtime/Composer.useNode ()V (itf)
   L529
    LINENUMBER 525 L529
    ALOAD 137
    INVOKESTATIC androidx/compose/runtime/Updater.constructor-impl (Landroidx/compose/runtime/Composer;)Landroidx/compose/runtime/Composer;
    ASTORE 140
   L531
    ICONST_0
    ISTORE 141
   L532
    LINENUMBER 526 L532
    ALOAD 140
    ALOAD 129
    GETSTATIC androidx/compose/ui/node/ComposeUiNode.Companion : Landroidx/compose/ui/node/ComposeUiNode$Companion;
    INVOKEVIRTUAL androidx/compose/ui/node/ComposeUiNode$Companion.getSetMeasurePolicy ()Lkotlin/jvm/functions/Function2;
    INVOKESTATIC androidx/compose/runtime/Updater.set-impl (Landroidx/compose/runtime/Composer;Ljava/lang/Object;Lkotlin/jvm/functions/Function2;)V
   L533
    LINENUMBER 527 L533
    ALOAD 140
    ALOAD 134
    GETSTATIC androidx/compose/ui/node/ComposeUiNode.Companion : Landroidx/compose/ui/node/ComposeUiNode$Companion;
    INVOKEVIRTUAL androidx/compose/ui/node/ComposeUiNode$Companion.getSetResolvedCompositionLocals ()Lkotlin/jvm/functions/Function2;
    INVOKESTATIC androidx/compose/runtime/Updater.set-impl (Landroidx/compose/runtime/Composer;Ljava/lang/Object;Lkotlin/jvm/functions/Function2;)V
   L534
    LINENUMBER 528 L534
    ALOAD 140
    ILOAD 133
    INVOKESTATIC java/lang/Integer.valueOf (I)Ljava/lang/Integer;
    GETSTATIC androidx/compose/ui/node/ComposeUiNode.Companion : Landroidx/compose/ui/node/ComposeUiNode$Companion;
    INVOKEVIRTUAL androidx/compose/ui/node/ComposeUiNode$Companion.getSetCompositeKeyHash ()Lkotlin/jvm/functions/Function2;
    INVOKESTATIC androidx/compose/runtime/Updater.init-impl (Landroidx/compose/runtime/Composer;Ljava/lang/Object;Lkotlin/jvm/functions/Function2;)V
   L535
    LINENUMBER 529 L535
    ALOAD 140
    GETSTATIC androidx/compose/ui/node/ComposeUiNode.Companion : Landroidx/compose/ui/node/ComposeUiNode$Companion;
    INVOKEVIRTUAL androidx/compose/ui/node/ComposeUiNode$Companion.getApplyOnDeactivatedNodeAssertion ()Lkotlin/jvm/functions/Function1;
    INVOKESTATIC androidx/compose/runtime/Updater.reconcile-impl (Landroidx/compose/runtime/Composer;Lkotlin/jvm/functions/Function1;)V
   L536
    LINENUMBER 530 L536
    ALOAD 140
    ALOAD 135
    GETSTATIC androidx/compose/ui/node/ComposeUiNode.Companion : Landroidx/compose/ui/node/ComposeUiNode$Companion;
    INVOKEVIRTUAL androidx/compose/ui/node/ComposeUiNode$Companion.getSetModifier ()Lkotlin/jvm/functions/Function2;
    INVOKESTATIC androidx/compose/runtime/Updater.set-impl (Landroidx/compose/runtime/Composer;Ljava/lang/Object;Lkotlin/jvm/functions/Function2;)V
   L537
    LINENUMBER 531 L537
    NOP
   L538
    LINENUMBER 525 L538
    NOP
   L539
    LINENUMBER 532 L539
    ALOAD 137
    BIPUSH 14
    ILOAD 138
    BIPUSH 6
    ISHR
    IAND
    ISTORE 142
    ASTORE 143
   L540
    ICONST_0
    ISTORE 144
   L541
    ALOAD 143
    LDC 1456264949
    LDC "C101@5233L9:Row.kt#2w3rfo"
   L542
    LINENUMBER 508 L542
    INVOKESTATIC androidx/compose/runtime/ComposerKt.sourceInformationMarkerStart (Landroidx/compose/runtime/Composer;ILjava/lang/String;)V
    GETSTATIC androidx/compose/foundation/layout/RowScopeInstance.INSTANCE : Landroidx/compose/foundation/layout/RowScopeInstance;
    ALOAD 143
    BIPUSH 6
    BIPUSH 112
    ILOAD 125
    BIPUSH 6
    ISHR
    IAND
    IOR
    INVOKESTATIC java/lang/Integer.valueOf (I)Ljava/lang/Integer;
    CHECKCAST java/lang/Number
    INVOKEVIRTUAL java/lang/Number.intValue ()I
    ISTORE 145
    CHECKCAST androidx/compose/runtime/Composer
    ASTORE 146
    CHECKCAST androidx/compose/foundation/layout/RowScope
    ASTORE 147
   L543
    ICONST_0
    ISTORE 148
   L544
    ALOAD 146
    LDC -392334094
    LDC "C203@7729L1381,231@9136L39,234@9246L34,238@9473L3,233@9201L362,242@9589L40,245@9700L40,249@9933L389,244@9655L693:ChannelScreen.kt#dnwu2"
   L545
    LINENUMBER 204 L545
    INVOKESTATIC androidx/compose/runtime/ComposerKt.sourceInformationMarkerStart (Landroidx/compose/runtime/Composer;ILjava/lang/String;)V
   L546
    LINENUMBER 205 L546
    ALOAD 147
    GETSTATIC androidx/compose/ui/Modifier.Companion : Landroidx/compose/ui/Modifier$Companion;
    CHECKCAST androidx/compose/ui/Modifier
   L547
    LINENUMBER 206 L547
    FCONST_1
    ICONST_0
    ICONST_2
    ACONST_NULL
    INVOKESTATIC androidx/compose/foundation/layout/RowScope.weight$default (Landroidx/compose/foundation/layout/RowScope;Landroidx/compose/ui/Modifier;FZILjava/lang/Object;)Landroidx/compose/ui/Modifier; (itf)
   L548
    LINENUMBER 207 L548
    BIPUSH 46
    ISTORE 149
   L549
    ICONST_0
    ISTORE 150
   L550
    LINENUMBER 533 L550
    ILOAD 149
    I2F
    INVOKESTATIC androidx/compose/ui/unit/Dp.constructor-impl (F)F
    GOTO L551
   L551
    LINENUMBER 207 L551
    INVOKESTATIC androidx/compose/foundation/layout/SizeKt.height-3ABfNKs (Landroidx/compose/ui/Modifier;F)Landroidx/compose/ui/Modifier;
    ASTORE 149
    ICONST_0
    ISTORE 167
   L552
    LINENUMBER 204 L552
    NOP
   L553
    ICONST_0
    ISTORE 168
   L554
    ALOAD 146
    LDC 1042775818
    LDC "CC(Box)N(modifier,contentAlignment,propagateMinConstraints,content)71@3424L131:Box.kt#2w3rfo"
   L555
    LINENUMBER 534 L555
    INVOKESTATIC androidx/compose/runtime/ComposerKt.sourceInformationMarkerStart (Landroidx/compose/runtime/Composer;ILjava/lang/String;)V
   L556
    LINENUMBER 535 L556
    GETSTATIC androidx/compose/ui/Alignment.Companion : Landroidx/compose/ui/Alignment$Companion;
    INVOKEVIRTUAL androidx/compose/ui/Alignment$Companion.getTopStart ()Landroidx/compose/ui/Alignment;
    ASTORE 150
   L557
    LINENUMBER 536 L557
    ICONST_0
    ISTORE 169
   L558
    LINENUMBER 539 L558
    ALOAD 150
    ILOAD 169
    INVOKESTATIC androidx/compose/foundation/layout/BoxKt.maybeCachedBoxMeasurePolicy (Landroidx/compose/ui/Alignment;Z)Landroidx/compose/ui/layout/MeasurePolicy;
    ASTORE 170
   L559
    LINENUMBER 543 L559
    ALOAD 149
    ASTORE 155
   L560
    LINENUMBER 542 L560
    ALOAD 170
    ASTORE 156
    ALOAD 146
    ASTORE 171
    BIPUSH 112
    ILOAD 167
    ICONST_3
    ISHL
    IAND
    ISTORE 172
   L561
    LINENUMBER 540 L561
    NOP
   L562
    ICONST_0
    ISTORE 173
   L563
    ALOAD 171
    LDC -1159599143
    LDC "CC(Layout)P(!1,2)81@3355L27,84@3521L416:Layout.kt#80mrfh"
   L564
    LINENUMBER 544 L564
    INVOKESTATIC androidx/compose/runtime/ComposerKt.sourceInformationMarkerStart (Landroidx/compose/runtime/Composer;ILjava/lang/String;)V
   L565
    LINENUMBER 545 L565
    ALOAD 171
    ICONST_0
    INVOKESTATIC androidx/compose/runtime/ComposablesKt.getCurrentCompositeKeyHashCode (Landroidx/compose/runtime/Composer;I)J
    INVOKESTATIC java/lang/Long.hashCode (J)I
    ISTORE 174
   L566
    ALOAD 171
   L567
    LINENUMBER 546 L567
    INVOKEINTERFACE androidx/compose/runtime/Composer.getCurrentCompositionLocalMap ()Landroidx/compose/runtime/CompositionLocalMap; (itf)
    ASTORE 175
   L568
    ALOAD 171
   L569
    LINENUMBER 547 L569
    ALOAD 155
    INVOKESTATIC androidx/compose/ui/ComposedModifierKt.materializeModifier (Landroidx/compose/runtime/Composer;Landroidx/compose/ui/Modifier;)Landroidx/compose/ui/Modifier;
    ASTORE 176
   L570
    LINENUMBER 549 L570
    GETSTATIC androidx/compose/ui/node/ComposeUiNode.Companion : Landroidx/compose/ui/node/ComposeUiNode$Companion;
    INVOKEVIRTUAL androidx/compose/ui/node/ComposeUiNode$Companion.getConstructor ()Lkotlin/jvm/functions/Function0;
    ASTORE 177
    ALOAD 171
    ASTORE 178
    BIPUSH 6
    SIPUSH 896
    ILOAD 172
    BIPUSH 6
    ISHL
    IAND
    IOR
    ISTORE 179
   L571
    LINENUMBER 548 L571
    NOP
   L572
    ICONST_0
    ISTORE 180
   L573
    ALOAD 178
    LDC -553112988
    LDC "CC(ReusableComposeNode)N(factory,update,content)399@15590L9:Composables.kt#9igjgp"
   L574
    LINENUMBER 550 L574
    INVOKESTATIC androidx/compose/runtime/ComposerKt.sourceInformationMarkerStart (Landroidx/compose/runtime/Composer;ILjava/lang/String;)V
   L575
    LINENUMBER 551 L575
    ALOAD 178
    INVOKEINTERFACE androidx/compose/runtime/Composer.getApplier ()Landroidx/compose/runtime/Applier; (itf)
    INSTANCEOF androidx/compose/runtime/Applier
    IFNE L576
    INVOKESTATIC androidx/compose/runtime/ComposablesKt.invalidApplier ()V
   L576
    ALOAD 178
   L577
    LINENUMBER 552 L577
    INVOKEINTERFACE androidx/compose/runtime/Composer.startReusableNode ()V (itf)
   L578
    LINENUMBER 553 L578
    ALOAD 178
    INVOKEINTERFACE androidx/compose/runtime/Composer.getInserting ()Z (itf)
    IFEQ L579
    ALOAD 178
   L580
    LINENUMBER 554 L580
    ALOAD 177
    INVOKEINTERFACE androidx/compose/runtime/Composer.createNode (Lkotlin/jvm/functions/Function0;)V (itf)
    GOTO L581
   L579
    ALOAD 178
   L582
    LINENUMBER 556 L582
    INVOKEINTERFACE androidx/compose/runtime/Composer.useNode ()V (itf)
   L581
    LINENUMBER 558 L581
    ALOAD 178
    INVOKESTATIC androidx/compose/runtime/Updater.constructor-impl (Landroidx/compose/runtime/Composer;)Landroidx/compose/runtime/Composer;
    ASTORE 181
   L583
    ICONST_0
    ISTORE 182
   L584
    LINENUMBER 559 L584
    ALOAD 181
    ALOAD 156
    GETSTATIC androidx/compose/ui/node/ComposeUiNode.Companion : Landroidx/compose/ui/node/ComposeUiNode$Companion;
    INVOKEVIRTUAL androidx/compose/ui/node/ComposeUiNode$Companion.getSetMeasurePolicy ()Lkotlin/jvm/functions/Function2;
    INVOKESTATIC androidx/compose/runtime/Updater.set-impl (Landroidx/compose/runtime/Composer;Ljava/lang/Object;Lkotlin/jvm/functions/Function2;)V
   L585
    LINENUMBER 560 L585
    ALOAD 181
    ALOAD 175
    GETSTATIC androidx/compose/ui/node/ComposeUiNode.Companion : Landroidx/compose/ui/node/ComposeUiNode$Companion;
    INVOKEVIRTUAL androidx/compose/ui/node/ComposeUiNode$Companion.getSetResolvedCompositionLocals ()Lkotlin/jvm/functions/Function2;
    INVOKESTATIC androidx/compose/runtime/Updater.set-impl (Landroidx/compose/runtime/Composer;Ljava/lang/Object;Lkotlin/jvm/functions/Function2;)V
   L586
    LINENUMBER 561 L586
    ALOAD 181
    ILOAD 174
    INVOKESTATIC java/lang/Integer.valueOf (I)Ljava/lang/Integer;
    GETSTATIC androidx/compose/ui/node/ComposeUiNode.Companion : Landroidx/compose/ui/node/ComposeUiNode$Companion;
    INVOKEVIRTUAL androidx/compose/ui/node/ComposeUiNode$Companion.getSetCompositeKeyHash ()Lkotlin/jvm/functions/Function2;
    INVOKESTATIC androidx/compose/runtime/Updater.init-impl (Landroidx/compose/runtime/Composer;Ljava/lang/Object;Lkotlin/jvm/functions/Function2;)V
   L587
    LINENUMBER 562 L587
    ALOAD 181
    GETSTATIC androidx/compose/ui/node/ComposeUiNode.Companion : Landroidx/compose/ui/node/ComposeUiNode$Companion;
    INVOKEVIRTUAL androidx/compose/ui/node/ComposeUiNode$Companion.getApplyOnDeactivatedNodeAssertion ()Lkotlin/jvm/functions/Function1;
    INVOKESTATIC androidx/compose/runtime/Updater.reconcile-impl (Landroidx/compose/runtime/Composer;Lkotlin/jvm/functions/Function1;)V
   L588
    LINENUMBER 563 L588
    ALOAD 181
    ALOAD 176
    GETSTATIC androidx/compose/ui/node/ComposeUiNode.Companion : Landroidx/compose/ui/node/ComposeUiNode$Companion;
    INVOKEVIRTUAL androidx/compose/ui/node/ComposeUiNode$Companion.getSetModifier ()Lkotlin/jvm/functions/Function2;
    INVOKESTATIC androidx/compose/runtime/Updater.set-impl (Landroidx/compose/runtime/Composer;Ljava/lang/Object;Lkotlin/jvm/functions/Function2;)V
   L589
    LINENUMBER 564 L589
    NOP
   L590
    LINENUMBER 558 L590
    NOP
   L591
    LINENUMBER 565 L591
    ALOAD 178
    BIPUSH 14
    ILOAD 179
    BIPUSH 6
    ISHR
    IAND
    ISTORE 183
    ASTORE 184
   L592
    ICONST_0
    ISTORE 185
   L593
    ALOAD 184
    LDC 1833054614
    LDC "C72@3469L9:Box.kt#2w3rfo"
   L594
    LINENUMBER 541 L594
    INVOKESTATIC androidx/compose/runtime/ComposerKt.sourceInformationMarkerStart (Landroidx/compose/runtime/Composer;ILjava/lang/String;)V
    GETSTATIC androidx/compose/foundation/layout/BoxScopeInstance.INSTANCE : Landroidx/compose/foundation/layout/BoxScopeInstance;
    ALOAD 184
    BIPUSH 6
    BIPUSH 112
    ILOAD 167
    BIPUSH 6
    ISHR
    IAND
    IOR
    INVOKESTATIC java/lang/Integer.valueOf (I)Ljava/lang/Integer;
    CHECKCAST java/lang/Number
    INVOKEVIRTUAL java/lang/Number.intValue ()I
    ISTORE 186
    CHECKCAST androidx/compose/runtime/Composer
    ASTORE 187
    CHECKCAST androidx/compose/foundation/layout/BoxScope
    ASTORE 188
   L595
    ICONST_0
    ISTORE 189
   L596
    ALOAD 187
    LDC 1838496139
    LDC "C209@7978L37,208@7929L242,216@8333L13,221@8653L401,214@8228L856:ChannelScreen.kt#dnwu2"
   L597
    LINENUMBER 209 L597
    INVOKESTATIC androidx/compose/runtime/ComposerKt.sourceInformationMarkerStart (Landroidx/compose/runtime/Composer;ILjava/lang/String;)V
   L598
    LINENUMBER 210 L598
    GETSTATIC capstone/safeline/R$drawable.input_box : I
    ALOAD 187
    ICONST_0
    INVOKESTATIC androidx/compose/ui/res/PainterResources_androidKt.painterResource (ILandroidx/compose/runtime/Composer;I)Landroidx/compose/ui/graphics/painter/Painter;
   L599
    LINENUMBER 211 L599
    ACONST_NULL
   L600
    LINENUMBER 212 L600
    GETSTATIC androidx/compose/ui/Modifier.Companion : Landroidx/compose/ui/Modifier$Companion;
    CHECKCAST androidx/compose/ui/Modifier
    FCONST_0
    ICONST_1
    ACONST_NULL
    INVOKESTATIC androidx/compose/foundation/layout/SizeKt.fillMaxSize$default (Landroidx/compose/ui/Modifier;FILjava/lang/Object;)Landroidx/compose/ui/Modifier;
    ACONST_NULL
    ACONST_NULL
    FCONST_0
    ACONST_NULL
    ALOAD 187
    SIPUSH 432
    GETSTATIC androidx/compose/ui/graphics/painter/Painter.$stable : I
    IOR
    BIPUSH 120
   L601
    LINENUMBER 209 L601
    INVOKESTATIC androidx/compose/foundation/ImageKt.Image (Landroidx/compose/ui/graphics/painter/Painter;Ljava/lang/String;Landroidx/compose/ui/Modifier;Landroidx/compose/ui/Alignment;Landroidx/compose/ui/layout/ContentScale;FLandroidx/compose/ui/graphics/ColorFilter;Landroidx/compose/runtime/Composer;II)V
   L602
    LINENUMBER 216 L602
    ALOAD 9
    INVOKESTATIC capstone/safeline/ui/ChannelScreenKt.ChannelScreenUI$lambda$4 (Landroidx/compose/runtime/MutableState;)Ljava/lang/String;
    ALOAD 187
    LDC 1167696770
    INVOKEINTERFACE androidx/compose/runtime/Composer.startReplaceGroup (I)V (itf)
    ALOAD 187
    LDC "CC(remember):ChannelScreen.kt#9igjgp"
    INVOKESTATIC androidx/compose/runtime/ComposerKt.sourceInformation (Landroidx/compose/runtime/Composer;Ljava/lang/String;)V
    ALOAD 187
    ASTORE 190
    ICONST_0
    ISTORE 191
   L603
    LINENUMBER 217 L603
    NOP
   L604
    ICONST_0
    ISTORE 192
   L605
    LINENUMBER 566 L605
    ALOAD 190
    INVOKEINTERFACE androidx/compose/runtime/Composer.rememberedValue ()Ljava/lang/Object; (itf)
    ASTORE 193
   L606
    ICONST_0
    ISTORE 194
   L607
    LINENUMBER 567 L607
    ILOAD 191
    IFNE L608
    ALOAD 193
    GETSTATIC androidx/compose/runtime/Composer.Companion : Landroidx/compose/runtime/Composer$Companion;
    INVOKEVIRTUAL androidx/compose/runtime/Composer$Companion.getEmpty ()Ljava/lang/Object;
    IF_ACMPNE L609
   L608
    LINENUMBER 568 L608
    ASTORE 195
    ICONST_0
    ISTORE 196
   L610
    LINENUMBER 217 L610
    ALOAD 9
    INVOKEDYNAMIC invoke(Landroidx/compose/runtime/MutableState;)Lkotlin/jvm/functions/Function1; [
      // handle kind 0x6 : INVOKESTATIC
      java/lang/invoke/LambdaMetafactory.metafactory(Ljava/lang/invoke/MethodHandles$Lookup;Ljava/lang/String;Ljava/lang/invoke/MethodType;Ljava/lang/invoke/MethodType;Ljava/lang/invoke/MethodHandle;Ljava/lang/invoke/MethodType;)Ljava/lang/invoke/CallSite;
      // arguments:
      (Ljava/lang/Object;)Ljava/lang/Object;, 
      // handle kind 0x6 : INVOKESTATIC
      capstone/safeline/ui/ChannelScreenKt.ChannelScreenUI$lambda$27$lambda$26$lambda$25$lambda$24$lambda$23$lambda$18$lambda$17$lambda$16(Landroidx/compose/runtime/MutableState;Ljava/lang/String;)Lkotlin/Unit;, 
      (Ljava/lang/String;)Lkotlin/Unit;
    ]
    GOTO L611
   L611
    ALOAD 195
    SWAP
   L612
    LINENUMBER 568 L612
    ASTORE 197
   L613
    LINENUMBER 569 L613
    ALOAD 190
    ALOAD 197
    INVOKEINTERFACE androidx/compose/runtime/Composer.updateRememberedValue (Ljava/lang/Object;)V (itf)
   L614
    LINENUMBER 570 L614
    ALOAD 197
   L615
    GOTO L616
   L609
    LINENUMBER 571 L609
    ALOAD 193
   L616
    LINENUMBER 566 L616
    NOP
   L617
    LINENUMBER 566 L617
    GOTO L618
   L618
    LINENUMBER 217 L618
    CHECKCAST kotlin/jvm/functions/Function1
    ASTORE 198
    ALOAD 187
    INVOKEINTERFACE androidx/compose/runtime/Composer.endReplaceGroup ()V (itf)
    ALOAD 198
   L619
    LINENUMBER 218 L619
    GETSTATIC androidx/compose/ui/Modifier.Companion : Landroidx/compose/ui/Modifier$Companion;
    CHECKCAST androidx/compose/ui/Modifier
   L620
    LINENUMBER 219 L620
    FCONST_0
    ICONST_1
    ACONST_NULL
    INVOKESTATIC androidx/compose/foundation/layout/SizeKt.fillMaxSize$default (Landroidx/compose/ui/Modifier;FILjava/lang/Object;)Landroidx/compose/ui/Modifier;
   L621
    LINENUMBER 220 L621
    BIPUSH 6
    ISTORE 198
   L622
    ICONST_0
    ISTORE 190
   L623
    LINENUMBER 572 L623
    ILOAD 198
    I2F
    INVOKESTATIC androidx/compose/ui/unit/Dp.constructor-impl (F)F
    GOTO L624
   L624
    LINENUMBER 220 L624
    FCONST_0
    ICONST_2
    ACONST_NULL
    INVOKESTATIC androidx/compose/foundation/layout/PaddingKt.padding-VpY3zN4$default (Landroidx/compose/ui/Modifier;FFILjava/lang/Object;)Landroidx/compose/ui/Modifier;
    ICONST_0
    ICONST_0
    ACONST_NULL
    ACONST_NULL
    ACONST_NULL
    ACONST_NULL
    ACONST_NULL
    ACONST_NULL
    ACONST_NULL
    ACONST_NULL
    ICONST_0
    ACONST_NULL
    ACONST_NULL
    ACONST_NULL
   L625
    LINENUMBER 221 L625
    ICONST_1
    ICONST_0
    ICONST_0
    ACONST_NULL
    ACONST_NULL
   L626
    LINENUMBER 222 L626
    GETSTATIC androidx/compose/material3/TextFieldDefaults.INSTANCE : Landroidx/compose/material3/TextFieldDefaults;
    ASTORE 198
   L627
    LINENUMBER 223 L627
    GETSTATIC androidx/compose/ui/graphics/Color.Companion : Landroidx/compose/ui/graphics/Color$Companion;
    INVOKEVIRTUAL androidx/compose/ui/graphics/Color$Companion.getTransparent-0d7_KjU ()J
    LSTORE 199
   L628
    LINENUMBER 224 L628
    GETSTATIC androidx/compose/ui/graphics/Color.Companion : Landroidx/compose/ui/graphics/Color$Companion;
    INVOKEVIRTUAL androidx/compose/ui/graphics/Color$Companion.getTransparent-0d7_KjU ()J
    LSTORE 201
   L629
    LINENUMBER 225 L629
    GETSTATIC androidx/compose/ui/graphics/Color.Companion : Landroidx/compose/ui/graphics/Color$Companion;
    INVOKEVIRTUAL androidx/compose/ui/graphics/Color$Companion.getWhite-0d7_KjU ()J
    LSTORE 203
   L630
    LINENUMBER 226 L630
    GETSTATIC androidx/compose/ui/graphics/Color.Companion : Landroidx/compose/ui/graphics/Color$Companion;
    INVOKEVIRTUAL androidx/compose/ui/graphics/Color$Companion.getWhite-0d7_KjU ()J
    LSTORE 205
   L631
    LINENUMBER 227 L631
    GETSTATIC androidx/compose/ui/graphics/Color.Companion : Landroidx/compose/ui/graphics/Color$Companion;
    INVOKEVIRTUAL androidx/compose/ui/graphics/Color$Companion.getWhite-0d7_KjU ()J
    LSTORE 207
   L632
    LINENUMBER 222 L632
    ALOAD 198
   L633
    LINENUMBER 226 L633
    LLOAD 205
   L634
    LINENUMBER 227 L634
    LLOAD 207
    LCONST_0
    LCONST_0
   L635
    LINENUMBER 223 L635
    LLOAD 199
   L636
    LINENUMBER 224 L636
    LLOAD 201
    LCONST_0
    LCONST_0
   L637
    LINENUMBER 225 L637
    LLOAD 203
    LCONST_0
    ACONST_NULL
    LCONST_0
    LCONST_0
    LCONST_0
    LCONST_0
    LCONST_0
    LCONST_0
    LCONST_0
    LCONST_0
    LCONST_0
    LCONST_0
    LCONST_0
    LCONST_0
    LCONST_0
    LCONST_0
    LCONST_0
    LCONST_0
    LCONST_0
    LCONST_0
    LCONST_0
    LCONST_0
    LCONST_0
    LCONST_0
    LCONST_0
    LCONST_0
    LCONST_0
    LCONST_0
    LCONST_0
    LCONST_0
    LCONST_0
    LCONST_0
    LCONST_0
    LCONST_0
    ALOAD 187
    LDC 100884534
    ICONST_0
    ICONST_0
    ICONST_0
    SIPUSH 3072
    LDC 2147483340
    SIPUSH 4095
   L638
    LINENUMBER 222 L638
    INVOKEVIRTUAL androidx/compose/material3/TextFieldDefaults.colors-0hiis_0 (JJJJJJJJJJLandroidx/compose/foundation/text/selection/TextSelectionColors;JJJJJJJJJJJJJJJJJJJJJJJJJJJJJJJJLandroidx/compose/runtime/Composer;IIIIIII)Landroidx/compose/material3/TextFieldColors;
    ALOAD 187
    SIPUSH 432
    LDC 12582912
    ICONST_0
    LDC 4063224
   L639
    LINENUMBER 215 L639
    INVOKESTATIC androidx/compose/material3/TextFieldKt.TextField (Ljava/lang/String;Lkotlin/jvm/functions/Function1;Landroidx/compose/ui/Modifier;ZZLandroidx/compose/ui/text/TextStyle;Lkotlin/jvm/functions/Function2;Lkotlin/jvm/functions/Function2;Lkotlin/jvm/functions/Function2;Lkotlin/jvm/functions/Function2;Lkotlin/jvm/functions/Function2;Lkotlin/jvm/functions/Function2;Lkotlin/jvm/functions/Function2;ZLandroidx/compose/ui/text/input/VisualTransformation;Landroidx/compose/foundation/text/KeyboardOptions;Landroidx/compose/foundation/text/KeyboardActions;ZIILandroidx/compose/foundation/interaction/MutableInteractionSource;Landroidx/compose/ui/graphics/Shape;Landroidx/compose/material3/TextFieldColors;Landroidx/compose/runtime/Composer;IIII)V
    ALOAD 187
   L640
    LINENUMBER 209 L640
    INVOKESTATIC androidx/compose/runtime/ComposerKt.sourceInformationMarkerEnd (Landroidx/compose/runtime/Composer;)V
   L641
    LINENUMBER 230 L641
    GOTO L642
   L642
    GETSTATIC kotlin/Unit.INSTANCE : Lkotlin/Unit;
   L643
    LINENUMBER 541 L643
    POP
    ALOAD 184
    INVOKESTATIC androidx/compose/runtime/ComposerKt.sourceInformationMarkerEnd (Landroidx/compose/runtime/Composer;)V
   L644
    LINENUMBER 565 L644
    ALOAD 178
   L645
    LINENUMBER 573 L645
    INVOKEINTERFACE androidx/compose/runtime/Composer.endNode ()V (itf)
    ALOAD 178
   L646
    LINENUMBER 550 L646
    INVOKESTATIC androidx/compose/runtime/ComposerKt.sourceInformationMarkerEnd (Landroidx/compose/runtime/Composer;)V
   L647
    LINENUMBER 574 L647
    NOP
   L648
    ALOAD 171
   L649
    LINENUMBER 544 L649
    INVOKESTATIC androidx/compose/runtime/ComposerKt.sourceInformationMarkerEnd (Landroidx/compose/runtime/Composer;)V
   L650
    LINENUMBER 575 L650
    NOP
   L651
    ALOAD 146
   L652
    LINENUMBER 534 L652
    INVOKESTATIC androidx/compose/runtime/ComposerKt.sourceInformationMarkerEnd (Landroidx/compose/runtime/Composer;)V
   L653
    LINENUMBER 576 L653
    GOTO L654
   L654
    LINENUMBER 232 L654
    GETSTATIC androidx/compose/ui/Modifier.Companion : Landroidx/compose/ui/Modifier$Companion;
    CHECKCAST androidx/compose/ui/Modifier
    ICONST_0
    ISTORE 149
   L655
    ICONST_0
    ISTORE 150
   L656
    LINENUMBER 577 L656
    ILOAD 149
    I2F
    INVOKESTATIC androidx/compose/ui/unit/Dp.constructor-impl (F)F
    GOTO L657
   L657
    LINENUMBER 232 L657
    INVOKESTATIC androidx/compose/foundation/layout/SizeKt.width-3ABfNKs (Landroidx/compose/ui/Modifier;F)Landroidx/compose/ui/Modifier;
    ALOAD 146
    BIPUSH 6
    INVOKESTATIC androidx/compose/foundation/layout/SpacerKt.Spacer (Landroidx/compose/ui/Modifier;Landroidx/compose/runtime/Composer;I)V
   L658
    LINENUMBER 235 L658
    GETSTATIC capstone/safeline/R$drawable.attach : I
    ALOAD 146
    ICONST_0
    INVOKESTATIC androidx/compose/ui/res/PainterResources_androidKt.painterResource (ILandroidx/compose/runtime/Composer;I)Landroidx/compose/ui/graphics/painter/Painter;
   L659
    LINENUMBER 236 L659
    ACONST_NULL
   L660
    LINENUMBER 237 L660
    GETSTATIC androidx/compose/ui/Modifier.Companion : Landroidx/compose/ui/Modifier$Companion;
    CHECKCAST androidx/compose/ui/Modifier
   L661
    LINENUMBER 238 L661
    BIPUSH 34
    ISTORE 149
   L662
    ICONST_0
    ISTORE 150
   L663
    LINENUMBER 578 L663
    ILOAD 149
    I2F
    INVOKESTATIC androidx/compose/ui/unit/Dp.constructor-impl (F)F
    GOTO L664
   L664
    LINENUMBER 238 L664
    INVOKESTATIC androidx/compose/foundation/layout/SizeKt.size-3ABfNKs (Landroidx/compose/ui/Modifier;F)Landroidx/compose/ui/Modifier;
   L665
    LINENUMBER 239 L665
    ICONST_0
    ACONST_NULL
    ACONST_NULL
    ACONST_NULL
    ALOAD 146
    LDC -428244743
    INVOKEINTERFACE androidx/compose/runtime/Composer.startReplaceGroup (I)V (itf)
    ALOAD 146
    LDC "CC(remember):ChannelScreen.kt#9igjgp"
    INVOKESTATIC androidx/compose/runtime/ComposerKt.sourceInformation (Landroidx/compose/runtime/Composer;Ljava/lang/String;)V
    ALOAD 146
    ASTORE 150
    ICONST_0
    ISTORE 169
   L666
    ICONST_0
    ISTORE 167
   L667
    LINENUMBER 579 L667
    ALOAD 150
    INVOKEINTERFACE androidx/compose/runtime/Composer.rememberedValue ()Ljava/lang/Object; (itf)
    ASTORE 168
   L668
    ICONST_0
    ISTORE 170
   L669
    LINENUMBER 580 L669
    ILOAD 169
    IFNE L670
    ALOAD 168
    GETSTATIC androidx/compose/runtime/Composer.Companion : Landroidx/compose/runtime/Composer$Companion;
    INVOKEVIRTUAL androidx/compose/runtime/Composer$Companion.getEmpty ()Ljava/lang/Object;
    IF_ACMPNE L671
   L670
    LINENUMBER 581 L670
    ASTORE 209
    ASTORE 210
    ASTORE 211
    ISTORE 212
    ASTORE 213
    ASTORE 214
    ASTORE 215
    ICONST_0
    ISTORE 155
   L672
    INVOKEDYNAMIC invoke()Lkotlin/jvm/functions/Function0; [
      // handle kind 0x6 : INVOKESTATIC
      java/lang/invoke/LambdaMetafactory.metafactory(Ljava/lang/invoke/MethodHandles$Lookup;Ljava/lang/String;Ljava/lang/invoke/MethodType;Ljava/lang/invoke/MethodType;Ljava/lang/invoke/MethodHandle;Ljava/lang/invoke/MethodType;)Ljava/lang/invoke/CallSite;
      // arguments:
      ()Ljava/lang/Object;, 
      // handle kind 0x6 : INVOKESTATIC
      capstone/safeline/ui/ChannelScreenKt.ChannelScreenUI$lambda$27$lambda$26$lambda$25$lambda$24$lambda$23$lambda$20$lambda$19()Lkotlin/Unit;, 
      ()Lkotlin/Unit;
    ]
    GOTO L673
   L673
    ASTORE 216
    ALOAD 215
    ALOAD 214
    ALOAD 213
    ILOAD 212
    ALOAD 211
    ALOAD 210
    ALOAD 209
    ALOAD 216
   L674
    LINENUMBER 581 L674
    ASTORE 155
   L675
    LINENUMBER 582 L675
    ALOAD 150
    ALOAD 155
    INVOKEINTERFACE androidx/compose/runtime/Composer.updateRememberedValue (Ljava/lang/Object;)V (itf)
   L676
    LINENUMBER 583 L676
    ALOAD 155
   L677
    GOTO L678
   L671
    LINENUMBER 584 L671
    ALOAD 168
   L678
    LINENUMBER 579 L678
    NOP
   L679
    LINENUMBER 579 L679
    GOTO L680
   L680
    LINENUMBER 239 L680
    CHECKCAST kotlin/jvm/functions/Function0
    ASTORE 149
    ALOAD 146
    INVOKEINTERFACE androidx/compose/runtime/Composer.endReplaceGroup ()V (itf)
    ALOAD 149
    BIPUSH 15
    ACONST_NULL
    INVOKESTATIC androidx/compose/foundation/ClickableKt.clickable-oSLSa3U$default (Landroidx/compose/ui/Modifier;ZLjava/lang/String;Landroidx/compose/ui/semantics/Role;Landroidx/compose/foundation/interaction/MutableInteractionSource;Lkotlin/jvm/functions/Function0;ILjava/lang/Object;)Landroidx/compose/ui/Modifier;
    ACONST_NULL
   L681
    LINENUMBER 240 L681
    GETSTATIC androidx/compose/ui/layout/ContentScale.Companion : Landroidx/compose/ui/layout/ContentScale$Companion;
    INVOKEVIRTUAL androidx/compose/ui/layout/ContentScale$Companion.getFit ()Landroidx/compose/ui/layout/ContentScale;
    FCONST_0
    ACONST_NULL
    ALOAD 146
    SIPUSH 24624
    GETSTATIC androidx/compose/ui/graphics/painter/Painter.$stable : I
    IOR
    BIPUSH 104
   L682
    LINENUMBER 234 L682
    INVOKESTATIC androidx/compose/foundation/ImageKt.Image (Landroidx/compose/ui/graphics/painter/Painter;Ljava/lang/String;Landroidx/compose/ui/Modifier;Landroidx/compose/ui/Alignment;Landroidx/compose/ui/layout/ContentScale;FLandroidx/compose/ui/graphics/ColorFilter;Landroidx/compose/runtime/Composer;II)V
   L683
    LINENUMBER 243 L683
    GETSTATIC androidx/compose/ui/Modifier.Companion : Landroidx/compose/ui/Modifier$Companion;
    CHECKCAST androidx/compose/ui/Modifier
    BIPUSH 10
    ISTORE 149
   L684
    ICONST_0
    ISTORE 150
   L685
    LINENUMBER 585 L685
    ILOAD 149
    I2F
    INVOKESTATIC androidx/compose/ui/unit/Dp.constructor-impl (F)F
    GOTO L686
   L686
    LINENUMBER 243 L686
    INVOKESTATIC androidx/compose/foundation/layout/SizeKt.width-3ABfNKs (Landroidx/compose/ui/Modifier;F)Landroidx/compose/ui/Modifier;
    ALOAD 146
    BIPUSH 6
    INVOKESTATIC androidx/compose/foundation/layout/SpacerKt.Spacer (Landroidx/compose/ui/Modifier;Landroidx/compose/runtime/Composer;I)V
   L687
    LINENUMBER 246 L687
    GETSTATIC capstone/safeline/R$drawable.enter_button : I
    ALOAD 146
    ICONST_0
    INVOKESTATIC androidx/compose/ui/res/PainterResources_androidKt.painterResource (ILandroidx/compose/runtime/Composer;I)Landroidx/compose/ui/graphics/painter/Painter;
   L688
    LINENUMBER 247 L688
    ACONST_NULL
   L689
    LINENUMBER 248 L689
    GETSTATIC androidx/compose/ui/Modifier.Companion : Landroidx/compose/ui/Modifier$Companion;
    CHECKCAST androidx/compose/ui/Modifier
   L690
    LINENUMBER 249 L690
    BIPUSH 46
    ISTORE 149
   L691
    ICONST_0
    ISTORE 150
   L692
    LINENUMBER 586 L692
    ILOAD 149
    I2F
    INVOKESTATIC androidx/compose/ui/unit/Dp.constructor-impl (F)F
    GOTO L693
   L693
    LINENUMBER 249 L693
    INVOKESTATIC androidx/compose/foundation/layout/SizeKt.size-3ABfNKs (Landroidx/compose/ui/Modifier;F)Landroidx/compose/ui/Modifier;
   L694
    LINENUMBER 250 L694
    ICONST_0
    ACONST_NULL
    ACONST_NULL
    ACONST_NULL
    ALOAD 146
    LDC -428229637
    INVOKEINTERFACE androidx/compose/runtime/Composer.startReplaceGroup (I)V (itf)
    ALOAD 146
    LDC "CC(remember):ChannelScreen.kt#9igjgp"
    INVOKESTATIC androidx/compose/runtime/ComposerKt.sourceInformation (Landroidx/compose/runtime/Composer;Ljava/lang/String;)V
    ALOAD 146
    ASTORE 150
    ICONST_0
    ISTORE 169
   L695
    ICONST_0
    ISTORE 167
   L696
    LINENUMBER 587 L696
    ALOAD 150
    INVOKEINTERFACE androidx/compose/runtime/Composer.rememberedValue ()Ljava/lang/Object; (itf)
    ASTORE 168
   L697
    ICONST_0
    ISTORE 170
   L698
    LINENUMBER 588 L698
    ILOAD 169
    IFNE L699
    ALOAD 168
    GETSTATIC androidx/compose/runtime/Composer.Companion : Landroidx/compose/runtime/Composer$Companion;
    INVOKEVIRTUAL androidx/compose/runtime/Composer$Companion.getEmpty ()Ljava/lang/Object;
    IF_ACMPNE L700
   L699
    LINENUMBER 589 L699
    ASTORE 209
    ASTORE 210
    ASTORE 211
    ISTORE 212
    ASTORE 213
    ASTORE 214
    ASTORE 215
    ICONST_0
    ISTORE 155
   L701
    LINENUMBER 250 L701
    ALOAD 9
    ALOAD 8
    INVOKEDYNAMIC invoke(Landroidx/compose/runtime/MutableState;Landroidx/compose/runtime/MutableState;)Lkotlin/jvm/functions/Function0; [
      // handle kind 0x6 : INVOKESTATIC
      java/lang/invoke/LambdaMetafactory.metafactory(Ljava/lang/invoke/MethodHandles$Lookup;Ljava/lang/String;Ljava/lang/invoke/MethodType;Ljava/lang/invoke/MethodType;Ljava/lang/invoke/MethodHandle;Ljava/lang/invoke/MethodType;)Ljava/lang/invoke/CallSite;
      // arguments:
      ()Ljava/lang/Object;, 
      // handle kind 0x6 : INVOKESTATIC
      capstone/safeline/ui/ChannelScreenKt.ChannelScreenUI$lambda$27$lambda$26$lambda$25$lambda$24$lambda$23$lambda$22$lambda$21(Landroidx/compose/runtime/MutableState;Landroidx/compose/runtime/MutableState;)Lkotlin/Unit;, 
      ()Lkotlin/Unit;
    ]
    GOTO L702
   L702
    ASTORE 216
    ALOAD 215
    ALOAD 214
    ALOAD 213
    ILOAD 212
    ALOAD 211
    ALOAD 210
    ALOAD 209
    ALOAD 216
   L703
    LINENUMBER 589 L703
    ASTORE 156
   L704
    LINENUMBER 590 L704
    ALOAD 150
    ALOAD 156
    INVOKEINTERFACE androidx/compose/runtime/Composer.updateRememberedValue (Ljava/lang/Object;)V (itf)
   L705
    LINENUMBER 591 L705
    ALOAD 156
   L706
    GOTO L707
   L700
    LINENUMBER 592 L700
    ALOAD 168
   L707
    LINENUMBER 587 L707
    NOP
   L708
    LINENUMBER 587 L708
    GOTO L709
   L709
    LINENUMBER 250 L709
    CHECKCAST kotlin/jvm/functions/Function0
    ASTORE 149
    ALOAD 146
    INVOKEINTERFACE androidx/compose/runtime/Composer.endReplaceGroup ()V (itf)
    ALOAD 149
    BIPUSH 15
    ACONST_NULL
    INVOKESTATIC androidx/compose/foundation/ClickableKt.clickable-oSLSa3U$default (Landroidx/compose/ui/Modifier;ZLjava/lang/String;Landroidx/compose/ui/semantics/Role;Landroidx/compose/foundation/interaction/MutableInteractionSource;Lkotlin/jvm/functions/Function0;ILjava/lang/Object;)Landroidx/compose/ui/Modifier;
    ACONST_NULL
    ACONST_NULL
    FCONST_0
    ACONST_NULL
    ALOAD 146
    BIPUSH 48
    GETSTATIC androidx/compose/ui/graphics/painter/Painter.$stable : I
    IOR
    BIPUSH 120
   L710
    LINENUMBER 245 L710
    INVOKESTATIC androidx/compose/foundation/ImageKt.Image (Landroidx/compose/ui/graphics/painter/Painter;Ljava/lang/String;Landroidx/compose/ui/Modifier;Landroidx/compose/ui/Alignment;Landroidx/compose/ui/layout/ContentScale;FLandroidx/compose/ui/graphics/ColorFilter;Landroidx/compose/runtime/Composer;II)V
    ALOAD 146
   L711
    LINENUMBER 204 L711
    INVOKESTATIC androidx/compose/runtime/ComposerKt.sourceInformationMarkerEnd (Landroidx/compose/runtime/Composer;)V
   L712
    LINENUMBER 260 L712
    GOTO L713
   L713
    GETSTATIC kotlin/Unit.INSTANCE : Lkotlin/Unit;
   L714
    LINENUMBER 508 L714
    POP
    ALOAD 143
    INVOKESTATIC androidx/compose/runtime/ComposerKt.sourceInformationMarkerEnd (Landroidx/compose/runtime/Composer;)V
   L715
    LINENUMBER 532 L715
    ALOAD 137
   L716
    LINENUMBER 593 L716
    INVOKEINTERFACE androidx/compose/runtime/Composer.endNode ()V (itf)
    ALOAD 137
   L717
    LINENUMBER 517 L717
    INVOKESTATIC androidx/compose/runtime/ComposerKt.sourceInformationMarkerEnd (Landroidx/compose/runtime/Composer;)V
   L718
    LINENUMBER 594 L718
    NOP
   L719
    ALOAD 130
   L720
    LINENUMBER 511 L720
    INVOKESTATIC androidx/compose/runtime/ComposerKt.sourceInformationMarkerEnd (Landroidx/compose/runtime/Composer;)V
   L721
    LINENUMBER 595 L721
    NOP
   L722
    ALOAD 119
   L723
    LINENUMBER 501 L723
    INVOKESTATIC androidx/compose/runtime/ComposerKt.sourceInformationMarkerEnd (Landroidx/compose/runtime/Composer;)V
   L724
    LINENUMBER 596 L724
    GOTO L725
   L725
    ALOAD 119
   L726
    LINENUMBER 191 L726
    INVOKESTATIC androidx/compose/runtime/ComposerKt.sourceInformationMarkerEnd (Landroidx/compose/runtime/Composer;)V
   L727
    LINENUMBER 261 L727
    GOTO L728
   L728
    GETSTATIC kotlin/Unit.INSTANCE : Lkotlin/Unit;
   L729
    LINENUMBER 475 L729
    POP
    ALOAD 116
    INVOKESTATIC androidx/compose/runtime/ComposerKt.sourceInformationMarkerEnd (Landroidx/compose/runtime/Composer;)V
   L730
    LINENUMBER 499 L730
    ALOAD 110
   L731
    LINENUMBER 597 L731
    INVOKEINTERFACE androidx/compose/runtime/Composer.endNode ()V (itf)
    ALOAD 110
   L732
    LINENUMBER 484 L732
    INVOKESTATIC androidx/compose/runtime/ComposerKt.sourceInformationMarkerEnd (Landroidx/compose/runtime/Composer;)V
   L733
    LINENUMBER 598 L733
    NOP
   L734
    ALOAD 103
   L735
    LINENUMBER 478 L735
    INVOKESTATIC androidx/compose/runtime/ComposerKt.sourceInformationMarkerEnd (Landroidx/compose/runtime/Composer;)V
   L736
    LINENUMBER 599 L736
    NOP
   L737
    ALOAD 92
   L738
    LINENUMBER 468 L738
    INVOKESTATIC androidx/compose/runtime/ComposerKt.sourceInformationMarkerEnd (Landroidx/compose/runtime/Composer;)V
   L739
    LINENUMBER 600 L739
    GOTO L740
   L740
    ALOAD 92
   L741
    LINENUMBER 114 L741
    INVOKESTATIC androidx/compose/runtime/ComposerKt.sourceInformationMarkerEnd (Landroidx/compose/runtime/Composer;)V
   L742
    LINENUMBER 262 L742
    GOTO L743
   L743
    GETSTATIC kotlin/Unit.INSTANCE : Lkotlin/Unit;
   L744
    LINENUMBER 361 L744
    POP
    ALOAD 89
    INVOKESTATIC androidx/compose/runtime/ComposerKt.sourceInformationMarkerEnd (Landroidx/compose/runtime/Composer;)V
   L745
    LINENUMBER 385 L745
    ALOAD 83
   L746
    LINENUMBER 601 L746
    INVOKEINTERFACE androidx/compose/runtime/Composer.endNode ()V (itf)
    ALOAD 83
   L747
    LINENUMBER 370 L747
    INVOKESTATIC androidx/compose/runtime/ComposerKt.sourceInformationMarkerEnd (Landroidx/compose/runtime/Composer;)V
   L748
    LINENUMBER 602 L748
    NOP
   L749
    ALOAD 76
   L750
    LINENUMBER 364 L750
    INVOKESTATIC androidx/compose/runtime/ComposerKt.sourceInformationMarkerEnd (Landroidx/compose/runtime/Composer;)V
   L751
    LINENUMBER 603 L751
    NOP
   L752
    ALOAD 61
   L753
    LINENUMBER 354 L753
    INVOKESTATIC androidx/compose/runtime/ComposerKt.sourceInformationMarkerEnd (Landroidx/compose/runtime/Composer;)V
   L754
    LINENUMBER 604 L754
    GOTO L755
   L755
    ALOAD 61
   L756
    LINENUMBER 98 L756
    INVOKESTATIC androidx/compose/runtime/ComposerKt.sourceInformationMarkerEnd (Landroidx/compose/runtime/Composer;)V
   L757
    LINENUMBER 263 L757
    GOTO L758
   L758
    GETSTATIC kotlin/Unit.INSTANCE : Lkotlin/Unit;
   L759
    LINENUMBER 322 L759
    POP
    ALOAD 58
    INVOKESTATIC androidx/compose/runtime/ComposerKt.sourceInformationMarkerEnd (Landroidx/compose/runtime/Composer;)V
   L760
    LINENUMBER 346 L760
    ALOAD 52
   L761
    LINENUMBER 605 L761
    INVOKEINTERFACE androidx/compose/runtime/Composer.endNode ()V (itf)
    ALOAD 52
   L762
    LINENUMBER 331 L762
    INVOKESTATIC androidx/compose/runtime/ComposerKt.sourceInformationMarkerEnd (Landroidx/compose/runtime/Composer;)V
   L763
    LINENUMBER 606 L763
    NOP
   L764
    ALOAD 45
   L765
    LINENUMBER 325 L765
    INVOKESTATIC androidx/compose/runtime/ComposerKt.sourceInformationMarkerEnd (Landroidx/compose/runtime/Composer;)V
   L766
    LINENUMBER 607 L766
    NOP
   L767
    ALOAD 34
   L768
    LINENUMBER 315 L768
    INVOKESTATIC androidx/compose/runtime/ComposerKt.sourceInformationMarkerEnd (Landroidx/compose/runtime/Composer;)V
   L769
    LINENUMBER 608 L769
    GOTO L770
   L770
    LINENUMBER 266 L770
    ALOAD 4
   L771
    LINENUMBER 267 L771
    ALOAD 35
    GETSTATIC androidx/compose/ui/Modifier.Companion : Landroidx/compose/ui/Modifier$Companion;
    CHECKCAST androidx/compose/ui/Modifier
    GETSTATIC androidx/compose/ui/Alignment.Companion : Landroidx/compose/ui/Alignment$Companion;
    INVOKEVIRTUAL androidx/compose/ui/Alignment$Companion.getTopStart ()Landroidx/compose/ui/Alignment;
    INVOKEINTERFACE androidx/compose/foundation/layout/BoxScope.align (Landroidx/compose/ui/Modifier;Landroidx/compose/ui/Alignment;)Landroidx/compose/ui/Modifier; (itf)
    ALOAD 34
    BIPUSH 14
    ILOAD 7
    BIPUSH 12
    ISHR
    IAND
    ICONST_0
   L772
    LINENUMBER 265 L772
    INVOKESTATIC capstone/safeline/ui/components/BackButtonKt.BackButton (Lkotlin/jvm/functions/Function0;Landroidx/compose/ui/Modifier;Landroidx/compose/runtime/Composer;II)V
    ALOAD 34
   L773
    LINENUMBER 77 L773
    INVOKESTATIC androidx/compose/runtime/ComposerKt.sourceInformationMarkerEnd (Landroidx/compose/runtime/Composer;)V
   L774
    LINENUMBER 269 L774
    NOP
    GOTO L775
   L775
    GETSTATIC kotlin/Unit.INSTANCE : Lkotlin/Unit;
    INVOKESTATIC kotlin/jvm/internal/InlineMarker.afterInlineCall ()V
   L776
    LINENUMBER 290 L776
    POP
    ALOAD 31
    INVOKESTATIC androidx/compose/runtime/ComposerKt.sourceInformationMarkerEnd (Landroidx/compose/runtime/Composer;)V
   L777
    LINENUMBER 314 L777
    ALOAD 25
   L778
    LINENUMBER 609 L778
    INVOKEINTERFACE androidx/compose/runtime/Composer.endNode ()V (itf)
    ALOAD 25
   L779
    LINENUMBER 299 L779
    INVOKESTATIC androidx/compose/runtime/ComposerKt.sourceInformationMarkerEnd (Landroidx/compose/runtime/Composer;)V
   L780
    LINENUMBER 610 L780
    NOP
   L781
    ALOAD 18
   L782
    LINENUMBER 293 L782
    INVOKESTATIC androidx/compose/runtime/ComposerKt.sourceInformationMarkerEnd (Landroidx/compose/runtime/Composer;)V
   L783
    LINENUMBER 611 L783
    NOP
   L784
    ALOAD 5
   L785
    LINENUMBER 283 L785
    INVOKESTATIC androidx/compose/runtime/ComposerKt.sourceInformationMarkerEnd (Landroidx/compose/runtime/Composer;)V
   L786
    LINENUMBER 612 L786
    NOP
    GOTO L787
   L787
    INVOKESTATIC androidx/compose/runtime/ComposerKt.isTraceInProgress ()Z
    IFEQ L788
    INVOKESTATIC androidx/compose/runtime/ComposerKt.traceEventEnd ()V
   L788
    GOTO L789
   L18
    LINENUMBER 270 L18
    ALOAD 5
    INVOKEINTERFACE androidx/compose/runtime/Composer.skipToGroupEnd ()V (itf)
   L789
    ALOAD 5
    INVOKEINTERFACE androidx/compose/runtime/Composer.endRestartGroup ()Landroidx/compose/runtime/ScopeUpdateScope; (itf)
    ASTORE 8
   L790
    ALOAD 8
    IFNULL L791
    ALOAD 8
    ALOAD 0
    ALOAD 1
    ALOAD 2
    ALOAD 3
    ALOAD 4
    ILOAD 6
    INVOKEDYNAMIC invoke(Ljava/util/List;Ljava/lang/String;Lkotlin/jvm/functions/Function1;Ljava/lang/String;Lkotlin/jvm/functions/Function0;I)Lkotlin/jvm/functions/Function2; [
      // handle kind 0x6 : INVOKESTATIC
      java/lang/invoke/LambdaMetafactory.metafactory(Ljava/lang/invoke/MethodHandles$Lookup;Ljava/lang/String;Ljava/lang/invoke/MethodType;Ljava/lang/invoke/MethodType;Ljava/lang/invoke/MethodHandle;Ljava/lang/invoke/MethodType;)Ljava/lang/invoke/CallSite;
      // arguments:
      (Ljava/lang/Object;Ljava/lang/Object;)Ljava/lang/Object;, 
      // handle kind 0x6 : INVOKESTATIC
      capstone/safeline/ui/ChannelScreenKt.ChannelScreenUI$lambda$28(Ljava/util/List;Ljava/lang/String;Lkotlin/jvm/functions/Function1;Ljava/lang/String;Lkotlin/jvm/functions/Function0;ILandroidx/compose/runtime/Composer;I)Lkotlin/Unit;, 
      (Landroidx/compose/runtime/Composer;Ljava/lang/Integer;)Lkotlin/Unit;
    ]
    INVOKEINTERFACE androidx/compose/runtime/ScopeUpdateScope.updateScope (Lkotlin/jvm/functions/Function2;)V (itf)
    GOTO L792
   L791
    NOP
   L792
    NOP
    RETURN
   L793
    LOCALVARIABLE $i$a$-cache-ChannelScreenKt$ChannelScreenUI$messages$2\3\273\0 I L28 L30 15
    LOCALVARIABLE value\2 Ljava/lang/Object; L32 L34 15
    LOCALVARIABLE $i$a$-let-ComposerKt$cache$1\2\271\1 I L24 L35 14
    LOCALVARIABLE it\1 Ljava/lang/Object; L23 L35 13
    LOCALVARIABLE $i$f$cache\1\72 I L22 L37 12
    LOCALVARIABLE $this$cache\1 Landroidx/compose/runtime/Composer; L21 L37 10
    LOCALVARIABLE invalid\1 Z L21 L37 11
    LOCALVARIABLE $i$a$-cache-ChannelScreenKt$ChannelScreenUI$text$2\6\279\0 I L49 L50 16
    LOCALVARIABLE value\5 Ljava/lang/Object; L52 L54 16
    LOCALVARIABLE $i$a$-let-ComposerKt$cache$1\5\277\4 I L45 L55 15
    LOCALVARIABLE it\4 Ljava/lang/Object; L44 L55 14
    LOCALVARIABLE $i$f$cache\4\73 I L43 L57 13
    LOCALVARIABLE $this$cache\4 Landroidx/compose/runtime/Composer; L42 L57 11
    LOCALVARIABLE invalid\4 Z L42 L57 12
    LOCALVARIABLE $i$a$-cache-ChannelScreenKt$ChannelScreenUI$1$1$1\21\349\18 I L177 L178 72
    LOCALVARIABLE value\20 Ljava/lang/Object; L180 L182 72
    LOCALVARIABLE $i$a$-let-ComposerKt$cache$1\20\347\19 I L174 L183 68
    LOCALVARIABLE it\19 Ljava/lang/Object; L173 L183 67
    LOCALVARIABLE $i$f$cache\19\102 I L172 L185 66
    LOCALVARIABLE $this$cache\19 Landroidx/compose/runtime/Composer; L171 L185 64
    LOCALVARIABLE invalid\19 Z L171 L185 65
    LOCALVARIABLE $i$f$getDp\22\111 I L194 L195 66
    LOCALVARIABLE $this$dp\22 I L193 L195 65
    LOCALVARIABLE $i$f$getDp\23\111 I L197 L198 67
    LOCALVARIABLE $this$dp\23 I L196 L198 66
    LOCALVARIABLE $i$f$getDp\24\111 I L200 L201 68
    LOCALVARIABLE $this$dp\24 I L199 L201 67
    LOCALVARIABLE $i$a$-Box-ChannelScreenKt$ChannelScreenUI$1$1$2$1$1\42\425\36 I L340 L372 148
    LOCALVARIABLE $this$ChannelScreenUI_u24lambda_u2427_u24lambda_u2426_u24lambda_u2425_u24lambda_u249_u24lambda_u248\42 Landroidx/compose/foundation/layout/BoxScope; L339 L372 147
    LOCALVARIABLE $composer\42 Landroidx/compose/runtime/Composer; L339 L372 146
    LOCALVARIABLE $changed\42 I L339 L372 145
    LOCALVARIABLE $i$a$-Layout-BoxKt$Box$1\41\449\37 I L337 L374 144
    LOCALVARIABLE $composer\41 Landroidx/compose/runtime/Composer; L336 L374 143
    LOCALVARIABLE $changed\41 I L336 L374 142
    LOCALVARIABLE $i$a$-ReusableComposeNode-LayoutKt$Layout$1\40\442\38 I L328 L334 141
    LOCALVARIABLE $this$Layout_u24lambda_u240\40 Landroidx/compose/runtime/Composer; L327 L334 140
    LOCALVARIABLE $i$f$ReusableComposeNode\39\432 I L317 L378 139
    LOCALVARIABLE factory\39 Lkotlin/jvm/functions/Function0; L316 L378 136
    LOCALVARIABLE $composer\39 Landroidx/compose/runtime/Composer; L316 L378 137
    LOCALVARIABLE $changed\39 I L316 L378 138
    LOCALVARIABLE $i$f$Layout\38\424 I L307 L381 132
    LOCALVARIABLE compositeKeyHash\38 I L310 L381 133
    LOCALVARIABLE localMap\38 Landroidx/compose/runtime/CompositionLocalMap; L312 L381 134
    LOCALVARIABLE materialized\38 Landroidx/compose/ui/Modifier; L314 L381 135
    LOCALVARIABLE modifier\38 Landroidx/compose/ui/Modifier; L306 L381 128
    LOCALVARIABLE measurePolicy\38 Landroidx/compose/ui/layout/MeasurePolicy; L306 L381 129
    LOCALVARIABLE $composer\38 Landroidx/compose/runtime/Composer; L306 L381 130
    LOCALVARIABLE $changed\38 I L306 L381 131
    LOCALVARIABLE $i$f$Box\37\116 I L299 L384 125
    LOCALVARIABLE measurePolicy\37 Landroidx/compose/ui/layout/MeasurePolicy; L303 L384 127
    LOCALVARIABLE modifier\37 Landroidx/compose/ui/Modifier; L298 L384 122
    LOCALVARIABLE contentAlignment\37 Landroidx/compose/ui/Alignment; L298 L384 123
    LOCALVARIABLE propagateMinConstraints\37 Z L302 L384 126
    LOCALVARIABLE $changed\37 I L298 L384 124
    LOCALVARIABLE $i$a$-Row-ChannelScreenKt$ChannelScreenUI$1$1$2$1\36\394\30 I L293 L387 121
    LOCALVARIABLE $this$ChannelScreenUI_u24lambda_u2427_u24lambda_u2426_u24lambda_u2425_u24lambda_u249\36 Landroidx/compose/foundation/layout/RowScope; L292 L387 120
    LOCALVARIABLE $composer\36 Landroidx/compose/runtime/Composer; L292 L387 119
    LOCALVARIABLE $changed\36 I L292 L387 118
    LOCALVARIABLE $i$a$-Layout-RowKt$Row$1\35\418\31 I L290 L389 117
    LOCALVARIABLE $composer\35 Landroidx/compose/runtime/Composer; L289 L389 116
    LOCALVARIABLE $changed\35 I L289 L389 115
    LOCALVARIABLE $i$a$-ReusableComposeNode-LayoutKt$Layout$1\34\411\32 I L281 L287 114
    LOCALVARIABLE $this$Layout_u24lambda_u240\34 Landroidx/compose/runtime/Composer; L280 L287 113
    LOCALVARIABLE $i$f$ReusableComposeNode\33\401 I L270 L393 112
    LOCALVARIABLE factory\33 Lkotlin/jvm/functions/Function0; L269 L393 109
    LOCALVARIABLE $composer\33 Landroidx/compose/runtime/Composer; L269 L393 110
    LOCALVARIABLE $changed\33 I L269 L393 111
    LOCALVARIABLE $i$f$Layout\32\393 I L260 L396 105
    LOCALVARIABLE compositeKeyHash\32 I L263 L396 106
    LOCALVARIABLE localMap\32 Landroidx/compose/runtime/CompositionLocalMap; L265 L396 107
    LOCALVARIABLE materialized\32 Landroidx/compose/ui/Modifier; L267 L396 108
    LOCALVARIABLE modifier\32 Landroidx/compose/ui/Modifier; L259 L396 101
    LOCALVARIABLE measurePolicy\32 Landroidx/compose/ui/layout/MeasurePolicy; L259 L396 102
    LOCALVARIABLE $composer\32 Landroidx/compose/runtime/Composer; L259 L396 103
    LOCALVARIABLE $changed\32 I L259 L396 104
    LOCALVARIABLE $i$f$Row\31\114 I L251 L399 97
    LOCALVARIABLE measurePolicy\31 Landroidx/compose/ui/layout/MeasurePolicy; L256 L399 100
    LOCALVARIABLE modifier\31 Landroidx/compose/ui/Modifier; L254 L399 98
    LOCALVARIABLE horizontalArrangement\31 Landroidx/compose/foundation/layout/Arrangement$Horizontal; L255 L399 99
    LOCALVARIABLE verticalAlignment\31 Landroidx/compose/ui/Alignment$Vertical; L250 L399 95
    LOCALVARIABLE $changed\31 I L250 L399 96
    LOCALVARIABLE $i$f$getDp\43\149 I L404 L405 95
    LOCALVARIABLE $this$dp\43 I L403 L405 99
    LOCALVARIABLE $i$f$getDp\44\150 I L408 L409 96
    LOCALVARIABLE $this$dp\44 I L407 L409 95
    LOCALVARIABLE $i$f$getDp\45\151 I L412 L413 97
    LOCALVARIABLE $this$dp\45 I L411 L413 96
    LOCALVARIABLE $i$f$getDp\46\151 I L415 L416 97
    LOCALVARIABLE $this$dp\46 I L414 L416 96
    LOCALVARIABLE $i$a$-cache-ChannelScreenKt$ChannelScreenUI$1$1$2$2\49\463\30 I L427 L428 104
    LOCALVARIABLE value\48 Ljava/lang/Object; L430 L432 105
    LOCALVARIABLE $i$a$-let-ComposerKt$cache$1\48\461\47 I L424 L433 103
    LOCALVARIABLE it\47 Ljava/lang/Object; L423 L433 102
    LOCALVARIABLE $i$f$cache\47\152 I L422 L435 101
    LOCALVARIABLE $this$cache\47 Landroidx/compose/runtime/Composer; L421 L435 97
    LOCALVARIABLE invalid\47 Z L421 L435 100
    LOCALVARIABLE $i$f$getDp\50\189 I L441 L442 99
    LOCALVARIABLE $this$dp\50 I L440 L442 98
    LOCALVARIABLE $i$f$getDp\57\201 I L498 L499 123
    LOCALVARIABLE $this$dp\57 I L497 L499 122
    LOCALVARIABLE $i$f$getDp\64\207 I L550 L551 150
    LOCALVARIABLE $this$dp\64 I L549 L551 149
    LOCALVARIABLE $i$a$-cache-ChannelScreenKt$ChannelScreenUI$1$1$2$3$1$1$1\73\568\70 I L610 L611 196
    LOCALVARIABLE value\72 Ljava/lang/Object; L613 L615 197
    LOCALVARIABLE $i$a$-let-ComposerKt$cache$1\72\566\71 I L607 L616 194
    LOCALVARIABLE it\71 Ljava/lang/Object; L606 L616 193
    LOCALVARIABLE $i$f$cache\71\217 I L605 L618 192
    LOCALVARIABLE $this$cache\71 Landroidx/compose/runtime/Composer; L604 L618 190
    LOCALVARIABLE invalid\71 Z L604 L618 191
    LOCALVARIABLE $i$f$getDp\74\220 I L623 L624 190
    LOCALVARIABLE $this$dp\74 I L622 L624 198
    LOCALVARIABLE $i$a$-Box-ChannelScreenKt$ChannelScreenUI$1$1$2$3$1$1\70\541\63 I L596 L642 189
    LOCALVARIABLE $this$ChannelScreenUI_u24lambda_u2427_u24lambda_u2426_u24lambda_u2425_u24lambda_u2424_u24lambda_u2423_u24lambda_u2418\70 Landroidx/compose/foundation/layout/BoxScope; L595 L642 188
    LOCALVARIABLE $composer\70 Landroidx/compose/runtime/Composer; L595 L642 187
    LOCALVARIABLE $changed\70 I L595 L642 186
    LOCALVARIABLE $i$a$-Layout-BoxKt$Box$1\69\565\65 I L593 L644 185
    LOCALVARIABLE $composer\69 Landroidx/compose/runtime/Composer; L592 L644 184
    LOCALVARIABLE $changed\69 I L592 L644 183
    LOCALVARIABLE $i$a$-ReusableComposeNode-LayoutKt$Layout$1\68\558\66 I L584 L590 182
    LOCALVARIABLE $this$Layout_u24lambda_u240\68 Landroidx/compose/runtime/Composer; L583 L590 181
    LOCALVARIABLE $i$f$ReusableComposeNode\67\548 I L573 L648 180
    LOCALVARIABLE factory\67 Lkotlin/jvm/functions/Function0; L572 L648 177
    LOCALVARIABLE $composer\67 Landroidx/compose/runtime/Composer; L572 L648 178
    LOCALVARIABLE $changed\67 I L572 L648 179
    LOCALVARIABLE $i$f$Layout\66\540 I L563 L651 173
    LOCALVARIABLE compositeKeyHash\66 I L566 L651 174
    LOCALVARIABLE localMap\66 Landroidx/compose/runtime/CompositionLocalMap; L568 L651 175
    LOCALVARIABLE materialized\66 Landroidx/compose/ui/Modifier; L570 L651 176
    LOCALVARIABLE modifier\66 Landroidx/compose/ui/Modifier; L562 L651 155
    LOCALVARIABLE measurePolicy\66 Landroidx/compose/ui/layout/MeasurePolicy; L562 L651 156
    LOCALVARIABLE $composer\66 Landroidx/compose/runtime/Composer; L562 L651 171
    LOCALVARIABLE $changed\66 I L562 L651 172
    LOCALVARIABLE $i$f$Box\65\204 I L554 L654 168
    LOCALVARIABLE measurePolicy\65 Landroidx/compose/ui/layout/MeasurePolicy; L559 L654 170
    LOCALVARIABLE modifier\65 Landroidx/compose/ui/Modifier; L553 L654 149
    LOCALVARIABLE contentAlignment\65 Landroidx/compose/ui/Alignment; L557 L654 150
    LOCALVARIABLE propagateMinConstraints\65 Z L558 L654 169
    LOCALVARIABLE $changed\65 I L553 L654 167
    LOCALVARIABLE $i$f$getDp\75\232 I L656 L657 150
    LOCALVARIABLE $this$dp\75 I L655 L657 149
    LOCALVARIABLE $i$f$getDp\76\238 I L663 L664 150
    LOCALVARIABLE $this$dp\76 I L662 L664 149
    LOCALVARIABLE $i$a$-cache-ChannelScreenKt$ChannelScreenUI$1$1$2$3$1$2\79\581\63 I L672 L673 155
    LOCALVARIABLE value\78 Ljava/lang/Object; L675 L677 155
    LOCALVARIABLE $i$a$-let-ComposerKt$cache$1\78\579\77 I L669 L678 170
    LOCALVARIABLE it\77 Ljava/lang/Object; L668 L678 168
    LOCALVARIABLE $i$f$cache\77\239 I L667 L680 167
    LOCALVARIABLE $this$cache\77 Landroidx/compose/runtime/Composer; L666 L680 150
    LOCALVARIABLE invalid\77 Z L666 L680 169
    LOCALVARIABLE $i$f$getDp\80\243 I L685 L686 150
    LOCALVARIABLE $this$dp\80 I L684 L686 149
    LOCALVARIABLE $i$f$getDp\81\249 I L692 L693 150
    LOCALVARIABLE $this$dp\81 I L691 L693 149
    LOCALVARIABLE $i$a$-cache-ChannelScreenKt$ChannelScreenUI$1$1$2$3$1$3\84\589\63 I L701 L702 155
    LOCALVARIABLE value\83 Ljava/lang/Object; L704 L706 156
    LOCALVARIABLE $i$a$-let-ComposerKt$cache$1\83\587\82 I L698 L707 170
    LOCALVARIABLE it\82 Ljava/lang/Object; L697 L707 168
    LOCALVARIABLE $i$f$cache\82\250 I L696 L709 167
    LOCALVARIABLE $this$cache\82 Landroidx/compose/runtime/Composer; L695 L709 150
    LOCALVARIABLE invalid\82 Z L695 L709 169
    LOCALVARIABLE $i$a$-Row-ChannelScreenKt$ChannelScreenUI$1$1$2$3$1\63\508\56 I L544 L713 148
    LOCALVARIABLE $this$ChannelScreenUI_u24lambda_u2427_u24lambda_u2426_u24lambda_u2425_u24lambda_u2424_u24lambda_u2423\63 Landroidx/compose/foundation/layout/RowScope; L543 L713 147
    LOCALVARIABLE $composer\63 Landroidx/compose/runtime/Composer; L543 L713 146
    LOCALVARIABLE $changed\63 I L543 L713 145
    LOCALVARIABLE $i$a$-Layout-RowKt$Row$1\62\532\58 I L541 L715 144
    LOCALVARIABLE $composer\62 Landroidx/compose/runtime/Composer; L540 L715 143
    LOCALVARIABLE $changed\62 I L540 L715 142
    LOCALVARIABLE $i$a$-ReusableComposeNode-LayoutKt$Layout$1\61\525\59 I L532 L538 141
    LOCALVARIABLE $this$Layout_u24lambda_u240\61 Landroidx/compose/runtime/Composer; L531 L538 140
    LOCALVARIABLE $i$f$ReusableComposeNode\60\515 I L521 L719 139
    LOCALVARIABLE factory\60 Lkotlin/jvm/functions/Function0; L520 L719 136
    LOCALVARIABLE $composer\60 Landroidx/compose/runtime/Composer; L520 L719 137
    LOCALVARIABLE $changed\60 I L520 L719 138
    LOCALVARIABLE $i$f$Layout\59\507 I L511 L722 132
    LOCALVARIABLE compositeKeyHash\59 I L514 L722 133
    LOCALVARIABLE localMap\59 Landroidx/compose/runtime/CompositionLocalMap; L516 L722 134
    LOCALVARIABLE materialized\59 Landroidx/compose/ui/Modifier; L518 L722 135
    LOCALVARIABLE modifier\59 Landroidx/compose/ui/Modifier; L510 L722 128
    LOCALVARIABLE measurePolicy\59 Landroidx/compose/ui/layout/MeasurePolicy; L510 L722 129
    LOCALVARIABLE $composer\59 Landroidx/compose/runtime/Composer; L510 L722 130
    LOCALVARIABLE $changed\59 I L510 L722 131
    LOCALVARIABLE $i$f$Row\58\198 I L503 L725 126
    LOCALVARIABLE measurePolicy\58 Landroidx/compose/ui/layout/MeasurePolicy; L507 L725 127
    LOCALVARIABLE modifier\58 Landroidx/compose/ui/Modifier; L502 L725 122
    LOCALVARIABLE horizontalArrangement\58 Landroidx/compose/foundation/layout/Arrangement$Horizontal; L506 L725 123
    LOCALVARIABLE verticalAlignment\58 Landroidx/compose/ui/Alignment$Vertical; L502 L725 124
    LOCALVARIABLE $changed\58 I L502 L725 125
    LOCALVARIABLE $i$a$-Box-ChannelScreenKt$ChannelScreenUI$1$1$2$3\56\475\30 I L487 L728 121
    LOCALVARIABLE $this$ChannelScreenUI_u24lambda_u2427_u24lambda_u2426_u24lambda_u2425_u24lambda_u2424\56 Landroidx/compose/foundation/layout/BoxScope; L486 L728 120
    LOCALVARIABLE $composer\56 Landroidx/compose/runtime/Composer; L486 L728 119
    LOCALVARIABLE $changed\56 I L486 L728 118
    LOCALVARIABLE $i$a$-Layout-BoxKt$Box$1\55\499\51 I L484 L730 117
    LOCALVARIABLE $composer\55 Landroidx/compose/runtime/Composer; L483 L730 116
    LOCALVARIABLE $changed\55 I L483 L730 115
    LOCALVARIABLE $i$a$-ReusableComposeNode-LayoutKt$Layout$1\54\492\52 I L475 L481 114
    LOCALVARIABLE $this$Layout_u24lambda_u240\54 Landroidx/compose/runtime/Composer; L474 L481 113
    LOCALVARIABLE $i$f$ReusableComposeNode\53\482 I L464 L734 112
    LOCALVARIABLE factory\53 Lkotlin/jvm/functions/Function0; L463 L734 109
    LOCALVARIABLE $composer\53 Landroidx/compose/runtime/Composer; L463 L734 110
    LOCALVARIABLE $changed\53 I L463 L734 111
    LOCALVARIABLE $i$f$Layout\52\474 I L454 L737 105
    LOCALVARIABLE compositeKeyHash\52 I L457 L737 106
    LOCALVARIABLE localMap\52 Landroidx/compose/runtime/CompositionLocalMap; L459 L737 107
    LOCALVARIABLE materialized\52 Landroidx/compose/ui/Modifier; L461 L737 108
    LOCALVARIABLE modifier\52 Landroidx/compose/ui/Modifier; L453 L737 101
    LOCALVARIABLE measurePolicy\52 Landroidx/compose/ui/layout/MeasurePolicy; L453 L737 102
    LOCALVARIABLE $composer\52 Landroidx/compose/runtime/Composer; L453 L737 103
    LOCALVARIABLE $changed\52 I L453 L737 104
    LOCALVARIABLE $i$f$Box\51\186 I L445 L740 97
    LOCALVARIABLE measurePolicy\51 Landroidx/compose/ui/layout/MeasurePolicy; L450 L740 100
    LOCALVARIABLE modifier\51 Landroidx/compose/ui/Modifier; L444 L740 98
    LOCALVARIABLE contentAlignment\51 Landroidx/compose/ui/Alignment; L448 L740 99
    LOCALVARIABLE propagateMinConstraints\51 Z L449 L740 95
    LOCALVARIABLE $changed\51 I L444 L740 96
    LOCALVARIABLE $i$a$-Column-ChannelScreenKt$ChannelScreenUI$1$1$2\30\361\18 I L248 L743 94
    LOCALVARIABLE $this$ChannelScreenUI_u24lambda_u2427_u24lambda_u2426_u24lambda_u2425\30 Landroidx/compose/foundation/layout/ColumnScope; L247 L743 93
    LOCALVARIABLE $composer\30 Landroidx/compose/runtime/Composer; L247 L743 92
    LOCALVARIABLE $changed\30 I L247 L743 91
    LOCALVARIABLE $i$a$-Layout-ColumnKt$Column$1\29\385\25 I L245 L745 90
    LOCALVARIABLE $composer\29 Landroidx/compose/runtime/Composer; L244 L745 89
    LOCALVARIABLE $changed\29 I L244 L745 88
    LOCALVARIABLE $i$a$-ReusableComposeNode-LayoutKt$Layout$1\28\378\26 I L236 L242 87
    LOCALVARIABLE $this$Layout_u24lambda_u240\28 Landroidx/compose/runtime/Composer; L235 L242 86
    LOCALVARIABLE $i$f$ReusableComposeNode\27\368 I L225 L749 85
    LOCALVARIABLE factory\27 Lkotlin/jvm/functions/Function0; L224 L749 82
    LOCALVARIABLE $composer\27 Landroidx/compose/runtime/Composer; L224 L749 83
    LOCALVARIABLE $changed\27 I L224 L749 84
    LOCALVARIABLE $i$f$Layout\26\360 I L215 L752 78
    LOCALVARIABLE compositeKeyHash\26 I L218 L752 79
    LOCALVARIABLE localMap\26 Landroidx/compose/runtime/CompositionLocalMap; L220 L752 80
    LOCALVARIABLE materialized\26 Landroidx/compose/ui/Modifier; L222 L752 81
    LOCALVARIABLE modifier\26 Landroidx/compose/ui/Modifier; L214 L752 72
    LOCALVARIABLE measurePolicy\26 Landroidx/compose/ui/layout/MeasurePolicy; L214 L752 75
    LOCALVARIABLE $composer\26 Landroidx/compose/runtime/Composer; L214 L752 76
    LOCALVARIABLE $changed\26 I L214 L752 77
    LOCALVARIABLE $i$f$Column\25\107 I L206 L755 67
    LOCALVARIABLE measurePolicy\25 Landroidx/compose/ui/layout/MeasurePolicy; L211 L755 68
    LOCALVARIABLE modifier\25 Landroidx/compose/ui/Modifier; L205 L755 74
    LOCALVARIABLE verticalArrangement\25 Landroidx/compose/foundation/layout/Arrangement$Vertical; L209 L755 64
    LOCALVARIABLE horizontalAlignment\25 Landroidx/compose/ui/Alignment$Horizontal; L210 L755 65
    LOCALVARIABLE $changed\25 I L205 L755 66
    LOCALVARIABLE $i$a$-Row-ChannelScreenKt$ChannelScreenUI$1$1\18\322\12 I L165 L758 63
    LOCALVARIABLE $this$ChannelScreenUI_u24lambda_u2427_u24lambda_u2426\18 Landroidx/compose/foundation/layout/RowScope; L164 L758 62
    LOCALVARIABLE $composer\18 Landroidx/compose/runtime/Composer; L164 L758 61
    LOCALVARIABLE $changed\18 I L164 L758 60
    LOCALVARIABLE $i$a$-Layout-RowKt$Row$1\17\346\13 I L162 L760 59
    LOCALVARIABLE $composer\17 Landroidx/compose/runtime/Composer; L161 L760 58
    LOCALVARIABLE $changed\17 I L161 L760 57
    LOCALVARIABLE $i$a$-ReusableComposeNode-LayoutKt$Layout$1\16\339\14 I L153 L159 56
    LOCALVARIABLE $this$Layout_u24lambda_u240\16 Landroidx/compose/runtime/Composer; L152 L159 55
    LOCALVARIABLE $i$f$ReusableComposeNode\15\329 I L142 L764 54
    LOCALVARIABLE factory\15 Lkotlin/jvm/functions/Function0; L141 L764 51
    LOCALVARIABLE $composer\15 Landroidx/compose/runtime/Composer; L141 L764 52
    LOCALVARIABLE $changed\15 I L141 L764 53
    LOCALVARIABLE $i$f$Layout\14\321 I L132 L767 47
    LOCALVARIABLE compositeKeyHash\14 I L135 L767 48
    LOCALVARIABLE localMap\14 Landroidx/compose/runtime/CompositionLocalMap; L137 L767 49
    LOCALVARIABLE materialized\14 Landroidx/compose/ui/Modifier; L139 L767 50
    LOCALVARIABLE modifier\14 Landroidx/compose/ui/Modifier; L131 L767 43
    LOCALVARIABLE measurePolicy\14 Landroidx/compose/ui/layout/MeasurePolicy; L131 L767 44
    LOCALVARIABLE $composer\14 Landroidx/compose/runtime/Composer; L131 L767 45
    LOCALVARIABLE $changed\14 I L131 L767 46
    LOCALVARIABLE $i$f$Row\13\96 I L123 L770 39
    LOCALVARIABLE measurePolicy\13 Landroidx/compose/ui/layout/MeasurePolicy; L128 L770 42
    LOCALVARIABLE modifier\13 Landroidx/compose/ui/Modifier; L122 L770 37
    LOCALVARIABLE horizontalArrangement\13 Landroidx/compose/foundation/layout/Arrangement$Horizontal; L126 L770 40
    LOCALVARIABLE verticalAlignment\13 Landroidx/compose/ui/Alignment$Vertical; L127 L770 41
    LOCALVARIABLE $changed\13 I L122 L770 38
    LOCALVARIABLE $i$a$-Box-ChannelScreenKt$ChannelScreenUI$1\12\290\0 I L104 L775 36
    LOCALVARIABLE $this$ChannelScreenUI_u24lambda_u2427\12 Landroidx/compose/foundation/layout/BoxScope; L103 L775 35
    LOCALVARIABLE $composer\12 Landroidx/compose/runtime/Composer; L103 L775 34
    LOCALVARIABLE $changed\12 I L103 L775 33
    LOCALVARIABLE $i$a$-Layout-BoxKt$Box$1\11\314\7 I L101 L777 32
    LOCALVARIABLE $composer\11 Landroidx/compose/runtime/Composer; L100 L777 31
    LOCALVARIABLE $changed\11 I L100 L777 30
    LOCALVARIABLE $i$a$-ReusableComposeNode-LayoutKt$Layout$1\10\307\8 I L92 L98 29
    LOCALVARIABLE $this$Layout_u24lambda_u240\10 Landroidx/compose/runtime/Composer; L91 L98 28
    LOCALVARIABLE $i$f$ReusableComposeNode\9\297 I L81 L781 27
    LOCALVARIABLE factory\9 Lkotlin/jvm/functions/Function0; L80 L781 24
    LOCALVARIABLE $composer\9 Landroidx/compose/runtime/Composer; L80 L781 25
    LOCALVARIABLE $changed\9 I L80 L781 26
    LOCALVARIABLE $i$f$Layout\8\289 I L71 L784 20
    LOCALVARIABLE compositeKeyHash\8 I L74 L784 21
    LOCALVARIABLE localMap\8 Landroidx/compose/runtime/CompositionLocalMap; L76 L784 22
    LOCALVARIABLE materialized\8 Landroidx/compose/ui/Modifier; L78 L784 23
    LOCALVARIABLE modifier\8 Landroidx/compose/ui/Modifier; L70 L784 16
    LOCALVARIABLE measurePolicy\8 Landroidx/compose/ui/layout/MeasurePolicy; L70 L784 17
    LOCALVARIABLE $composer\8 Landroidx/compose/runtime/Composer; L70 L784 18
    LOCALVARIABLE $changed\8 I L70 L784 19
    LOCALVARIABLE $i$f$Box\7\75 I L62 L787 14
    LOCALVARIABLE measurePolicy\7 Landroidx/compose/ui/layout/MeasurePolicy; L67 L787 15
    LOCALVARIABLE modifier\7 Landroidx/compose/ui/Modifier; L61 L787 10
    LOCALVARIABLE contentAlignment\7 Landroidx/compose/ui/Alignment; L65 L787 11
    LOCALVARIABLE propagateMinConstraints\7 Z L66 L787 12
    LOCALVARIABLE $changed\7 I L61 L787 13
    LOCALVARIABLE messages$delegate Landroidx/compose/runtime/MutableState; L40 L788 8
    LOCALVARIABLE text$delegate Landroidx/compose/runtime/MutableState; L60 L788 9
    LOCALVARIABLE $dirty I L1 L793 7
    LOCALVARIABLE servers Ljava/util/List; L0 L793 0
    LOCALVARIABLE selectedServer Ljava/lang/String; L0 L793 1
    LOCALVARIABLE onSelectServer Lkotlin/jvm/functions/Function1; L0 L793 2
    LOCALVARIABLE channelName Ljava/lang/String; L0 L793 3
    LOCALVARIABLE onBack Lkotlin/jvm/functions/Function0; L0 L793 4
    LOCALVARIABLE $composer Landroidx/compose/runtime/Composer; L0 L793 5
    LOCALVARIABLE $changed I L0 L793 6
    MAXSTACK = 116
    MAXLOCALS = 217

File is unknown
The root cause java.lang.OutOfMemoryError was thrown at: org.jetbrains.org.objectweb.asm.tree.analysis.Frame.<init>(Frame.java:78)
	at org.jetbrains.kotlin.codegen.TransformationMethodVisitor.visitEnd(TransformationMethodVisitor.kt:89)
	at org.jetbrains.org.objectweb.asm.MethodVisitor.visitEnd(MethodVisitor.java:783)
	at org.jetbrains.org.objectweb.asm.tree.MethodNode.accept(MethodNode.java:772)
	at org.jetbrains.kotlin.backend.jvm.codegen.ClassCodegen.generateMethod(ClassCodegen.kt:454)
	at org.jetbrains.kotlin.backend.jvm.codegen.ClassCodegen.generate(ClassCodegen.kt:169)
	at org.jetbrains.kotlin.backend.jvm.FileCodegen.lower(JvmPhases.kt:39)
	at org.jetbrains.kotlin.backend.common.phaser.PhaseFactoriesKt.createFilePhase$lambda$4(PhaseFactories.kt:71)
	at org.jetbrains.kotlin.backend.common.phaser.PhaseBuildersKt$createSimpleNamedCompilerPhase$1.phaseBody(PhaseBuilders.kt:69)
	at org.jetbrains.kotlin.backend.common.phaser.SimpleNamedCompilerPhase.phaseBody(CompilerPhase.kt:226)
	at org.jetbrains.kotlin.backend.common.phaser.AbstractNamedCompilerPhase.invoke(CompilerPhase.kt:113)
	at org.jetbrains.kotlin.backend.common.phaser.PerformByIrFilePhase.invokeSequential(performByIrFile.kt:52)
	at org.jetbrains.kotlin.backend.common.phaser.PerformByIrFilePhase.invoke(performByIrFile.kt:42)
	at org.jetbrains.kotlin.backend.common.phaser.PerformByIrFilePhase.invoke(performByIrFile.kt:28)
	at org.jetbrains.kotlin.backend.common.phaser.NamedCompilerPhase.phaseBody(CompilerPhase.kt:166)
	at org.jetbrains.kotlin.backend.common.phaser.AbstractNamedCompilerPhase.invoke(CompilerPhase.kt:113)
	at org.jetbrains.kotlin.backend.common.phaser.CompositePhase.invoke(PhaseBuilders.kt:27)
	at org.jetbrains.kotlin.backend.common.phaser.CompositePhase.invoke(PhaseBuilders.kt:14)
	at org.jetbrains.kotlin.backend.common.phaser.NamedCompilerPhase.phaseBody(CompilerPhase.kt:166)
	at org.jetbrains.kotlin.backend.common.phaser.AbstractNamedCompilerPhase.invoke(CompilerPhase.kt:113)
	at org.jetbrains.kotlin.backend.common.phaser.CompilerPhaseKt.invokeToplevel(CompilerPhase.kt:62)
	at org.jetbrains.kotlin.backend.jvm.JvmIrCodegenFactory.invokeCodegen(JvmIrCodegenFactory.kt:371)
	at org.jetbrains.kotlin.codegen.CodegenFactory.generateModule(CodegenFactory.kt:47)
	at org.jetbrains.kotlin.backend.jvm.JvmIrCodegenFactory.generateModuleInFrontendIRMode(JvmIrCodegenFactory.kt:433)
	at org.jetbrains.kotlin.cli.jvm.compiler.pipeline.JvmCompilerPipelineKt.generateCodeFromIr(jvmCompilerPipeline.kt:192)
	at org.jetbrains.kotlin.cli.jvm.compiler.pipeline.JvmCompilerPipelineKt.runBackend(jvmCompilerPipeline.kt:80)
	at org.jetbrains.kotlin.cli.jvm.compiler.pipeline.JvmCompilerPipelineLightTreeKt.compileModule(jvmCompilerPipelineLightTree.kt:264)
	at org.jetbrains.kotlin.cli.jvm.compiler.pipeline.JvmCompilerPipelineLightTreeKt.compileSingleModuleUsingFrontendIrAndLightTree(jvmCompilerPipelineLightTree.kt:231)
	at org.jetbrains.kotlin.cli.jvm.compiler.pipeline.JvmCompilerPipelineLightTreeKt.compileModulesUsingFrontendIrAndLightTree(jvmCompilerPipelineLightTree.kt:86)
	at org.jetbrains.kotlin.cli.jvm.K2JVMCompiler.doExecute(K2JVMCompiler.kt:146)
	at org.jetbrains.kotlin.cli.jvm.K2JVMCompiler.doExecute(K2JVMCompiler.kt:43)
	at org.jetbrains.kotlin.cli.common.CLICompiler.execImpl(CLICompiler.kt:102)
	at org.jetbrains.kotlin.cli.common.CLICompiler.exec(CLICompiler.kt:316)
	at org.jetbrains.kotlin.incremental.IncrementalJvmCompilerRunner.runCompiler(IncrementalJvmCompilerRunner.kt:464)
	at org.jetbrains.kotlin.incremental.IncrementalJvmCompilerRunner.runCompiler(IncrementalJvmCompilerRunner.kt:73)
	at org.jetbrains.kotlin.incremental.IncrementalCompilerRunner.doCompile(IncrementalCompilerRunner.kt:506)
	at org.jetbrains.kotlin.incremental.IncrementalCompilerRunner.compileImpl(IncrementalCompilerRunner.kt:423)
	at org.jetbrains.kotlin.incremental.IncrementalCompilerRunner.compileNonIncrementally(IncrementalCompilerRunner.kt:301)
	at org.jetbrains.kotlin.incremental.IncrementalCompilerRunner.compile(IncrementalCompilerRunner.kt:129)
	at org.jetbrains.kotlin.daemon.CompileServiceImplBase.execIncrementalCompiler(CompileServiceImpl.kt:683)
	at org.jetbrains.kotlin.daemon.CompileServiceImplBase.access$execIncrementalCompiler(CompileServiceImpl.kt:91)
	at org.jetbrains.kotlin.daemon.CompileServiceImpl.compile(CompileServiceImpl.kt:1811)
	at java.base/jdk.internal.reflect.NativeMethodAccessorImpl.invoke0(Native Method)
	at java.base/jdk.internal.reflect.NativeMethodAccessorImpl.invoke(NativeMethodAccessorImpl.java:77)
	at java.base/jdk.internal.reflect.DelegatingMethodAccessorImpl.invoke(DelegatingMethodAccessorImpl.java:43)
	at java.base/java.lang.reflect.Method.invoke(Method.java:568)
	at java.rmi/sun.rmi.server.UnicastServerRef.dispatch(UnicastServerRef.java:360)
	at java.rmi/sun.rmi.transport.Transport$1.run(Transport.java:200)
	at java.rmi/sun.rmi.transport.Transport$1.run(Transport.java:197)
	at java.base/java.security.AccessController.doPrivileged(AccessController.java:712)
	at java.rmi/sun.rmi.transport.Transport.serviceCall(Transport.java:196)
	at java.rmi/sun.rmi.transport.tcp.TCPTransport.handleMessages(TCPTransport.java:587)
	at java.rmi/sun.rmi.transport.tcp.TCPTransport$ConnectionHandler.run0(TCPTransport.java:828)
	at java.rmi/sun.rmi.transport.tcp.TCPTransport$ConnectionHandler.lambda$run$0(TCPTransport.java:705)
	at java.base/java.security.AccessController.doPrivileged(AccessController.java:399)
	at java.rmi/sun.rmi.transport.tcp.TCPTransport$ConnectionHandler.run(TCPTransport.java:704)
	at java.base/java.util.concurrent.ThreadPoolExecutor.runWorker(ThreadPoolExecutor.java:1136)
	at java.base/java.util.concurrent.ThreadPoolExecutor$Worker.run(ThreadPoolExecutor.java:635)
	at java.base/java.lang.Thread.run(Thread.java:842)
Caused by: java.lang.OutOfMemoryError: GC overhead limit exceeded
	at org.jetbrains.org.objectweb.asm.tree.analysis.Frame.<init>(Frame.java:78)
	at org.jetbrains.kotlin.codegen.optimization.fixStack.FixStackAnalyzer$FixStackFrame.<init>(FixStackAnalyzer.kt:98)
	at org.jetbrains.kotlin.codegen.optimization.fixStack.FixStackAnalyzer.analyzer$lambda$0(FixStackAnalyzer.kt:46)
	at org.jetbrains.kotlin.codegen.optimization.fixStack.FixStackAnalyzer$$Lambda$3472/0x00000150b9cee060.invoke(Unknown Source)
	at org.jetbrains.kotlin.codegen.optimization.common.FastAnalyzer.fastMergeControlFlowEdge(FastAnalyzer.kt:256)
	at org.jetbrains.kotlin.codegen.optimization.common.FastAnalyzer.mergeControlFlowEdge(FastAnalyzer.kt:214)
	at org.jetbrains.kotlin.codegen.optimization.common.FastAnalyzer.processControlFlowEdge(FastAnalyzer.kt:208)
	at org.jetbrains.kotlin.codegen.optimization.common.FastAnalyzer.processControlFlowEdge$default(FastAnalyzer.kt:206)
	at org.jetbrains.kotlin.codegen.optimization.common.FastAnalyzer.visitOpInsn(FastAnalyzer.kt:292)
	at org.jetbrains.kotlin.codegen.optimization.common.FastAnalyzer.visitMeaningfulInstruction(FastAnalyzer.kt:281)
	at org.jetbrains.kotlin.codegen.optimization.common.FastAnalyzer.analyzeInstruction(FastAnalyzer.kt:113)
	at org.jetbrains.kotlin.codegen.optimization.common.FastAnalyzer.analyzeMainLoop(FastAnalyzer.kt:74)
	at org.jetbrains.kotlin.codegen.optimization.common.FastAnalyzer.analyze(FastAnalyzer.kt:53)
	at org.jetbrains.kotlin.codegen.optimization.fixStack.FixStackAnalyzer.analyze(FixStackAnalyzer.kt:60)
	at org.jetbrains.kotlin.codegen.optimization.fixStack.FixStackMethodTransformer.analyzeAndTransformSaveRestoreStack(FixStackMethodTransformer.kt:68)
	at org.jetbrains.kotlin.codegen.optimization.fixStack.FixStackMethodTransformer.transform(FixStackMethodTransformer.kt:46)
	at org.jetbrains.kotlin.codegen.optimization.transformer.CompositeMethodTransformer.transform(CompositeMethodTransformer.kt:25)
	at org.jetbrains.kotlin.codegen.optimization.transformer.CompositeMethodTransformer.transform(CompositeMethodTransformer.kt:25)
	at org.jetbrains.kotlin.codegen.optimization.OptimizationMethodVisitor.performTransformations(OptimizationMethodVisitor.kt:70)
	at org.jetbrains.kotlin.codegen.TransformationMethodVisitor.visitEnd(TransformationMethodVisitor.kt:67)
	at org.jetbrains.org.objectweb.asm.MethodVisitor.visitEnd(MethodVisitor.java:783)
	at org.jetbrains.org.objectweb.asm.tree.MethodNode.accept(MethodNode.java:772)
	at org.jetbrains.kotlin.backend.jvm.codegen.ClassCodegen.generateMethod(ClassCodegen.kt:454)
	at org.jetbrains.kotlin.backend.jvm.codegen.ClassCodegen.generate(ClassCodegen.kt:169)
	at org.jetbrains.kotlin.backend.jvm.FileCodegen.lower(JvmPhases.kt:39)
	at org.jetbrains.kotlin.backend.common.phaser.PhaseFactoriesKt.createFilePhase$lambda$4(PhaseFactories.kt:71)
	at org.jetbrains.kotlin.backend.common.phaser.PhaseFactoriesKt$$Lambda$179/0x00000150b91245a0.invoke(Unknown Source)
	at org.jetbrains.kotlin.backend.common.phaser.PhaseBuildersKt$createSimpleNamedCompilerPhase$1.phaseBody(PhaseBuilders.kt:69)
	at org.jetbrains.kotlin.backend.common.phaser.SimpleNamedCompilerPhase.phaseBody(CompilerPhase.kt:226)
	at org.jetbrains.kotlin.backend.common.phaser.AbstractNamedCompilerPhase.invoke(CompilerPhase.kt:113)
	at org.jetbrains.kotlin.backend.common.phaser.PerformByIrFilePhase.invokeSequential(performByIrFile.kt:52)
	at org.jetbrains.kotlin.backend.common.phaser.PerformByIrFilePhase.invoke(performByIrFile.kt:42)


